Workbook

Sheet Resumen
A1: WACC base (USD)
A2: Empresa | B2: 2020 | C2: 2021 | D2: 2022 | E2: 2023 | F2: 2024 | G2: 2025
A3: SQM | B3: =WACC!T2 -> 0.062598894 | C3: =WACC!T3 -> 0.064604321 | D3: =WACC!T4 -> 0.10392311 | E3: =WACC!T5 -> 0.083746819 | F3: =WACC!T6 -> 0.084075924 | G3: =WACC!T7 -> 0.090137467
A4: CAP | B4: =WACC!T8 -> 0.067229455 | C4: =WACC!T9 -> 0.069953628 | D4: =WACC!T10 -> 0.10912119 | E4: =WACC!T11 -> 0.09379834 | F4: =WACC!T12 -> 0.086287972 | G4: =WACC!T13 -> 0.084780079
A5: Molymet | B5: =WACC!T14 -> 0.060345917 | C5: =WACC!T15 -> 0.065067397 | D5: =WACC!T16 -> 0.099555642 | E5: =WACC!T17 -> 0.097695006 | F5: =WACC!T18 -> 0.096808423 | G5: =WACC!T19 -> 0.10554636
A6: Enaex | B6: =WACC!T20 -> 0.057850767 | C6: =WACC!T21 -> 0.060743532 | D6: =WACC!T22 -> 0.095385453 | E6: =WACC!T23 -> 0.082949877 | F6: =WACC!T24 -> 0.088041492 | G6: =WACC!T25 -> 0.090049863
A7: Minera Valparaíso | B7: =WACC!T26 -> 0.044439907 | C7: =WACC!T27 -> 0.046591707 | D7: =WACC!T28 -> 0.06775417 | E7: =WACC!T29 -> 0.062570722 | F7: =WACC!T30 -> 0.062027255 | G7: =WACC!T31 -> 0.060449627
A9: Ke base (USD): tasa para descontar flujos del accionista, consistente con V = capitalización bursátil
A10: Empresa | B10: 2020 | C10: 2021 | D10: 2022 | E10: 2023 | F10: 2024 | G10: 2025
A11: SQM | B11: =WACC!S2 -> 0.068149021 | C11: =WACC!S3 -> 0.070705955 | D11: =WACC!S4 -> 0.11462954 | E11: =WACC!S5 -> 0.098491228 | F11: =WACC!S6 -> 0.10813071 | G11: =WACC!S7 -> 0.10295784
A12: CAP | B12: =WACC!S8 -> 0.062972617 | C12: =WACC!S9 -> 0.071247074 | D12: =WACC!S10 -> 0.12493588 | E12: =WACC!S11 -> 0.11183631 | F12: =WACC!S12 -> 0.11251082 | G12: =WACC!S13 -> 0.10656717
A13: Molymet | B13: =WACC!S14 -> 0.062031379 | C13: =WACC!S15 -> 0.094520531 | D13: =WACC!S16 -> 0.15521184 | E13: =WACC!S17 -> 0.14272626 | F13: =WACC!S18 -> 0.13429704 | G13: =WACC!S19 -> 0.12992925
A14: Enaex | B14: =WACC!S20 -> 0.066723206 | C14: =WACC!S21 -> 0.074317933 | D14: =WACC!S22 -> 0.12279432 | E14: =WACC!S23 -> 0.099207724 | F14: =WACC!S24 -> 0.10112336 | G14: =WACC!S25 -> 0.099439422
A15: Minera Valparaíso | B15: =WACC!S26 -> 0.044930676 | C15: =WACC!S27 -> 0.054143016 | D15: =WACC!S28 -> 0.090138994 | E15: =WACC!S29 -> 0.079421235 | F15: =WACC!S30 -> 0.082396942 | G15: =WACC!S31 -> 0.07965595
A17: WACC con industria alternativa (sensibilidad del beta)
A18: Empresa | B18: 2020 | C18: 2021 | D18: 2022 | E18: 2023 | F18: 2024 | G18: 2025
A19: SQM | B19: =WACC!X2 -> 0.057010676 | C19: =WACC!X3 -> 0.066724878 | D19: =WACC!X4 -> 0.10974965 | E19: =WACC!X5 -> 0.089806718 | F19: =WACC!X6 -> 0.092330713 | G19: =WACC!X7 -> 0.10118615
A20: CAP | B20: =WACC!X8 -> 0.066837931 | C20: =WACC!X9 -> 0.073744685 | D20: =WACC!X10 -> 0.11469665 | E20: =WACC!X11 -> 0.097812714 | F20: =WACC!X12 -> 0.096985187 | G20: =WACC!X13 -> 0.10221096
A21: Molymet | B21: =WACC!X14 -> 0.060738668 | C21: =WACC!X15 -> 0.061543301 | D21: =WACC!X16 -> 0.094291233 | E21: =WACC!X17 -> 0.093909651 | F21: =WACC!X18 -> 0.08618583 | G21: =WACC!X19 -> 0.087793499
A22: Enaex | B22: =WACC!X20 -> 0.062139361 | C22: =WACC!X21 -> 0.063605356 | D22: =WACC!X22 -> 0.097195684 | E22: =WACC!X23 -> 0.084419826 | F22: =WACC!X24 -> 0.08957829 | G22: =WACC!X25 -> 0.092401381
A23: Minera Valparaíso | B23: =WACC!X26 -> 0.031322716 | C23: =WACC!X27 -> 0.040346468 | D23: =WACC!X28 -> 0.060314963 | E23: =WACC!X29 -> 0.056683588 | F23: =WACC!X30 -> 0.057217936 | G23: =WACC!X31 -> 0.059182115
A25: Fórmulas en la hoja WACC. Supuestos y fuentes en Supuestos, Betas y Datos.

Sheet Supuestos
A1: Año | B1: Rf (T-Bond 10 años EE.UU.) | C1: ERP implícita (Damodaran) | D1: Riesgo país Chile (CRP) | E1: Rating Moody's Chile | F1: Fuente Rf y ERP | G1: Fuente CRP | I1: Tasa de impuesto (t) | J1: Valor
A2: 2020 | B2: 0.0093 | C2: 0.0472 | D2: 0.006815 | E2: A1 | F2: https://pages.stern.nyu.edu/~adamodar/pc/datasets/histimpl.xls | G2: https://pages.stern.nyu.edu/~adamodar/pc/archives/ctryprem20.xlsx | I2: Tasa legal Chile (régimen general) | J2: 0.27
A3: 2021 | B3: 0.0151 | C3: 0.0424 | D3: 0.006959 | E3: A1 | F3: https://pages.stern.nyu.edu/~adamodar/pc/datasets/histimpl.xls | G3: https://pages.stern.nyu.edu/~adamodar/pc/archives/ctryprem21.xlsx
A4: 2022 | B4: 0.0388 | C4: 0.0594 | D4: 0.014606 | E4: A2 | F4: https://pages.stern.nyu.edu/~adamodar/pc/datasets/histimpl.xls | G4: https://pages.stern.nyu.edu/~adamodar/pc/archives/ctryprem22.xlsx
A5: 2023 | B5: 0.0388 | C5: 0.046 | D5: 0.012376 | E5: A2 | F5: https://pages.stern.nyu.edu/~adamodar/pc/datasets/histimpl.xls | G5: https://pages.stern.nyu.edu/~adamodar/pc/archives/ctryprem23.xlsx
A6: 2024 | B6: 0.0458 | C6: 0.0433 | D6: 0.011294 | E6: A2 | F6: https://pages.stern.nyu.edu/~adamodar/pc/datasets/histimpl.xls | G6: https://pages.stern.nyu.edu/~adamodar/pc/archives/ctryprem24.xlsx
A7: 2025 | B7: 0.0418 | C7: 0.0423 | D7: 0.010955 | E7: A2 | F7: https://pages.stern.nyu.edu/~adamodar/pc/datasets/histimpl.xls | G7: https://pages.stern.nyu.edu/~adamodar/pc/datasets/ctryprem.xlsx
A10: Notas
A11: Rf y ERP: columnas "T.Bond Rate" e "Implied ERP (FCFE)" de histimpl.xls, valor al cierre de cada año.
A12: CRP: columna "Country Risk Premium" (basada en rating) de cada archivo anual ctryprem; cada archivo se publica el 1 de enero siguiente y refleja el cierre del año.
A13: Control: la ERP madura de cada ctryprem (Total ERP − CRP) coincide con la ERP implícita de histimpl para ese año.
A14: No se usa "Rf ajustada" por default spread de EE.UU.: se usa el rendimiento del T-Bond tal cual.
A15: Todas las empresas reportan en USD, así que Ke y WACC son tasas en USD (sin ajuste por devaluación del peso).

Sheet Betas
A1: Industria (Damodaran, mercados emergentes) | B1: 2020 | C1: 2021 | D1: 2022 | E1: 2023 | F1: 2024 | G1: 2025 | H1: Fuente
A2: Chemical (Basic) | B2: 0.8795 | C2: 0.9509 | D2: 0.9065 | E2: 0.8282 | F2: 0.8458 | G2: 0.969 | H2: Unlevered beta, hoja "Industry Averages" de betaemerg (un archivo por año, ver Supuestos)
A3: Chemical (Specialty) | B3: 0.9764 | C3: 1.0241 | D3: 0.9395 | E3: 0.8626 | F3: 0.8835 | G3: 1.0271 | H3: Unlevered beta, hoja "Industry Averages" de betaemerg (un archivo por año, ver Supuestos)
A4: Metals & Mining | B4: 0.853 | C4: 1.0761 | D4: 1.0408 | E4: 1.0022 | F4: 1.0918 | G4: 1.3013 | H4: Unlevered beta, hoja "Industry Averages" de betaemerg (un archivo por año, ver Supuestos)
A5: Steel | B5: 0.8617 | C5: 0.9816 | D5: 0.9393 | E5: 0.9048 | F5: 0.8113 | G5: 0.8371 | H5: Unlevered beta, hoja "Industry Averages" de betaemerg (un archivo por año, ver Supuestos)
A6: Power | B6: 0.487 | C6: 0.5177 | D6: 0.416 | E6: 0.4218 | F6: 0.4047 | G6: 0.4331 | H6: Unlevered beta, hoja "Industry Averages" de betaemerg (un archivo por año, ver Supuestos)
A7: Investments & Asset Management | B7: 0.1883 | C7: 0.3532 | D7: 0.2756 | E7: 0.279 | F7: 0.281 | G7: 0.3996 | H7: Unlevered beta, hoja "Industry Averages" de betaemerg (un archivo por año, ver Supuestos)

Sheet Datos
A1: Empresa | B1: Año | C1: Acciones en circulación (serie única o A) | D1: Precio cierre CLP (serie única o A) | E1: Acciones serie B | F1: Precio cierre CLP serie B | G1: Dólar observado (CLP/USD) | H1: Deuda financiera D (MUS$) | I1: Costos financieros (MUS$) | J1: Patrimonio total (MUS$) | K1: Patrimonio controladora (MUS$) | L1: Industria base | M1: Industria alternativa | N1: Fuentes (archivo, página del PDF)
A2: SQM | B2: 2020 | C2: 142819552 | D2: 25246 | E2: 120376972 | F2: 34074.91 | G2: 711.24 | H2: 1922865 | I2: 82199 | J2: 2162578 | K2: 2123085 | L2: Chemical (Specialty) | M2: Metals & Mining | N2: prestamos_que_devengan_intereses_total: Estados_financieros_sqm_20_21.pdf p.93 | costos_financieros: Estados_financieros_sqm_20_21.pdf p.11 | patrimonio_total: Estados_financieros_sqm_20_21.pdf p.10 | patrimonio_atribuible_controladora: Estados_financieros_sqm_20_21.pdf p.10
A3: SQM | B3: 2021 | C3: 142818904 | D3: 48600 | E3: 142818904 | F3: 43489 | G3: 850.25 | H3: 2555511 | I3: 84626 | J3: 3215971 | K3: 3181520 | L3: Chemical (Specialty) | M3: Metals & Mining | N3: prestamos_que_devengan_intereses_total: Estados_financieros_sqm_20_21.pdf p.93 | costos_financieros: Estados_financieros_sqm_20_21.pdf p.11 | patrimonio_total: Estados_financieros_sqm_20_21.pdf p.10 | patrimonio_atribuible_controladora: Estados_financieros_sqm_20_21.pdf p.10
A4: SQM | B4: 2022 | C4: 142818904 | D4: 60121 | E4: 142818904 | F4: 68600 | G4: 859.51 | H4: 2848875 | I4: 86651 | J4: 4932001 | K4: 4896632 | L4: Chemical (Specialty) | M4: Metals & Mining | N4: prestamos_que_devengan_intereses_total: Estados_financieros_sqm_22_23.pdf p.90 | costos_financieros: Estados_financieros_sqm_22_23.pdf p.12 | patrimonio_total: Estados_financieros_sqm_22_23.pdf p.11 | patrimonio_atribuible_controladora: Estados_financieros_sqm_22_23.pdf p.11
A5: SQM | B5: 2023 | C5: 142818904 | D5: 50892 | E5: 142818904 | F5: 52650 | G5: 884.59 | H5: 4416264 | I5: 138402 | J5: 5566905 | K5: 5530675 | L5: Chemical (Specialty) | M5: Metals & Mining | N5: prestamos_que_devengan_intereses_total: Estados_financieros_sqm_22_23.pdf p.90 | costos_financieros: Estados_financieros_sqm_22_23.pdf p.12 | patrimonio_total: Estados_financieros_sqm_22_23.pdf p.11 | patrimonio_atribuible_controladora: Estados_financieros_sqm_22_23.pdf p.11
A6: SQM | B6: 2024 | C6: 142818904 | D6: 35009 | E6: 142818904 | F6: 36600 | G6: 992.12 | H6: 4734876 | I6: 197544 | J6: 5198067 | K6: 5160819 | L6: Chemical (Specialty) | M6: Metals & Mining | N6: prestamos_que_devengan_intereses_total: Estados_financieros_sqm_24_25.pdf p.102 | costos_financieros: Estados_financieros_sqm_24_25.pdf p.19 | patrimonio_total: Estados_financieros_sqm_24_25.pdf p.18 | patrimonio_atribuible_controladora: Estados_financieros_sqm_24_25.pdf p.18
A7: SQM | B7: 2025 | C7: 142818904 | D7: 60543 | E7: 142818904 | F7: 63800 | G7: 911.18 | H7: 4655235 | I7: 192672 | J7: 8053879 | K7: 5691262 | L7: Chemical (Specialty) | M7: Metals & Mining | N7: prestamos_que_devengan_intereses_total: Estados_financieros_sqm_24_25.pdf p.102 | costos_financieros: Estados_financieros_sqm_24_25.pdf p.19 | patrimonio_total: Estados_financieros_sqm_24_25.pdf p.18 | patrimonio_atribuible_controladora: Estados_financieros_sqm_24_25.pdf p.18
A8: CAP | B8: 2020 | C8: 149448112 | D8: 9545 | E8: 0 | F8: 0 | G8: 711.24 | H8: 710115 | I8: 85275 | J8: 3463491 | K8: 2060460 | L8: Steel | M8: Metals & Mining | N8: prestamos_que_devengan_intereses_total: Estados_financieros_(PDF)_CAP_20_21.pdf p.91 | costos_financieros: Estados_financieros_(PDF)_CAP_20_21.pdf p.6 | patrimonio_total: Estados_financieros_(PDF)_CAP_20_21.pdf p.5 | patrimonio_atribuible_controladora: Estados_financieros_(PDF)_CAP_20_21.pdf p.5
A9: CAP | B9: 2021 | C9: 149448112 | D9: 8300 | E9: 0 | F9: 0 | G9: 850.25 | H9: 718275 | I9: 63359 | J9: 3667322 | K9: 2242713 | L9: Steel | M9: Metals & Mining | N9: prestamos_que_devengan_intereses_total: Estados_financieros_(PDF)_CAP_20_21.pdf p.91 | costos_financieros: Estados_financieros_(PDF)_CAP_20_21.pdf p.6 | patrimonio_total: Estados_financieros_(PDF)_CAP_20_21.pdf p.5 | patrimonio_atribuible_controladora: Estados_financieros_(PDF)_CAP_20_21.pdf p.5
A10: CAP | B10: 2022 | C10: 149448112 | D10: 6950 | E10: 0 | F10: 0 | G10: 859.51 | H10: 1009542 | I10: 80694 | J10: 3681990 | K10: 2277312 | L10: Steel | M10: Metals & Mining | N10: prestamos_que_devengan_intereses_total: Estados_financieros_(PDF)_22_23.pdf p.89 | costos_financieros: Estados_financieros_(PDF)_22_23.pdf p.7 | patrimonio_total: Estados_financieros_(PDF)_22_23.pdf p.6 | patrimonio_atribuible_controladora: Estados_financieros_(PDF)_22_23.pdf p.6
A11: CAP | B11: 2023 | C11: 149448112 | D11: 7200 | E11: 0 | F11: 0 | G11: 884.59 | H11: 1636398 | I11: 117823 | J11: 3661112 | K11: 2266167 | L11: Steel | M11: Metals & Mining | N11: prestamos_que_devengan_intereses_total: Estados_financieros_(PDF)_22_23.pdf p.89 | costos_financieros: Estados_financieros_(PDF)_22_23.pdf p.7 | patrimonio_total: Estados_financieros_(PDF)_22_23.pdf p.6 | patrimonio_atribuible_controladora: Estados_financieros_(PDF)_22_23.pdf p.6
A12: CAP | B12: 2024 | C12: 149448112 | D12: 5260 | E12: 0 | F12: 0 | G12: 992.12 | H12: 1709061 | I12: 121768 | J12: 3185971 | K12: 1817979 | L12: Steel | M12: Metals & Mining | N12: prestamos_que_devengan_intereses_total: Estados_financieros_(PDF)_24_25.pdf p.101 | costos_financieros: Estados_financieros_(PDF)_24_25.pdf p.9 | patrimonio_total: Estados_financieros_(PDF)_24_25.pdf p.8 | patrimonio_atribuible_controladora: Estados_financieros_(PDF)_24_25.pdf p.8
A13: CAP | B13: 2025 | C13: 149448112 | D13: 7420 | E13: 0 | F13: 0 | G13: 911.18 | H13: 1780319 | I13: 129484 | J13: 3017741 | K13: 1734086 | L13: Steel | M13: Metals & Mining | N13: prestamos_que_devengan_intereses_total: Estados_financieros_(PDF)_24_25.pdf p.101 | costos_financieros: Estados_financieros_(PDF)_24_25.pdf p.9 | patrimonio_total: Estados_financieros_(PDF)_24_25.pdf p.8 | patrimonio_atribuible_controladora: Estados_financieros_(PDF)_24_25.pdf p.8
... A31: Minera Valparaíso | B31: 2025 | C31: 125000000 | D31: 14289 | E31: 0 | F31: 0 | G31: 911.18 | H31: 2635839 | I31: 104155 | J31: 6354015 | K31: 4206143 | L31: Power | M31: Investments & Asset Management | N31: prestamos_que_devengan_intereses_total: Estados_financieros_mineraval_24_25.pdf p.109 | costos_financieros: Estados_financieros_mineraval_24_25.pdf p.14 | patrimonio_total: Estados_financieros_mineraval_24_25.pdf p.13 | patrimonio_atribuible_controladora: Estados_financieros_mineraval_24_25.pdf p.13
A33: Precios: Yahoo Finance (Bolsa de Santiago), último cierre de cada año. Dólar: mindicador.cl (Banco Central de Chile). Datos contables: estados financieros consolidados auditados de este repositorio; detalle línea por línea en wacc/data/<empresa>.json.

Sheet WACC
A1: Empresa | B1: Año | C1: Capitalización bursátil (MUS$) | D1: No controladoras libro (MUS$) | E1: E = cap. + no contr. | F1: D deuda financiera | G1: Wd = D/(D+E) | H1: We = E/(D+E) | I1: D/E | J1: Deuda promedio | K1: Kd bruto | L1: t | M1: Kd neto | N1: Rf | O1: ERP | P1: CRP Chile | Q1: βU base | R1: βL base | S1: Ke base (USD) | T1: WACC base (USD) | U1: βU alt | V1: βL alt | W1: Ke alt | X1: WACC alt
A2: =Datos!A2 -> SQM | B2: =Datos!B2 -> 2020 | C2: =(Datos!C2*Datos!D2+Datos!E2*Datos!F2)/Datos!G2/1000 -> 10836647 | D2: =Datos!J2-Datos!K2 -> 39493 | E2: =C2+D2 -> 10876140 | F2: =Datos!H2 -> 1922865 | G2: =F2/(E2+F2) -> 0.15023551 | H2: =E2/(E2+F2) -> 0.84976449 | I2: =F2/E2 -> 0.17679664 | J2: =F2 -> 1922865 | K2: =Datos!I2/J2 -> 0.042748191 | L2: =Supuestos!$J$2 -> 0.27 | M2: =K2*(1-L2) -> 0.031206179 | N2: =INDEX(Supuestos!$B$2:$B$7,MATCH(B2,Supuestos!$A$2:$A$7,0)) -> 0.0093 | O2: =INDEX(Supuestos!$C$2:$C$7,MATCH(B2,Supuestos!$A$2:$A$7,0)) -> 0.0472 | P2: =INDEX(Supuestos!$D$2:$D$7,MATCH(B2,Supuestos!$A$2:$A$7,0)) -> 0.006815 | Q2: =INDEX(Betas!$B$2:$G$7,MATCH(Datos!L2,Betas!$A$2:$A$7,0),MATCH(B2,Betas!$B$1:$G$1,0)) -> 0.9764 | R2: =Q2*(1+(1-L2)*I2) -> 1.1024157 | S2: =N2+R2*O2+P2 -> 0.068149021 | T2: =H2*S2+G2*M2 -> 0.062598894 | U2: =INDEX(Betas!$B$2:$G$7,MATCH(Datos!M2,Betas!$A$2:$A$7,0),MATCH(B2,Betas!$B$1:$G$1,0)) -> 0.853 | V2: =U2*(1+(1-L2)*I2) -> 0.9630895 | W2: =N2+V2*O2+P2 -> 0.061572824 | X2: =H2*W2+G2*M2 -> 0.057010676
A3: =Datos!A3 -> SQM | B3: =Datos!B3 -> 2021 | C3: =(Datos!C3*Datos!D3+Datos!E3*Datos!F3)/Datos!G3/1000 -> 15468451 | D3: =Datos!J3-Datos!K3 -> 34451 | E3: =C3+D3 -> 15502902 | F3: =Datos!H3 -> 2555511 | G3: =F3/(E3+F3) -> 0.1415136 | H3: =E3/(E3+F3) -> 0.8584864 | I3: =F3/E3 -> 0.16484082 | J3: =(F3+F2)/2 -> 2239188 | K3: =Datos!I3/J3 -> 0.037793164 | L3: =Supuestos!$J$2 -> 0.27 | M3: =K3*(1-L3) -> 0.02758901 | N3: =INDEX(Supuestos!$B$2:$B$7,MATCH(B3,Supuestos!$A$2:$A$7,0)) -> 0.0151 | O3: =INDEX(Supuestos!$C$2:$C$7,MATCH(B3,Supuestos!$A$2:$A$7,0)) -> 0.0424 | P3: =INDEX(Supuestos!$D$2:$D$7,MATCH(B3,Supuestos!$A$2:$A$7,0)) -> 0.006959 | Q3: =INDEX(Betas!$B$2:$G$7,MATCH(Datos!L3,Betas!$A$2:$A$7,0),MATCH(B3,Betas!$B$1:$G$1,0)) -> 1.0241 | R3: =Q3*(1+(1-L3)*I3) -> 1.1473338 | S3: =N3+R3*O3+P3 -> 0.070705955 | T3: =H3*S3+G3*M3 -> 0.064604321 | U3: =INDEX(Betas!$B$2:$G$7,MATCH(Datos!M3,Betas!$A$2:$A$7,0),MATCH(B3,Betas!$B$1:$G$1,0)) -> 1.0761 | V3: =U3*(1+(1-L3)*I3) -> 1.2055912 | W3: =N3+V3*O3+P3 -> 0.073176067 | X3: =H3*W3+G3*M3 -> 0.066724878
A4: =Datos!A4 -> SQM | B4: =Datos!B4 -> 2022 | C4: =(Datos!C4*Datos!D4+Datos!E4*Datos!F4)/Datos!G4/1000 -> 21388689 | D4: =Datos!J4-Datos!K4 -> 35369 | E4: =C4+D4 -> 21424058 | F4: =Datos!H4 -> 2848875 | G4: =F4/(E4+F4) -> 0.11736839 | H4: =E4/(E4+F4) -> 0.88263161 | I4: =F4/E4 -> 0.13297551 | J4: =(F4+F3)/2 -> 2702193 | K4: =Datos!I4/J4 -> 0.032066917 | L4: =Supuestos!$J$2 -> 0.27 | M4: =K4*(1-L4) -> 0.02340885 | N4: =INDEX(Supuestos!$B$2:$B$7,MATCH(B4,Supuestos!$A$2:$A$7,0)) -> 0.0388 | O4: =INDEX(Supuestos!$C$2:$C$7,MATCH(B4,Supuestos!$A$2:$A$7,0)) -> 0.0594 | P4: =INDEX(Supuestos!$D$2:$D$7,MATCH(B4,Supuestos!$A$2:$A$7,0)) -> 0.014606 | Q4: =INDEX(Betas!$B$2:$G$7,MATCH(Datos!L4,Betas!$A$2:$A$7,0),MATCH(B4,Betas!$B$1:$G$1,0)) -> 0.9395 | R4: =Q4*(1+(1-L4)*I4) -> 1.0306993 | S4: =N4+R4*O4+P4 -> 0.11462954 | T4: =H4*S4+G4*M4 -> 0.10392311 | U4: =INDEX(Betas!$B$2:$G$7,MATCH(Datos!M4,Betas!$A$2:$A$7,0),MATCH(B4,Betas!$B$1:$G$1,0)) -> 1.0408 | V4: =U4*(1+(1-L4)*I4) -> 1.1418327 | W4: =N4+V4*O4+P4 -> 0.12123086 | X4: =H4*W4+G4*M4 -> 0.10974965
A5: =Datos!A5 -> SQM | B5: =Datos!B5 -> 2023 | C5: =(Datos!C5*Datos!D5+Datos!E5*Datos!F5)/Datos!G5/1000 -> 16717072 | D5: =Datos!J5-Datos!K5 -> 36230 | E5: =C5+D5 -> 16753302 | F5: =Datos!H5 -> 4416264 | G5: =F5/(E5+F5) -> 0.20861382 | H5: =E5/(E5+F5) -> 0.79138618 | I5: =F5/E5 -> 0.26360558 | J5: =(F5+F4)/2 -> 3632569.5 | K5: =Datos!I5/J5 -> 0.038100303 | L5: =Supuestos!$J$2 -> 0.27 | M5: =K5*(1-L5) -> 0.027813221 | N5: =INDEX(Supuestos!$B$2:$B$7,MATCH(B5,Supuestos!$A$2:$A$7,0)) -> 0.0388 | O5: =INDEX(Supuestos!$C$2:$C$7,MATCH(B5,Supuestos!$A$2:$A$7,0)) -> 0.046 | P5: =INDEX(Supuestos!$D$2:$D$7,MATCH(B5,Supuestos!$A$2:$A$7,0)) -> 0.012376 | Q5: =INDEX(Betas!$B$2:$G$7,MATCH(Datos!L5,Betas!$A$2:$A$7,0),MATCH(B5,Betas!$B$1:$G$1,0)) -> 0.8626 | R5: =Q5*(1+(1-L5)*I5) -> 1.0285919 | S5: =N5+R5*O5+P5 -> 0.098491228 | T5: =H5*S5+G5*M5 -> 0.083746819 | U5: =INDEX(Betas!$B$2:$G$7,MATCH(Datos!M5,Betas!$A$2:$A$7,0),MATCH(B5,Betas!$B$1:$G$1,0)) -> 1.0022 | V5: =U5*(1+(1-L5)*I5) -> 1.1950554 | W5: =N5+V5*O5+P5 -> 0.10614855 | X5: =H5*W5+G5*M5 -> 0.089806718
A6: =Datos!A6 -> SQM | B6: =Datos!B6 -> 2024 | C6: =(Datos!C6*Datos!D6+Datos!E6*Datos!F6)/Datos!G6/1000 -> 10308349 | D6: =Datos!J6-Datos!K6 -> 37248 | E6: =C6+D6 -> 10345597 | F6: =Datos!H6 -> 4734876 | G6: =F6/(E6+F6) -> 0.31397398 | H6: =E6/(E6+F6) -> 0.68602602 | I6: =F6/E6 -> 0.45767065 | J6: =(F6+F5)/2 -> 4575570 | K6: =Datos!I6/J6 -> 0.043173637 | L6: =Supuestos!$J$2 -> 0.27 | M6: =K6*(1-L6) -> 0.031516755 | N6: =INDEX(Supuestos!$B$2:$B$7,MATCH(B6,Supuestos!$A$2:$A$7,0)) -> 0.0458 | O6: =INDEX(Supuestos!$C$2:$C$7,MATCH(B6,Supuestos!$A$2:$A$7,0)) -> 0.0433 | P6: =INDEX(Supuestos!$D$2:$D$7,MATCH(B6,Supuestos!$A$2:$A$7,0)) -> 0.011294 | Q6: =INDEX(Betas!$B$2:$G$7,MATCH(Datos!L6,Betas!$A$2:$A$7,0),MATCH(B6,Betas!$B$1:$G$1,0)) -> 0.8835 | R6: =Q6*(1+(1-L6)*I6) -> 1.178677 | S6: =N6+R6*O6+P6 -> 0.10813071 | T6: =H6*S6+G6*M6 -> 0.084075924 | U6: =INDEX(Betas!$B$2:$G$7,MATCH(Datos!M6,Betas!$A$2:$A$7,0),MATCH(B6,Betas!$B$1:$G$1,0)) -> 1.0918 | V6: =U6*(1+(1-L6)*I6) -> 1.4565699 | W6: =N6+V6*O6+P6 -> 0.12016348 | X6: =H6*W6+G6*M6 -> 0.092330713
A7: =Datos!A7 -> SQM | B7: =Datos!B7 -> 2025 | C7: =(Datos!C7*Datos!D7+Datos!E7*Datos!F7)/Datos!G7/1000 -> 19489597 | D7: =Datos!J7-Datos!K7 -> 2362617 | E7: =C7+D7 -> 21852214 | F7: =Datos!H7 -> 4655235 | G7: =F7/(E7+F7) -> 0.17561988 | H7: =E7/(E7+F7) -> 0.82438012 | I7: =F7/E7 -> 0.21303265 | J7: =(F7+F6)/2 -> 4695055.5 | K7: =Datos!I7/J7 -> 0.041037215 | L7: =Supuestos!$J$2 -> 0.27 | M7: =K7*(1-L7) -> 0.029957167 | N7: =INDEX(Supuestos!$B$2:$B$7,MATCH(B7,Supuestos!$A$2:$A$7,0)) -> 0.0418 | O7: =INDEX(Supuestos!$C$2:$C$7,MATCH(B7,Supuestos!$A$2:$A$7,0)) -> 0.0423 | P7: =INDEX(Supuestos!$D$2:$D$7,MATCH(B7,Supuestos!$A$2:$A$7,0)) -> 0.010955 | Q7: =INDEX(Betas!$B$2:$G$7,MATCH(Datos!L7,Betas!$A$2:$A$7,0),MATCH(B7,Betas!$B$1:$G$1,0)) -> 1.0271 | R7: =Q7*(1+(1-L7)*I7) -> 1.1868283 | S7: =N7+R7*O7+P7 -> 0.10295784 | T7: =H7*S7+G7*M7 -> 0.090137467 | U7: =INDEX(Betas!$B$2:$G$7,MATCH(Datos!M7,Betas!$A$2:$A$7,0),MATCH(B7,Betas!$B$1:$G$1,0)) -> 1.3013 | V7: =U7*(1+(1-L7)*I7) -> 1.5036702 | W7: =N7+V7*O7+P7 -> 0.11636025 | X7: =H7*W7+G7*M7 -> 0.10118615
A8: =Datos!A8 -> CAP | B8: =Datos!B8 -> 2020 | C8: =(Datos!C8*Datos!D8+Datos!E8*Datos!F8)/Datos!G8/1000 -> 2005627.1 | D8: =Datos!J8-Datos!K8 -> 1403031 | E8: =C8+D8 -> 3408658.1 | F8: =Datos!H8 -> 710115 | G8: =F8/(E8+F8) -> 0.17240935 | H8: =E8/(E8+F8) -> 0.82759065 | I8: =F8/E8 -> 0.20832685 | J8: =F8 -> 710115 | K8: =Datos!I8/J8 -> 0.12008618 | L8: =Supuestos!$J$2 -> 0.27 | M8: =K8*(1-L8) -> 0.087662914 | N8: =INDEX(Supuestos!$B$2:$B$7,MATCH(B8,Supuestos!$A$2:$A$7,0)) -> 0.0093 | O8: =INDEX(Supuestos!$C$2:$C$7,MATCH(B8,Supuestos!$A$2:$A$7,0)) -> 0.0472 | P8: =INDEX(Supuestos!$D$2:$D$7,MATCH(B8,Supuestos!$A$2:$A$7,0)) -> 0.006815 | Q8: =INDEX(Betas!$B$2:$G$7,MATCH(Datos!L8,Betas!$A$2:$A$7,0),MATCH(B8,Betas!$B$1:$G$1,0)) -> 0.8617 | R8: =Q8*(1+(1-L8)*I8) -> 0.99274613 | S8: =N8+R8*O8+P8 -> 0.062972617 | T8: =H8*S8+G8*M8 -> 0.067229455 | U8: =INDEX(Betas!$B$2:$G$7,MATCH(Datos!M8,Betas!$A$2:$A$7,0),MATCH(B8,Betas!$B$1:$G$1,0)) -> 0.853 | V8: =U8*(1+(1-L8)*I8) -> 0.98272304 | W8: =N8+V8*O8+P8 -> 0.062499528 | X8: =H8*W8+G8*M8 -> 0.066837931
A9: =Datos!A9 -> CAP | B9: =Datos!B9 -> 2021 | C9: =(Datos!C9*Datos!D9+Datos!E9*Datos!F9)/Datos!G9/1000 -> 1458887.8 | D9: =Datos!J9-Datos!K9 -> 1424609 | E9: =C9+D9 -> 2883496.8 | F9: =Datos!H9 -> 718275 | G9: =F9/(E9+F9) -> 0.19942269 | H9: =E9/(E9+F9) -> 0.80057731 | I9: =F9/E9 -> 0.2490986 | J9: =(F9+F8)/2 -> 714195 | K9: =Datos!I9/J9 -> 0.088713867 | L9: =Supuestos!$J$2 -> 0.27 | M9: =K9*(1-L9) -> 0.064761123 | N9: =INDEX(Supuestos!$B$2:$B$7,MATCH(B9,Supuestos!$A$2:$A$7,0)) -> 0.0151 | O9: =INDEX(Supuestos!$C$2:$C$7,MATCH(B9,Supuestos!$A$2:$A$7,0)) -> 0.0424 | P9: =INDEX(Supuestos!$D$2:$D$7,MATCH(B9,Supuestos!$A$2:$A$7,0)) -> 0.006959 | Q9: =INDEX(Betas!$B$2:$G$7,MATCH(Datos!L9,Betas!$A$2:$A$7,0),MATCH(B9,Betas!$B$1:$G$1,0)) -> 0.9816 | R9: =Q9*(1+(1-L9)*I9) -> 1.1600961 | S9: =N9+R9*O9+P9 -> 0.071247074 | T9: =H9*S9+G9*M9 -> 0.069953628 | U9: =INDEX(Betas!$B$2:$G$7,MATCH(Datos!M9,Betas!$A$2:$A$7,0),MATCH(B9,Betas!$B$1:$G$1,0)) -> 1.0761 | V9: =U9*(1+(1-L9)*I9) -> 1.2717801 | W9: =N9+V9*O9+P9 -> 0.075982478 | X9: =H9*W9+G9*M9 -> 0.073744685
A10: =Datos!A10 -> CAP | B10: =Datos!B10 -> 2022 | C10: =(Datos!C10*Datos!D10+Datos!E10*Datos!F10)/Datos!G10/1000 -> 1208437.8 | D10: =Datos!J10-Datos!K10 -> 1404678 | E10: =C10+D10 -> 2613115.8 | F10: =Datos!H10 -> 1009542 | G10: =F10/(E10+F10) -> 0.2786744 | H10: =E10/(E10+F10) -> 0.7213256 | I10: =F10/E10 -> 0.38633649 | J10: =(F10+F9)/2 -> 863908.5 | K10: =Datos!I10/J10 -> 0.093405725 | L10: =Supuestos!$J$2 -> 0.27 | M10: =K10*(1-L10) -> 0.068186179 | N10: =INDEX(Supuestos!$B$2:$B$7,MATCH(B10,Supuestos!$A$2:$A$7,0)) -> 0.0388 | O10: =INDEX(Supuestos!$C$2:$C$7,MATCH(B10,Supuestos!$A$2:$A$7,0)) -> 0.0594 | P10: =INDEX(Supuestos!$D$2:$D$7,MATCH(B10,Supuestos!$A$2:$A$7,0)) -> 0.014606 | Q10: =INDEX(Betas!$B$2:$G$7,MATCH(Datos!L10,Betas!$A$2:$A$7,0),MATCH(B10,Betas!$B$1:$G$1,0)) -> 0.9393 | R10: =Q10*(1+(1-L10)*I10) -> 1.2042067 | S10: =N10+R10*O10+P10 -> 0.12493588 | T10: =H10*S10+G10*M10 -> 0.10912119 | U10: =INDEX(Betas!$B$2:$G$7,MATCH(Datos!M10,Betas!$A$2:$A$7,0),MATCH(B10,Betas!$B$1:$G$1,0)) -> 1.0408 | V10: =U10*(1+(1-L10)*I10) -> 1.3343323 | W10: =N10+V10*O10+P10 -> 0.13266534 | X10: =H10*W10+G10*M10 -> 0.11469665
A11: =Datos!A11 -> CAP | B11: =Datos!B11 -> 2023 | C11: =(Datos!C11*Datos!D11+Datos!E11*Datos!F11)/Datos!G11/1000 -> 1216412.6 | D11: =Datos!J11-Datos!K11 -> 1394945 | E11: =C11+D11 -> 2611357.6 | F11: =Datos!H11 -> 1636398 | G11: =F11/(E11+F11) -> 0.38523827 | H11: =E11/(E11+F11) -> 0.61476173 | I11: =F11/E11 -> 0.62664647 | J11: =(F11+F10)/2 -> 1322970 | K11: =Datos!I11/J11 -> 0.089059465 | L11: =Supuestos!$J$2 -> 0.27 | M11: =K11*(1-L11) -> 0.065013409 | N11: =INDEX(Supuestos!$B$2:$B$7,MATCH(B11,Supuestos!$A$2:$A$7,0)) -> 0.0388 | O11: =INDEX(Supuestos!$C$2:$C$7,MATCH(B11,Supuestos!$A$2:$A$7,0)) -> 0.046 | P11: =INDEX(Supuestos!$D$2:$D$7,MATCH(B11,Supuestos!$A$2:$A$7,0)) -> 0.012376 | Q11: =INDEX(Betas!$B$2:$G$7,MATCH(Datos!L11,Betas!$A$2:$A$7,0),MATCH(B11,Betas!$B$1:$G$1,0)) -> 0.9048 | R11: =Q11*(1+(1-L11)*I11) -> 1.3187025 | S11: =N11+R11*O11+P11 -> 0.11183631 | T11: =H11*S11+G11*M11 -> 0.09379834 | U11: =INDEX(Betas!$B$2:$G$7,MATCH(Datos!M11,Betas!$A$2:$A$7,0),MATCH(B11,Betas!$B$1:$G$1,0)) -> 1.0022 | V11: =U11*(1+(1-L11)*I11) -> 1.4606583 | W11: =N11+V11*O11+P11 -> 0.11836628 | X11: =H11*W11+G11*M11 -> 0.097812714
A12: =Datos!A12 -> CAP | B12: =Datos!B12 -> 2024 | C12: =(Datos!C12*Datos!D12+Datos!E12*Datos!F12)/Datos!G12/1000 -> 792340.71 | D12: =Datos!J12-Datos!K12 -> 1367992 | E12: =C12+D12 -> 2160332.7 | F12: =Datos!H12 -> 1709061 | G12: =F12/(E12+F12) -> 0.44168703 | H12: =E12/(E12+F12) -> 0.55831297 | I12: =F12/E12 -> 0.79111009 | J12: =(F12+F11)/2 -> 1672729.5 | K12: =Datos!I12/J12 -> 0.07279599 | L12: =Supuestos!$J$2 -> 0.27 | M12: =K12*(1-L12) -> 0.053141073 | N12: =INDEX(Supuestos!$B$2:$B$7,MATCH(B12,Supuestos!$A$2:$A$7,0)) -> 0.0458 | O12: =INDEX(Supuestos!$C$2:$C$7,MATCH(B12,Supuestos!$A$2:$A$7,0)) -> 0.0433 | P12: =INDEX(Supuestos!$D$2:$D$7,MATCH(B12,Supuestos!$A$2:$A$7,0)) -> 0.011294 | Q12: =INDEX(Betas!$B$2:$G$7,MATCH(Datos!L12,Betas!$A$2:$A$7,0),MATCH(B12,Betas!$B$1:$G$1,0)) -> 0.8113 | R12: =Q12*(1+(1-L12)*I12) -> 1.2798342 | S12: =N12+R12*O12+P12 -> 0.11251082 | T12: =H12*S12+G12*M12 -> 0.086287972 | U12: =INDEX(Betas!$B$2:$G$7,MATCH(Datos!M12,Betas!$A$2:$A$7,0),MATCH(B12,Betas!$B$1:$G$1,0)) -> 1.0918 | V12: =U12*(1+(1-L12)*I12) -> 1.7223258 | W12: =N12+V12*O12+P12 -> 0.13167071 | X12: =H12*W12+G12*M12 -> 0.096985187
A13: =Datos!A13 -> CAP | B13: =Datos!B13 -> 2025 | C13: =(Datos!C13*Datos!D13+Datos!E13*Datos!F13)/Datos!G13/1000 -> 1216998.8 | D13: =Datos!J13-Datos!K13 -> 1283655 | E13: =C13+D13 -> 2500653.8 | F13: =Datos!H13 -> 1780319 | G13: =F13/(E13+F13) -> 0.41586786 | H13: =E13/(E13+F13) -> 0.58413214 | I13: =F13/E13 -> 0.71194141 | J13: =(F13+F12)/2 -> 1744690 | K13: =Datos!I13/J13 -> 0.07421605 | L13: =Supuestos!$J$2 -> 0.27 | M13: =K13*(1-L13) -> 0.054177716 | N13: =INDEX(Supuestos!$B$2:$B$7,MATCH(B13,Supuestos!$A$2:$A$7,0)) -> 0.0418 | O13: =INDEX(Supuestos!$C$2:$C$7,MATCH(B13,Supuestos!$A$2:$A$7,0)) -> 0.0423 | P13: =INDEX(Supuestos!$D$2:$D$7,MATCH(B13,Supuestos!$A$2:$A$7,0)) -> 0.010955 | Q13: =INDEX(Betas!$B$2:$G$7,MATCH(Datos!L13,Betas!$A$2:$A$7,0),MATCH(B13,Betas!$B$1:$G$1,0)) -> 0.8371 | R13: =Q13*(1+(1-L13)*I13) -> 1.2721553 | S13: =N13+R13*O13+P13 -> 0.10656717 | T13: =H13*S13+G13*M13 -> 0.084780079 | U13: =INDEX(Betas!$B$2:$G$7,MATCH(Datos!M13,Betas!$A$2:$A$7,0),MATCH(B13,Betas!$B$1:$G$1,0)) -> 1.3013 | V13: =U13*(1+(1-L13)*I13) -> 1.977608 | W13: =N13+V13*O13+P13 -> 0.13640782 | X13: =H13*W13+G13*M13 -> 0.10221096
A14: =Datos!A14 -> Molymet | B14: =Datos!B14 -> 2020 | C14: =(Datos!C14*Datos!D14+Datos!E14*Datos!F14)/Datos!G14/1000 -> 998560.66 | D14: =Datos!J14-Datos!K14 -> 1447 | E14: =C14+D14 -> 1000007.7 | F14: =Datos!H14 -> 192400 | G14: =F14/(E14+F14) -> 0.16135421 | H14: =E14/(E14+F14) -> 0.83864579 | I14: =F14/E14 -> 0.19239853 | J14: =F14 -> 192400 | K14: =Datos!I14/J14 -> 0.070665281 | L14: =Supuestos!$J$2 -> 0.27 | M14: =K14*(1-L14) -> 0.051585655 | N14: =INDEX(Supuestos!$B$2:$B$7,MATCH(B14,Supuestos!$A$2:$A$7,0)) -> 0.0093 | O14: =INDEX(Supuestos!$C$2:$C$7,MATCH(B14,Supuestos!$A$2:$A$7,0)) -> 0.0472 | P14: =INDEX(Supuestos!$D$2:$D$7,MATCH(B14,Supuestos!$A$2:$A$7,0)) -> 0.006815 | Q14: =INDEX(Betas!$B$2:$G$7,MATCH(Datos!L14,Betas!$A$2:$A$7,0),MATCH(B14,Betas!$B$1:$G$1,0)) -> 0.853 | R14: =Q14*(1+(1-L14)*I14) -> 0.97280464 | S14: =N14+R14*O14+P14 -> 0.062031379 | T14: =H14*S14+G14*M14 -> 0.060345917 | U14: =INDEX(Betas!$B$2:$G$7,MATCH(Datos!M14,Betas!$A$2:$A$7,0),MATCH(B14,Betas!$B$1:$G$1,0)) -> 0.8617 | V14: =U14*(1+(1-L14)*I14) -> 0.98272656 | W14: =N14+V14*O14+P14 -> 0.062499694 | X14: =H14*W14+G14*M14 -> 0.060738668
A15: =Datos!A15 -> Molymet | B15: =Datos!B15 -> 2021 | C15: =(Datos!C15*Datos!D15+Datos!E15*Datos!F15)/Datos!G15/1000 -> 641337.43 | D15: =Datos!J15-Datos!K15 -> 1327 | E15: =C15+D15 -> 642664.43 | F15: =Datos!H15 -> 517777 | G15: =F15/(E15+F15) -> 0.44618969 | H15: =E15/(E15+F15) -> 0.55381031 | I15: =F15/E15 -> 0.80567241 | J15: =(F15+F14)/2 -> 355088.5 | K15: =Datos!I15/J15 -> 0.039055052 | L15: =Supuestos!$J$2 -> 0.27 | M15: =K15*(1-L15) -> 0.028510188 | N15: =INDEX(Supuestos!$B$2:$B$7,MATCH(B15,Supuestos!$A$2:$A$7,0)) -> 0.0151 | O15: =INDEX(Supuestos!$C$2:$C$7,MATCH(B15,Supuestos!$A$2:$A$7,0)) -> 0.0424 | P15: =INDEX(Supuestos!$D$2:$D$7,MATCH(B15,Supuestos!$A$2:$A$7,0)) -> 0.006959 | Q15: =INDEX(Betas!$B$2:$G$7,MATCH(Datos!L15,Betas!$A$2:$A$7,0),MATCH(B15,Betas!$B$1:$G$1,0)) -> 1.0761 | R15: =Q15*(1+(1-L15)*I15) -> 1.7089984 | S15: =N15+R15*O15+P15 -> 0.094520531 | T15: =H15*S15+G15*M15 -> 0.065067397 | U15: =INDEX(Betas!$B$2:$G$7,MATCH(Datos!M15,Betas!$A$2:$A$7,0),MATCH(B15,Betas!$B$1:$G$1,0)) -> 0.9816 | V15: =U15*(1+(1-L15)*I15) -> 1.5589191 | W15: =N15+V15*O15+P15 -> 0.088157169 | X15: =H15*W15+G15*M15 -> 0.061543301
A16: =Datos!A16 -> Molymet | B16: =Datos!B16 -> 2022 | C16: =(Datos!C16*Datos!D16+Datos!E16*Datos!F16)/Datos!G16/1000 -> 525971.7 | D16: =Datos!J16-Datos!K16 -> 1302 | E16: =C16+D16 -> 527273.7 | F16: =Datos!H16 -> 467119 | G16: =F16/(E16+F16) -> 0.46975305 | H16: =E16/(E16+F16) -> 0.53024695 | I16: =F16/E16 -> 0.88591371 | J16: =(F16+F15)/2 -> 492448 | K16: =Datos!I16/J16 -> 0.050318003 | L16: =Supuestos!$J$2 -> 0.27 | M16: =K16*(1-L16) -> 0.036732142 | N16: =INDEX(Supuestos!$B$2:$B$7,MATCH(B16,Supuestos!$A$2:$A$7,0)) -> 0.0388 | O16: =INDEX(Supuestos!$C$2:$C$7,MATCH(B16,Supuestos!$A$2:$A$7,0)) -> 0.0594 | P16: =INDEX(Supuestos!$D$2:$D$7,MATCH(B16,Supuestos!$A$2:$A$7,0)) -> 0.014606 | Q16: =INDEX(Betas!$B$2:$G$7,MATCH(Datos!L16,Betas!$A$2:$A$7,0),MATCH(B16,Betas!$B$1:$G$1,0)) -> 1.0408 | R16: =Q16*(1+(1-L16)*I16) -> 1.7139031 | S16: =N16+R16*O16+P16 -> 0.15521184 | T16: =H16*S16+G16*M16 -> 0.099555642 | U16: =INDEX(Betas!$B$2:$G$7,MATCH(Datos!M16,Betas!$A$2:$A$7,0),MATCH(B16,Betas!$B$1:$G$1,0)) -> 0.9393 | V16: =U16*(1+(1-L16)*I16) -> 1.5467613 | W16: =N16+V16*O16+P16 -> 0.14528362 | X16: =H16*W16+G16*M16 -> 0.094291233
A17: =Datos!A17 -> Molymet | B17: =Datos!B17 -> 2023 | C17: =(Datos!C17*Datos!D17+Datos!E17*Datos!F17)/Datos!G17/1000 -> 563817.58 | D17: =Datos!J17-Datos!K17 -> 1226 | E17: =C17+D17 -> 565043.58 | F17: =Datos!H17 -> 763083 | G17: =F17/(E17+F17) -> 0.57455593 | H17: =E17/(E17+F17) -> 0.42544407 | I17: =F17/E17 -> 1.3504852 | J17: =(F17+F16)/2 -> 615101 | K17: =Datos!I17/J17 -> 0.088151377 | L17: =Supuestos!$J$2 -> 0.27 | M17: =K17*(1-L17) -> 0.064350505 | N17: =INDEX(Supuestos!$B$2:$B$7,MATCH(B17,Supuestos!$A$2:$A$7,0)) -> 0.0388 | O17: =INDEX(Supuestos!$C$2:$C$7,MATCH(B17,Supuestos!$A$2:$A$7,0)) -> 0.046 | P17: =INDEX(Supuestos!$D$2:$D$7,MATCH(B17,Supuestos!$A$2:$A$7,0)) -> 0.012376 | Q17: =INDEX(Betas!$B$2:$G$7,MATCH(Datos!L17,Betas!$A$2:$A$7,0),MATCH(B17,Betas!$B$1:$G$1,0)) -> 1.0022 | R17: =Q17*(1+(1-L17)*I17) -> 1.9902231 | S17: =N17+R17*O17+P17 -> 0.14272626 | T17: =H17*S17+G17*M17 -> 0.097695006 | U17: =INDEX(Betas!$B$2:$G$7,MATCH(Datos!M17,Betas!$A$2:$A$7,0),MATCH(B17,Betas!$B$1:$G$1,0)) -> 0.9048 | V17: =U17*(1+(1-L17)*I17) -> 1.7968009 | W17: =N17+V17*O17+P17 -> 0.13382884 | X17: =H17*W17+G17*M17 -> 0.093909651
A18: =Datos!A18 -> Molymet | B18: =Datos!B18 -> 2024 | C18: =(Datos!C18*Datos!D18+Datos!E18*Datos!F18)/Datos!G18/1000 -> 455789.25 | D18: =Datos!J18-Datos!K18 -> 1400 | E18: =C18+D18 -> 457189.25 | F18: =Datos!H18 -> 396480 | G18: =F18/(E18+F18) -> 0.46444217 | H18: =E18/(E18+F18) -> 0.53555783 | I18: =F18/E18 -> 0.86721199 | J18: =(F18+F17)/2 -> 579781.5 | K18: =Datos!I18/J18 -> 0.073396616 | L18: =Supuestos!$J$2 -> 0.27 | M18: =K18*(1-L18) -> 0.05357953 | N18: =INDEX(Supuestos!$B$2:$B$7,MATCH(B18,Supuestos!$A$2:$A$7,0)) -> 0.0458 | O18: =INDEX(Supuestos!$C$2:$C$7,MATCH(B18,Supuestos!$A$2:$A$7,0)) -> 0.0433 | P18: =INDEX(Supuestos!$D$2:$D$7,MATCH(B18,Supuestos!$A$2:$A$7,0)) -> 0.011294 | Q18: =INDEX(Betas!$B$2:$G$7,MATCH(Datos!L18,Betas!$A$2:$A$7,0),MATCH(B18,Betas!$B$1:$G$1,0)) -> 1.0918 | R18: =Q18*(1+(1-L18)*I18) -> 1.7829801 | S18: =N18+R18*O18+P18 -> 0.13429704 | T18: =H18*S18+G18*M18 -> 0.096808423 | U18: =INDEX(Betas!$B$2:$G$7,MATCH(Datos!M18,Betas!$A$2:$A$7,0),MATCH(B18,Betas!$B$1:$G$1,0)) -> 0.8113 | V18: =U18*(1+(1-L18)*I18) -> 1.3249054 | W18: =N18+V18*O18+P18 -> 0.11446241 | X18: =H18*W18+G18*M18 -> 0.08618583
A19: =Datos!A19 -> Molymet | B19: =Datos!B19 -> 2025 | C19: =(Datos!C19*Datos!D19+Datos!E19*Datos!F19)/Datos!G19/1000 -> 904975.62 | D19: =Datos!J19-Datos!K19 -> 1540 | E19: =C19+D19 -> 906515.62 | F19: =Datos!H19 -> 499231 | G19: =F19/(E19+F19) -> 0.35513584 | H19: =E19/(E19+F19) -> 0.64486416 | I19: =F19/E19 -> 0.55071417 | J19: =(F19+F18)/2 -> 447855.5 | K19: =Datos!I19/J19 -> 0.083933322 | L19: =Supuestos!$J$2 -> 0.27 | M19: =K19*(1-L19) -> 0.061271325 | N19: =INDEX(Supuestos!$B$2:$B$7,MATCH(B19,Supuestos!$A$2:$A$7,0)) -> 0.0418 | O19: =INDEX(Supuestos!$C$2:$C$7,MATCH(B19,Supuestos!$A$2:$A$7,0)) -> 0.0423 | P19: =INDEX(Supuestos!$D$2:$D$7,MATCH(B19,Supuestos!$A$2:$A$7,0)) -> 0.010955 | Q19: =INDEX(Betas!$B$2:$G$7,MATCH(Datos!L19,Betas!$A$2:$A$7,0),MATCH(B19,Betas!$B$1:$G$1,0)) -> 1.3013 | R19: =Q19*(1+(1-L19)*I19) -> 1.8244504 | S19: =N19+R19*O19+P19 -> 0.12992925 | T19: =H19*S19+G19*M19 -> 0.10554636 | U19: =INDEX(Betas!$B$2:$G$7,MATCH(Datos!M19,Betas!$A$2:$A$7,0),MATCH(B19,Betas!$B$1:$G$1,0)) -> 0.8371 | V19: =U19*(1+(1-L19)*I19) -> 1.1736321 | W19: =N19+V19*O19+P19 -> 0.10239964 | X19: =H19*W19+G19*M19 -> 0.087793499
A20: =Datos!A20 -> Enaex | B20: =Datos!B20 -> 2020 | C20: =(Datos!C20*Datos!D20+Datos!E20*Datos!F20)/Datos!G20/1000 -> 1239044.6 | D20: =Datos!J20-Datos!K20 -> 37061 | E20: =C20+D20 -> 1276105.6 | F20: =Datos!H20 -> 383025 | G20: =F20/(E20+F20) -> 0.23085886 | H20: =E20/(E20+F20) -> 0.76914114 | I20: =F20/E20 -> 0.30015149 | J20: =F20 -> 383025 | K20: =Datos!I20/J20 -> 0.03875465 | L20: =Supuestos!$J$2 -> 0.27 | M20: =K20*(1-L20) -> 0.028290895 | N20: =INDEX(Supuestos!$B$2:$B$7,MATCH(B20,Supuestos!$A$2:$A$7,0)) -> 0.0093 | O20: =INDEX(Supuestos!$C$2:$C$7,MATCH(B20,Supuestos!$A$2:$A$7,0)) -> 0.0472 | P20: =INDEX(Supuestos!$D$2:$D$7,MATCH(B20,Supuestos!$A$2:$A$7,0)) -> 0.006815 | Q20: =INDEX(Betas!$B$2:$G$7,MATCH(Datos!L20,Betas!$A$2:$A$7,0),MATCH(B20,Betas!$B$1:$G$1,0)) -> 0.8795 | R20: =Q20*(1+(1-L20)*I20) -> 1.0722078 | S20: =N20+R20*O20+P20 -> 0.066723206 | T20: =H20*S20+G20*M20 -> 0.057850767 | U20: =INDEX(Betas!$B$2:$G$7,MATCH(Datos!M20,Betas!$A$2:$A$7,0),MATCH(B20,Betas!$B$1:$G$1,0)) -> 0.9764 | V20: =U20*(1+(1-L20)*I20) -> 1.1903396 | W20: =N20+V20*O20+P20 -> 0.072299028 | X20: =H20*W20+G20*M20 -> 0.062139361
A21: =Datos!A21 -> Enaex | B21: =Datos!B21 -> 2021 | C21: =(Datos!C21*Datos!D21+Datos!E21*Datos!F21)/Datos!G21/1000 -> 1016361.2 | D21: =Datos!J21-Datos!K21 -> 37869 | E21: =C21+D21 -> 1054230.2 | F21: =Datos!H21 -> 427705 | G21: =F21/(E21+F21) -> 0.28861249 | H21: =E21/(E21+F21) -> 0.71138751 | I21: =F21/E21 -> 0.40570362 | J21: =(F21+F20)/2 -> 405365 | K21: =Datos!I21/J21 -> 0.037376192 | L21: =Supuestos!$J$2 -> 0.27 | M21: =K21*(1-L21) -> 0.02728462 | N21: =INDEX(Supuestos!$B$2:$B$7,MATCH(B21,Supuestos!$A$2:$A$7,0)) -> 0.0151 | O21: =INDEX(Supuestos!$C$2:$C$7,MATCH(B21,Supuestos!$A$2:$A$7,0)) -> 0.0424 | P21: =INDEX(Supuestos!$D$2:$D$7,MATCH(B21,Supuestos!$A$2:$A$7,0)) -> 0.006959 | Q21: =INDEX(Betas!$B$2:$G$7,MATCH(Datos!L21,Betas!$A$2:$A$7,0),MATCH(B21,Betas!$B$1:$G$1,0)) -> 0.9509 | R21: =Q21*(1+(1-L21)*I21) -> 1.232522 | S21: =N21+R21*O21+P21 -> 0.074317933 | T21: =H21*S21+G21*M21 -> 0.060743532 | U21: =INDEX(Betas!$B$2:$G$7,MATCH(Datos!M21,Betas!$A$2:$A$7,0),MATCH(B21,Betas!$B$1:$G$1,0)) -> 1.0241 | V21: =U21*(1+(1-L21)*I21) -> 1.3274012 | W21: =N21+V21*O21+P21 -> 0.07834081 | X21: =H21*W21+G21*M21 -> 0.063605356
A22: =Datos!A22 -> Enaex | B22: =Datos!B22 -> 2022 | C22: =(Datos!C22*Datos!D22+Datos!E22*Datos!F22)/Datos!G22/1000 -> 1350236.6 | D22: =Datos!J22-Datos!K22 -> 43825 | E22: =C22+D22 -> 1394061.6 | F22: =Datos!H22 -> 551211 | G22: =F22/(E22+F22) -> 0.28335925 | H22: =E22/(E22+F22) -> 0.71664075 | I22: =F22/E22 -> 0.3953993 | J22: =(F22+F21)/2 -> 489458 | K22: =Datos!I22/J22 -> 0.035706843 | L22: =Supuestos!$J$2 -> 0.27 | M22: =K22*(1-L22) -> 0.026065995 | N22: =INDEX(Supuestos!$B$2:$B$7,MATCH(B22,Supuestos!$A$2:$A$7,0)) -> 0.0388 | O22: =INDEX(Supuestos!$C$2:$C$7,MATCH(B22,Supuestos!$A$2:$A$7,0)) -> 0.0594 | P22: =INDEX(Supuestos!$D$2:$D$7,MATCH(B22,Supuestos!$A$2:$A$7,0)) -> 0.014606 | Q22: =INDEX(Betas!$B$2:$G$7,MATCH(Datos!L22,Betas!$A$2:$A$7,0),MATCH(B22,Betas!$B$1:$G$1,0)) -> 0.9065 | R22: =Q22*(1+(1-L22)*I22) -> 1.1681535 | S22: =N22+R22*O22+P22 -> 0.12279432 | T22: =H22*S22+G22*M22 -> 0.095385453 | U22: =INDEX(Betas!$B$2:$G$7,MATCH(Datos!M22,Betas!$A$2:$A$7,0),MATCH(B22,Betas!$B$1:$G$1,0)) -> 0.9395 | V22: =U22*(1+(1-L22)*I22) -> 1.2106787 | W22: =N22+V22*O22+P22 -> 0.12532031 | X22: =H22*W22+G22*M22 -> 0.097195684
A23: =Datos!A23 -> Enaex | B23: =Datos!B23 -> 2023 | C23: =(Datos!C23*Datos!D23+Datos!E23*Datos!F23)/Datos!G23/1000 -> 1657167.7 | D23: =Datos!J23-Datos!K23 -> 50840 | E23: =C23+D23 -> 1708007.7 | F23: =Datos!H23 -> 610128 | G23: =F23/(E23+F23) -> 0.2631977 | H23: =E23/(E23+F23) -> 0.7368023 | I23: =F23/E23 -> 0.35721618 | J23: =(F23+F22)/2 -> 580669.5 | K23: =Datos!I23/J23 -> 0.051283906 | L23: =Supuestos!$J$2 -> 0.27 | M23: =K23*(1-L23) -> 0.037437251 | N23: =INDEX(Supuestos!$B$2:$B$7,MATCH(B23,Supuestos!$A$2:$A$7,0)) -> 0.0388 | O23: =INDEX(Supuestos!$C$2:$C$7,MATCH(B23,Supuestos!$A$2:$A$7,0)) -> 0.046 | P23: =INDEX(Supuestos!$D$2:$D$7,MATCH(B23,Supuestos!$A$2:$A$7,0)) -> 0.012376 | Q23: =INDEX(Betas!$B$2:$G$7,MATCH(Datos!L23,Betas!$A$2:$A$7,0),MATCH(B23,Betas!$B$1:$G$1,0)) -> 0.8282 | R23: =Q23*(1+(1-L23)*I23) -> 1.0441679 | S23: =N23+R23*O23+P23 -> 0.099207724 | T23: =H23*S23+G23*M23 -> 0.082949877 | U23: =INDEX(Betas!$B$2:$G$7,MATCH(Datos!M23,Betas!$A$2:$A$7,0),MATCH(B23,Betas!$B$1:$G$1,0)) -> 0.8626 | V23: =U23*(1+(1-L23)*I23) -> 1.0875383 | W23: =N23+V23*O23+P23 -> 0.10120276 | X23: =H23*W23+G23*M23 -> 0.084419826
A24: =Datos!A24 -> Enaex | B24: =Datos!B24 -> 2024 | C24: =(Datos!C24*Datos!D24+Datos!E24*Datos!F24)/Datos!G24/1000 -> 1826304.3 | D24: =Datos!J24-Datos!K24 -> 59677 | E24: =C24+D24 -> 1885981.3 | F24: =Datos!H24 -> 522463 | G24: =F24/(E24+F24) -> 0.21692966 | H24: =E24/(E24+F24) -> 0.78307034 | I24: =F24/E24 -> 0.27702449 | J24: =(F24+F23)/2 -> 566295.5 | K24: =Datos!I24/J24 -> 0.055916037 | L24: =Supuestos!$J$2 -> 0.27 | M24: =K24*(1-L24) -> 0.040818707 | N24: =INDEX(Supuestos!$B$2:$B$7,MATCH(B24,Supuestos!$A$2:$A$7,0)) -> 0.0458 | O24: =INDEX(Supuestos!$C$2:$C$7,MATCH(B24,Supuestos!$A$2:$A$7,0)) -> 0.0433 | P24: =INDEX(Supuestos!$D$2:$D$7,MATCH(B24,Supuestos!$A$2:$A$7,0)) -> 0.011294 | Q24: =INDEX(Betas!$B$2:$G$7,MATCH(Datos!L24,Betas!$A$2:$A$7,0),MATCH(B24,Betas!$B$1:$G$1,0)) -> 0.8458 | R24: =Q24*(1+(1-L24)*I24) -> 1.0168443 | S24: =N24+R24*O24+P24 -> 0.10112336 | T24: =H24*S24+G24*M24 -> 0.088041492 | U24: =INDEX(Betas!$B$2:$G$7,MATCH(Datos!M24,Betas!$A$2:$A$7,0),MATCH(B24,Betas!$B$1:$G$1,0)) -> 0.8835 | V24: =U24*(1+(1-L24)*I24) -> 1.0621683 | W24: =N24+V24*O24+P24 -> 0.10308589 | X24: =H24*W24+G24*M24 -> 0.08957829
A25: =Datos!A25 -> Enaex | B25: =Datos!B25 -> 2025 | C25: =(Datos!C25*Datos!D25+Datos!E25*Datos!F25)/Datos!G25/1000 -> 3172125.2 | D25: =Datos!J25-Datos!K25 -> 78352 | E25: =C25+D25 -> 3250477.2 | F25: =Datos!H25 -> 618741 | G25: =F25/(E25+F25) -> 0.1599137 | H25: =E25/(E25+F25) -> 0.8400863 | I25: =F25/E25 -> 0.1903539 | J25: =(F25+F24)/2 -> 570602 | K25: =Datos!I25/J25 -> 0.055784943 | L25: =Supuestos!$J$2 -> 0.27 | M25: =K25*(1-L25) -> 0.040723008 | N25: =INDEX(Supuestos!$B$2:$B$7,MATCH(B25,Supuestos!$A$2:$A$7,0)) -> 0.0418 | O25: =INDEX(Supuestos!$C$2:$C$7,MATCH(B25,Supuestos!$A$2:$A$7,0)) -> 0.0423 | P25: =INDEX(Supuestos!$D$2:$D$7,MATCH(B25,Supuestos!$A$2:$A$7,0)) -> 0.010955 | Q25: =INDEX(Betas!$B$2:$G$7,MATCH(Datos!L25,Betas!$A$2:$A$7,0),MATCH(B25,Betas!$B$1:$G$1,0)) -> 0.969 | R25: =Q25*(1+(1-L25)*I25) -> 1.1036506 | S25: =N25+R25*O25+P25 -> 0.099439422 | T25: =H25*S25+G25*M25 -> 0.090049863 | U25: =INDEX(Betas!$B$2:$G$7,MATCH(Datos!M25,Betas!$A$2:$A$7,0),MATCH(B25,Betas!$B$1:$G$1,0)) -> 1.0271 | V25: =U25*(1+(1-L25)*I25) -> 1.1698241 | W25: =N25+V25*O25+P25 -> 0.10223856 | X25: =H25*W25+G25*M25 -> 0.092401381
A26: =Datos!A26 -> Minera Valparaíso | B26: =Datos!B26 -> 2020 | C26: =(Datos!C26*Datos!D26+Datos!E26*Datos!F26)/Datos!G26/1000 -> 2459085.5 | D26: =Datos!J26-Datos!K26 -> 2323731 | E26: =C26+D26 -> 4782816.5 | F26: =Datos!H26 -> 1661516 | G26: =F26/(E26+F26) -> 0.25782593 | H26: =E26/(E26+F26) -> 0.74217407 | I26: =F26/E26 -> 0.34739279 | J26: =F26 -> 1661516 | K26: =Datos!I26/J26 -> 0.058941352 | L26: =Supuestos!$J$2 -> 0.27 | M26: =K26*(1-L26) -> 0.043027187 | N26: =INDEX(Supuestos!$B$2:$B$7,MATCH(B26,Supuestos!$A$2:$A$7,0)) -> 0.0093 | O26: =INDEX(Supuestos!$C$2:$C$7,MATCH(B26,Supuestos!$A$2:$A$7,0)) -> 0.0472 | P26: =INDEX(Supuestos!$D$2:$D$7,MATCH(B26,Supuestos!$A$2:$A$7,0)) -> 0.006815 | Q26: =INDEX(Betas!$B$2:$G$7,MATCH(Datos!L26,Betas!$A$2:$A$7,0),MATCH(B26,Betas!$B$1:$G$1,0)) -> 0.487 | R26: =Q26*(1+(1-L26)*I26) -> 0.61050161 | S26: =N26+R26*O26+P26 -> 0.044930676 | T26: =H26*S26+G26*M26 -> 0.044439907 | U26: =INDEX(Betas!$B$2:$G$7,MATCH(Datos!M26,Betas!$A$2:$A$7,0),MATCH(B26,Betas!$B$1:$G$1,0)) -> 0.1883 | V26: =U26*(1+(1-L26)*I26) -> 0.23605227 | W26: =N26+V26*O26+P26 -> 0.027256667 | X26: =H26*W26+G26*M26 -> 0.031322716
A27: =Datos!A27 -> Minera Valparaíso | B27: =Datos!B27 -> 2021 | C27: =(Datos!C27*Datos!D27+Datos!E27*Datos!F27)/Datos!G27/1000 -> 1914289.9 | D27: =Datos!J27-Datos!K27 -> 1893723 | E27: =C27+D27 -> 3808012.9 | F27: =Datos!H27 -> 2408200 | G27: =F27/(E27+F27) -> 0.38740629 | H27: =E27/(E27+F27) -> 0.61259371 | I27: =F27/E27 -> 0.63240332 | J27: =(F27+F26)/2 -> 2034858 | K27: =Datos!I27/J27 -> 0.047467194 | L27: =Supuestos!$J$2 -> 0.27 | M27: =K27*(1-L27) -> 0.034651052 | N27: =INDEX(Supuestos!$B$2:$B$7,MATCH(B27,Supuestos!$A$2:$A$7,0)) -> 0.0151 | O27: =INDEX(Supuestos!$C$2:$C$7,MATCH(B27,Supuestos!$A$2:$A$7,0)) -> 0.0424 | P27: =INDEX(Supuestos!$D$2:$D$7,MATCH(B27,Supuestos!$A$2:$A$7,0)) -> 0.006959 | Q27: =INDEX(Betas!$B$2:$G$7,MATCH(Datos!L27,Betas!$A$2:$A$7,0),MATCH(B27,Betas!$B$1:$G$1,0)) -> 0.5177 | R27: =Q27*(1+(1-L27)*I27) -> 0.75669849 | S27: =N27+R27*O27+P27 -> 0.054143016 | T27: =H27*S27+G27*M27 -> 0.046591707 | U27: =INDEX(Betas!$B$2:$G$7,MATCH(Datos!M27,Betas!$A$2:$A$7,0),MATCH(B27,Betas!$B$1:$G$1,0)) -> 0.3532 | V27: =U27*(1+(1-L27)*I27) -> 0.51625634 | W27: =N27+V27*O27+P27 -> 0.043948269 | X27: =H27*W27+G27*M27 -> 0.040346468
A28: =Datos!A28 -> Minera Valparaíso | B28: =Datos!B28 -> 2022 | C28: =(Datos!C28*Datos!D28+Datos!E28*Datos!F28)/Datos!G28/1000 -> 1502309.5 | D28: =Datos!J28-Datos!K28 -> 1983123 | E28: =C28+D28 -> 3485432.5 | F28: =Datos!H28 -> 2323016 | G28: =F28/(E28+F28) -> 0.39993744 | H28: =E28/(E28+F28) -> 0.60006256 | I28: =F28/E28 -> 0.6664929 | J28: =(F28+F27)/2 -> 2365608 | K28: =Datos!I28/J28 -> 0.046805726 | L28: =Supuestos!$J$2 -> 0.27 | M28: =K28*(1-L28) -> 0.03416818 | N28: =INDEX(Supuestos!$B$2:$B$7,MATCH(B28,Supuestos!$A$2:$A$7,0)) -> 0.0388 | O28: =INDEX(Supuestos!$C$2:$C$7,MATCH(B28,Supuestos!$A$2:$A$7,0)) -> 0.0594 | P28: =INDEX(Supuestos!$D$2:$D$7,MATCH(B28,Supuestos!$A$2:$A$7,0)) -> 0.014606 | Q28: =INDEX(Betas!$B$2:$G$7,MATCH(Datos!L28,Betas!$A$2:$A$7,0),MATCH(B28,Betas!$B$1:$G$1,0)) -> 0.416 | R28: =Q28*(1+(1-L28)*I28) -> 0.61840057 | S28: =N28+R28*O28+P28 -> 0.090138994 | T28: =H28*S28+G28*M28 -> 0.06775417 | U28: =INDEX(Betas!$B$2:$G$7,MATCH(Datos!M28,Betas!$A$2:$A$7,0),MATCH(B28,Betas!$B$1:$G$1,0)) -> 0.2756 | V28: =U28*(1+(1-L28)*I28) -> 0.40969037 | W28: =N28+V28*O28+P28 -> 0.077741608 | X28: =H28*W28+G28*M28 -> 0.060314963
A29: =Datos!A29 -> Minera Valparaíso | B29: =Datos!B29 -> 2023 | C29: =(Datos!C29*Datos!D29+Datos!E29*Datos!F29)/Datos!G29/1000 -> 1781051.1 | D29: =Datos!J29-Datos!K29 -> 2066787 | E29: =C29+D29 -> 3847838.1 | F29: =Datos!H29 -> 2402157 | G29: =F29/(E29+F29) -> 0.38434542 | H29: =E29/(E29+F29) -> 0.61565458 | I29: =F29/E29 -> 0.62428744 | J29: =(F29+F28)/2 -> 2362586.5 | K29: =Datos!I29/J29 -> 0.048738533 | L29: =Supuestos!$J$2 -> 0.27 | M29: =K29*(1-L29) -> 0.035579129 | N29: =INDEX(Supuestos!$B$2:$B$7,MATCH(B29,Supuestos!$A$2:$A$7,0)) -> 0.0388 | O29: =INDEX(Supuestos!$C$2:$C$7,MATCH(B29,Supuestos!$A$2:$A$7,0)) -> 0.046 | P29: =INDEX(Supuestos!$D$2:$D$7,MATCH(B29,Supuestos!$A$2:$A$7,0)) -> 0.012376 | Q29: =INDEX(Betas!$B$2:$G$7,MATCH(Datos!L29,Betas!$A$2:$A$7,0),MATCH(B29,Betas!$B$1:$G$1,0)) -> 0.4218 | R29: =Q29*(1+(1-L29)*I29) -> 0.61402684 | S29: =N29+R29*O29+P29 -> 0.079421235 | T29: =H29*S29+G29*M29 -> 0.062570722 | U29: =INDEX(Betas!$B$2:$G$7,MATCH(Datos!M29,Betas!$A$2:$A$7,0),MATCH(B29,Betas!$B$1:$G$1,0)) -> 0.279 | V29: =U29*(1+(1-L29)*I29) -> 0.40614862 | W29: =N29+V29*O29+P29 -> 0.069858837 | X29: =H29*W29+G29*M29 -> 0.056683588
A30: =Datos!A30 -> Minera Valparaíso | B30: =Datos!B30 -> 2024 | C30: =(Datos!C30*Datos!D30+Datos!E30*Datos!F30)/Datos!G30/1000 -> 1752182.2 | D30: =Datos!J30-Datos!K30 -> 2107801 | E30: =C30+D30 -> 3859983.2 | F30: =Datos!H30 -> 2347412 | G30: =F30/(E30+F30) -> 0.37816377 | H30: =E30/(E30+F30) -> 0.62183623 | I30: =F30/E30 -> 0.60814047 | J30: =(F30+F29)/2 -> 2374784.5 | K30: =Datos!I30/J30 -> 0.039085231 | L30: =Supuestos!$J$2 -> 0.27 | M30: =K30*(1-L30) -> 0.028532218 | N30: =INDEX(Supuestos!$B$2:$B$7,MATCH(B30,Supuestos!$A$2:$A$7,0)) -> 0.0458 | O30: =INDEX(Supuestos!$C$2:$C$7,MATCH(B30,Supuestos!$A$2:$A$7,0)) -> 0.0433 | P30: =INDEX(Supuestos!$D$2:$D$7,MATCH(B30,Supuestos!$A$2:$A$7,0)) -> 0.011294 | Q30: =INDEX(Betas!$B$2:$G$7,MATCH(Datos!L30,Betas!$A$2:$A$7,0),MATCH(B30,Betas!$B$1:$G$1,0)) -> 0.4047 | R30: =Q30*(1+(1-L30)*I30) -> 0.58436355 | S30: =N30+R30*O30+P30 -> 0.082396942 | T30: =H30*S30+G30*M30 -> 0.062027255 | U30: =INDEX(Betas!$B$2:$G$7,MATCH(Datos!M30,Betas!$A$2:$A$7,0),MATCH(B30,Betas!$B$1:$G$1,0)) -> 0.281 | V30: =U30*(1+(1-L30)*I30) -> 0.40574785 | W30: =N30+V30*O30+P30 -> 0.074662882 | X30: =H30*W30+G30*M30 -> 0.057217936
A31: =Datos!A31 -> Minera Valparaíso | B31: =Datos!B31 -> 2025 | C31: =(Datos!C31*Datos!D31+Datos!E31*Datos!F31)/Datos!G31/1000 -> 1960232.9 | D31: =Datos!J31-Datos!K31 -> 2147872 | E31: =C31+D31 -> 4108104.9 | F31: =Datos!H31 -> 2635839 | G31: =F31/(E31+F31) -> 0.39084533 | H31: =E31/(E31+F31) -> 0.60915467 | I31: =F31/E31 -> 0.64161921 | J31: =(F31+F30)/2 -> 2491625.5 | K31: =Datos!I31/J31 -> 0.041802028 | L31: =Supuestos!$J$2 -> 0.27 | M31: =K31*(1-L31) -> 0.030515481 | N31: =INDEX(Supuestos!$B$2:$B$7,MATCH(B31,Supuestos!$A$2:$A$7,0)) -> 0.0418 | O31: =INDEX(Supuestos!$C$2:$C$7,MATCH(B31,Supuestos!$A$2:$A$7,0)) -> 0.0423 | P31: =INDEX(Supuestos!$D$2:$D$7,MATCH(B31,Supuestos!$A$2:$A$7,0)) -> 0.010955 | Q31: =INDEX(Betas!$B$2:$G$7,MATCH(Datos!L31,Betas!$A$2:$A$7,0),MATCH(B31,Betas!$B$1:$G$1,0)) -> 0.4331 | R31: =Q31*(1+(1-L31)*I31) -> 0.63595625 | S31: =N31+R31*O31+P31 -> 0.07965595 | T31: =H31*S31+G31*M31 -> 0.060449627 | U31: =INDEX(Betas!$B$2:$G$7,MATCH(Datos!M31,Betas!$A$2:$A$7,0),MATCH(B31,Betas!$B$1:$G$1,0)) -> 0.3996 | V31: =U31*(1+(1-L31)*I31) -> 0.58676546 | W31: =N31+V31*O31+P31 -> 0.077575179 | X31: =H31*W31+G31*M31 -> 0.059182115
