Workbook

Sheet 0_Inicio
B2: LABORATORIO CCI - Concurso Carteras de Inversion
B3: Herramientas para estudiar y practicar teoria de portafolios y gestionar tu cartera durante el concurso.
B5: COLORES
B6: Celda amarilla | C6: Dato que TU ingresas o puedes cambiar.
B7: Celda verde | C7: Resultado clave calculado con formulas (no escribir encima).
B8: Texto rojo | C8: Alertas automaticas (caja negativa, concentracion excesiva, etc.).
B10: HOJA | C10: PARA QUE SIRVE
B11: 1_Precios | C11: Precios diarios de 5 acciones y el IPSA. DATOS FICTICIOS para practicar: reemplazalos por datos reales (ver abajo).
B12: 2_Retornos | C12: Retornos diarios, retorno y volatilidad anualizados, Sharpe, retorno acumulado.
B13: 3_Cov_Correl | C13: Matriz de covarianzas y correlaciones (con mapa de calor). Base de la diversificacion.
B14: 4_Frontera_2A | C14: Frontera eficiente con 2 activos: cambia la correlacion y mira como cambia el riesgo. Portafolio de minima varianza.
B15: 5_Cartera | C15: Tu cartera de N acciones: pesos editables, retorno, riesgo, Sharpe, beta, Treynor, alfa de Jensen, tracking error, drawdown. Optimizable con Solver.
B16: 6_Beta_CAPM | C16: Beta de cada accion vs IPSA (regresion), R2 y retorno exigido por CAPM.
B17: 7_Tecnico | C17: Analisis tecnico de la accion que elijas: medias moviles 20/50, cruces, RSI(14) y bandas de Bollinger.
B18: 8_Drawdown | C18: Caida maxima desde el peak de cada activo.
... B23: 13_Plan_Estudio | C23: Plan de 21 dias para dominar el tema, con avance automatico.
B26: COMO PONER DATOS REALES
C27: 1) Yahoo Finance: busca el ticker con sufijo .SN (ej. SQM-B.SN, CHILE.SN, FALABELLA.SN). Indice: ^IPSA. Pestana "Historical Data" > Descargar.
C28: 2) Alternativas: Investing.com (Chile), TradingView, terminal de tu corredora o el sitio de la Bolsa de Santiago / nuam.
C29: 3) Pega los precios de CIERRE (ajustados por dividendos si vas a medir retorno total) en 1_Precios, misma estructura (columna = accion, fila = fecha).
C30: 4) Cambia los nombres de la fila 1 de 1_Precios por los tickers reales: todas las hojas se actualizan solas.
C31: 5) Si cambias el numero de filas, ajusta los rangos (las formulas usan filas 2 a 253 = 252 dias habiles ~ 1 ano).
C32: ADVERTENCIA: los datos de ejemplo son simulados con un modelo de mercado. No representan precios reales de ninguna empresa.

Sheet 1_Precios
A1: Fecha | B1: BANCO | C1: RETAIL | D1: MINERA | E1: ENERGIA | F1: CONSUMO | G1: IPSA | I1: DATOS FICTICIOS (simulados). Reemplazar por precios reales de cierre.
A2: 45659 | B2: 5200 | C2: 2100 | D2: 41000 | E2: 95 | F2: 6800 | G2: 7000
A3: 45660 | B3: 5199.25 | C3: 2137 | D3: 41549.37 | E3: 95.88 | F3: 6847.64 | G3: 7060.38
A4: 45663 | B4: 5218.97 | C4: 2120 | D4: 42744.95 | E4: 96.07 | F4: 6904.96 | G4: 7117.14
A5: 45664 | B5: 5055.01 | C5: 2043.88 | D5: 40630.26 | E5: 95.61 | F5: 6780.96 | G5: 6986.28
A6: 45665 | B6: 5060.47 | C6: 2073.95 | D6: 42226.06 | E6: 95.36 | F6: 6722.13 | G6: 6979.31
A7: 45666 | B7: 5007.77 | C7: 2059.43 | D7: 40841.1 | E7: 94.28 | F7: 6854.64 | G7: 7019.77
A8: 45667 | B8: 4985.59 | C8: 2110.26 | D8: 40941.19 | E8: 94.6 | F8: 6857.1 | G8: 7051.07
A9: 45670 | B9: 4901.59 | C9: 2138.76 | D9: 40006.07 | E9: 95 | F9: 6889.08 | G9: 6985.11
A10: 45671 | B10: 4826.61 | C10: 2182.11 | D10: 38906.16 | E10: 94.44 | F10: 6750.42 | G10: 6937.72
A11: 45672 | B11: 4815.24 | C11: 2224.17 | D11: 39772.57 | E11: 94.9 | F11: 6787.39 | G11: 6957.78
A12: 45673 | B12: 4719.9 | C12: 2229.04 | D12: 39014.02 | E12: 94.11 | F12: 6672.32 | G12: 6879.11
A13: 45674 | B13: 4693.18 | C13: 2205.28 | D13: 39309.44 | E13: 93.56 | F13: 6685.45 | G13: 6868.23
... A253: 46010 | B253: 4453.76 | C253: 3260.19 | D253: 37142.42 | E253: 96.07 | F253: 6860.26 | G253: 6558.76

Sheet 2_Retornos
A1: Fecha | B1: BANCO | C1: RETAIL | D1: MINERA | E1: ENERGIA | F1: CONSUMO | G1: IPSA | I1: PARAMETROS
A2: ='1_Precios'!A2 -> 0 | B2: ='1_Precios'!B2/'1_Precios'!B1-1 -> 0 | C2: ='1_Precios'!C2/'1_Precios'!C1-1 -> 0 | D2: ='1_Precios'!D2/'1_Precios'!D1-1 -> 0 | E2: ='1_Precios'!E2/'1_Precios'!E1-1 -> 0 | F2: ='1_Precios'!F2/'1_Precios'!F1-1 -> 0 | G2: ='1_Precios'!G2/'1_Precios'!G1-1 -> 0 | I2: Tasa libre de riesgo anual (rf) | J2: 0.0475 | K2: Ej.: TPM o BCP/BTP en pesos. Editable.
A3: ='1_Precios'!A3 -> 0 | B3: ='1_Precios'!B3/'1_Precios'!B2-1 -> 0 | C3: ='1_Precios'!C3/'1_Precios'!C2-1 -> 0 | D3: ='1_Precios'!D3/'1_Precios'!D2-1 -> 0 | E3: ='1_Precios'!E3/'1_Precios'!E2-1 -> 0 | F3: ='1_Precios'!F3/'1_Precios'!F2-1 -> 0 | G3: ='1_Precios'!G3/'1_Precios'!G2-1 -> 0 | I3: Dias habiles por ano | J3: 252
A4: ='1_Precios'!A4 -> 0 | B4: ='1_Precios'!B4/'1_Precios'!B3-1 -> 0 | C4: ='1_Precios'!C4/'1_Precios'!C3-1 -> 0 | D4: ='1_Precios'!D4/'1_Precios'!D3-1 -> 0 | E4: ='1_Precios'!E4/'1_Precios'!E3-1 -> 0 | F4: ='1_Precios'!F4/'1_Precios'!F3-1 -> 0 | G4: ='1_Precios'!G4/'1_Precios'!G3-1 -> 0
A5: ='1_Precios'!A5 -> 0 | B5: ='1_Precios'!B5/'1_Precios'!B4-1 -> 0 | C5: ='1_Precios'!C5/'1_Precios'!C4-1 -> 0 | D5: ='1_Precios'!D5/'1_Precios'!D4-1 -> 0 | E5: ='1_Precios'!E5/'1_Precios'!E4-1 -> 0 | F5: ='1_Precios'!F5/'1_Precios'!F4-1 -> 0 | G5: ='1_Precios'!G5/'1_Precios'!G4-1 -> 0 | I5: ESTADISTICO | J5: BANCO | K5: RETAIL | L5: MINERA | M5: ENERGIA | N5: CONSUMO | O5: IPSA
A6: ='1_Precios'!A6 -> 0 | B6: ='1_Precios'!B6/'1_Precios'!B5-1 -> 0 | C6: ='1_Precios'!C6/'1_Precios'!C5-1 -> 0 | D6: ='1_Precios'!D6/'1_Precios'!D5-1 -> 0 | E6: ='1_Precios'!E6/'1_Precios'!E5-1 -> 0 | F6: ='1_Precios'!F6/'1_Precios'!F5-1 -> 0 | G6: ='1_Precios'!G6/'1_Precios'!G5-1 -> 0 | I6: Retorno medio diario | J6: =AVERAGE(B2:B252) -> 0 | K6: =AVERAGE(C2:C252) -> 0 | L6: =AVERAGE(D2:D252) -> 0 | M6: =AVERAGE(E2:E252) -> 0 | N6: =AVERAGE(F2:F252) -> 0 | O6: =AVERAGE(G2:G252) -> 0
A7: ='1_Precios'!A7 -> 0 | B7: ='1_Precios'!B7/'1_Precios'!B6-1 -> 0 | C7: ='1_Precios'!C7/'1_Precios'!C6-1 -> 0 | D7: ='1_Precios'!D7/'1_Precios'!D6-1 -> 0 | E7: ='1_Precios'!E7/'1_Precios'!E6-1 -> 0 | F7: ='1_Precios'!F7/'1_Precios'!F6-1 -> 0 | G7: ='1_Precios'!G7/'1_Precios'!G6-1 -> 0 | I7: Retorno anualizado (compuesto) | J7: =(1+J6)^$J$3-1 -> 0 | K7: =(1+K6)^$J$3-1 -> 0 | L7: =(1+L6)^$J$3-1 -> 0 | M7: =(1+M6)^$J$3-1 -> 0 | N7: =(1+N6)^$J$3-1 -> 0 | O7: =(1+O6)^$J$3-1 -> 0
A8: ='1_Precios'!A8 -> 0 | B8: ='1_Precios'!B8/'1_Precios'!B7-1 -> 0 | C8: ='1_Precios'!C8/'1_Precios'!C7-1 -> 0 | D8: ='1_Precios'!D8/'1_Precios'!D7-1 -> 0 | E8: ='1_Precios'!E8/'1_Precios'!E7-1 -> 0 | F8: ='1_Precios'!F8/'1_Precios'!F7-1 -> 0 | G8: ='1_Precios'!G8/'1_Precios'!G7-1 -> 0 | I8: Volatilidad diaria | J8: =_xlfn.STDEV.S(B2:B252) -> 0 | K8: =_xlfn.STDEV.S(C2:C252) -> 0 | L8: =_xlfn.STDEV.S(D2:D252) -> 0 | M8: =_xlfn.STDEV.S(E2:E252) -> 0 | N8: =_xlfn.STDEV.S(F2:F252) -> 0 | O8: =_xlfn.STDEV.S(G2:G252) -> 0
A9: ='1_Precios'!A9 -> 0 | B9: ='1_Precios'!B9/'1_Precios'!B8-1 -> 0 | C9: ='1_Precios'!C9/'1_Precios'!C8-1 -> 0 | D9: ='1_Precios'!D9/'1_Precios'!D8-1 -> 0 | E9: ='1_Precios'!E9/'1_Precios'!E8-1 -> 0 | F9: ='1_Precios'!F9/'1_Precios'!F8-1 -> 0 | G9: ='1_Precios'!G9/'1_Precios'!G8-1 -> 0 | I9: Volatilidad anualizada | J9: =J8*SQRT($J$3) -> 0 | K9: =K8*SQRT($J$3) -> 0 | L9: =L8*SQRT($J$3) -> 0 | M9: =M8*SQRT($J$3) -> 0 | N9: =N8*SQRT($J$3) -> 0 | O9: =O8*SQRT($J$3) -> 0
A10: ='1_Precios'!A10 -> 0 | B10: ='1_Precios'!B10/'1_Precios'!B9-1 -> 0 | C10: ='1_Precios'!C10/'1_Precios'!C9-1 -> 0 | D10: ='1_Precios'!D10/'1_Precios'!D9-1 -> 0 | E10: ='1_Precios'!E10/'1_Precios'!E9-1 -> 0 | F10: ='1_Precios'!F10/'1_Precios'!F9-1 -> 0 | G10: ='1_Precios'!G10/'1_Precios'!G9-1 -> 0 | I10: Ratio de Sharpe anual | J10: =(J7-$J$2)/J9 -> 0 | K10: =(K7-$J$2)/K9 -> 0 | L10: =(L7-$J$2)/L9 -> 0 | M10: =(M7-$J$2)/M9 -> 0 | N10: =(N7-$J$2)/N9 -> 0 | O10: =(O7-$J$2)/O9 -> 0
A11: ='1_Precios'!A11 -> 0 | B11: ='1_Precios'!B11/'1_Precios'!B10-1 -> 0 | C11: ='1_Precios'!C11/'1_Precios'!C10-1 -> 0 | D11: ='1_Precios'!D11/'1_Precios'!D10-1 -> 0 | E11: ='1_Precios'!E11/'1_Precios'!E10-1 -> 0 | F11: ='1_Precios'!F11/'1_Precios'!F10-1 -> 0 | G11: ='1_Precios'!G11/'1_Precios'!G10-1 -> 0 | I11: Retorno acumulado periodo | J11: =INDEX('1_Precios'!B$2:B$253,252)/'1_Precios'!B$2-1 -> 0 | K11: =INDEX('1_Precios'!C$2:C$253,252)/'1_Precios'!C$2-1 -> 0 | L11: =INDEX('1_Precios'!D$2:D$253,252)/'1_Precios'!D$2-1 -> 0 | M11: =INDEX('1_Precios'!E$2:E$253,252)/'1_Precios'!E$2-1 -> 0 | N11: =INDEX('1_Precios'!F$2:F$253,252)/'1_Precios'!F$2-1 -> 0 | O11: =INDEX('1_Precios'!G$2:G$253,252)/'1_Precios'!G$2-1 -> 0
A12: ='1_Precios'!A12 -> 0 | B12: ='1_Precios'!B12/'1_Precios'!B11-1 -> 0 | C12: ='1_Precios'!C12/'1_Precios'!C11-1 -> 0 | D12: ='1_Precios'!D12/'1_Precios'!D11-1 -> 0 | E12: ='1_Precios'!E12/'1_Precios'!E11-1 -> 0 | F12: ='1_Precios'!F12/'1_Precios'!F11-1 -> 0 | G12: ='1_Precios'!G12/'1_Precios'!G11-1 -> 0 | I12: Mejor dia | J12: =MAX(B2:B252) -> 0 | K12: =MAX(C2:C252) -> 0 | L12: =MAX(D2:D252) -> 0 | M12: =MAX(E2:E252) -> 0 | N12: =MAX(F2:F252) -> 0 | O12: =MAX(G2:G252) -> 0
A13: ='1_Precios'!A13 -> 0 | B13: ='1_Precios'!B13/'1_Precios'!B12-1 -> 0 | C13: ='1_Precios'!C13/'1_Precios'!C12-1 -> 0 | D13: ='1_Precios'!D13/'1_Precios'!D12-1 -> 0 | E13: ='1_Precios'!E13/'1_Precios'!E12-1 -> 0 | F13: ='1_Precios'!F13/'1_Precios'!F12-1 -> 0 | G13: ='1_Precios'!G13/'1_Precios'!G12-1 -> 0 | I13: Peor dia | J13: =MIN(B2:B252) -> 0 | K13: =MIN(C2:C252) -> 0 | L13: =MIN(D2:D252) -> 0 | M13: =MIN(E2:E252) -> 0 | N13: =MIN(F2:F252) -> 0 | O13: =MIN(G2:G252) -> 0
A14: ='1_Precios'!A14 -> 0 | B14: ='1_Precios'!B14/'1_Precios'!B13-1 -> 0 | C14: ='1_Precios'!C14/'1_Precios'!C13-1 -> 0 | D14: ='1_Precios'!D14/'1_Precios'!D13-1 -> 0 | E14: ='1_Precios'!E14/'1_Precios'!E13-1 -> 0 | F14: ='1_Precios'!F14/'1_Precios'!F13-1 -> 0 | G14: ='1_Precios'!G14/'1_Precios'!G13-1 -> 0 | I14: % dias positivos | J14: =COUNTIF(B2:B252,">0")/COUNT(B2:B252) -> 0 | K14: =COUNTIF(C2:C252,">0")/COUNT(C2:C252) -> 0 | L14: =COUNTIF(D2:D252,">0")/COUNT(D2:D252) -> 0 | M14: =COUNTIF(E2:E252,">0")/COUNT(E2:E252) -> 0 | N14: =COUNTIF(F2:F252,">0")/COUNT(F2:F252) -> 0 | O14: =COUNTIF(G2:G252,">0")/COUNT(G2:G252) -> 0
A15: ='1_Precios'!A15 -> 0 | B15: ='1_Precios'!B15/'1_Precios'!B14-1 -> 0 | C15: ='1_Precios'!C15/'1_Precios'!C14-1 -> 0 | D15: ='1_Precios'!D15/'1_Precios'!D14-1 -> 0 | E15: ='1_Precios'!E15/'1_Precios'!E14-1 -> 0 | F15: ='1_Precios'!F15/'1_Precios'!F14-1 -> 0 | G15: ='1_Precios'!G15/'1_Precios'!G14-1 -> 0 | I15: Asimetria (skew) | J15: =SKEW(B2:B252) -> 0 | K15: =SKEW(C2:C252) -> 0 | L15: =SKEW(D2:D252) -> 0 | M15: =SKEW(E2:E252) -> 0 | N15: =SKEW(F2:F252) -> 0 | O15: =SKEW(G2:G252) -> 0
A16: ='1_Precios'!A16 -> 0 | B16: ='1_Precios'!B16/'1_Precios'!B15-1 -> 0 | C16: ='1_Precios'!C16/'1_Precios'!C15-1 -> 0 | D16: ='1_Precios'!D16/'1_Precios'!D15-1 -> 0 | E16: ='1_Precios'!E16/'1_Precios'!E15-1 -> 0 | F16: ='1_Precios'!F16/'1_Precios'!F15-1 -> 0 | G16: ='1_Precios'!G16/'1_Precios'!G15-1 -> 0 | I16: Curtosis (exceso) | J16: =KURT(B2:B252) -> 0 | K16: =KURT(C2:C252) -> 0 | L16: =KURT(D2:D252) -> 0 | M16: =KURT(E2:E252) -> 0 | N16: =KURT(F2:F252) -> 0 | O16: =KURT(G2:G252) -> 0
A17: ='1_Precios'!A17 -> 0 | B17: ='1_Precios'!B17/'1_Precios'!B16-1 -> 0 | C17: ='1_Precios'!C17/'1_Precios'!C16-1 -> 0 | D17: ='1_Precios'!D17/'1_Precios'!D16-1 -> 0 | E17: ='1_Precios'!E17/'1_Precios'!E16-1 -> 0 | F17: ='1_Precios'!F17/'1_Precios'!F16-1 -> 0 | G17: ='1_Precios'!G17/'1_Precios'!G16-1 -> 0
A18: ='1_Precios'!A18 -> 0 | B18: ='1_Precios'!B18/'1_Precios'!B17-1 -> 0 | C18: ='1_Precios'!C18/'1_Precios'!C17-1 -> 0 | D18: ='1_Precios'!D18/'1_Precios'!D17-1 -> 0 | E18: ='1_Precios'!E18/'1_Precios'!E17-1 -> 0 | F18: ='1_Precios'!F18/'1_Precios'!F17-1 -> 0 | G18: ='1_Precios'!G18/'1_Precios'!G17-1 -> 0 | I18: Como leer:
A19: ='1_Precios'!A19 -> 0 | B19: ='1_Precios'!B19/'1_Precios'!B18-1 -> 0 | C19: ='1_Precios'!C19/'1_Precios'!C18-1 -> 0 | D19: ='1_Precios'!D19/'1_Precios'!D18-1 -> 0 | E19: ='1_Precios'!E19/'1_Precios'!E18-1 -> 0 | F19: ='1_Precios'!F19/'1_Precios'!F18-1 -> 0 | G19: ='1_Precios'!G19/'1_Precios'!G18-1 -> 0 | I19: Volatilidad anual = vol diaria x RAIZ(252). Sharpe = (retorno anual - rf) / volatilidad anual: retorno por unidad de riesgo total. Curtosis > 0 = colas gordas (mas dias extremos que una normal).
A20: ='1_Precios'!A20 -> 0 | B20: ='1_Precios'!B20/'1_Precios'!B19-1 -> 0 | C20: ='1_Precios'!C20/'1_Precios'!C19-1 -> 0 | D20: ='1_Precios'!D20/'1_Precios'!D19-1 -> 0 | E20: ='1_Precios'!E20/'1_Precios'!E19-1 -> 0 | F20: ='1_Precios'!F20/'1_Precios'!F19-1 -> 0 | G20: ='1_Precios'!G20/'1_Precios'!G19-1 -> 0
A21: ='1_Precios'!A21 -> 0 | B21: ='1_Precios'!B21/'1_Precios'!B20-1 -> 0 | C21: ='1_Precios'!C21/'1_Precios'!C20-1 -> 0 | D21: ='1_Precios'!D21/'1_Precios'!D20-1 -> 0 | E21: ='1_Precios'!E21/'1_Precios'!E20-1 -> 0 | F21: ='1_Precios'!F21/'1_Precios'!F20-1 -> 0 | G21: ='1_Precios'!G21/'1_Precios'!G20-1 -> 0
A22: ='1_Precios'!A22 -> 0 | B22: ='1_Precios'!B22/'1_Precios'!B21-1 -> 0 | C22: ='1_Precios'!C22/'1_Precios'!C21-1 -> 0 | D22: ='1_Precios'!D22/'1_Precios'!D21-1 -> 0 | E22: ='1_Precios'!E22/'1_Precios'!E21-1 -> 0 | F22: ='1_Precios'!F22/'1_Precios'!F21-1 -> 0 | G22: ='1_Precios'!G22/'1_Precios'!G21-1 -> 0
A23: ='1_Precios'!A23 -> 0 | B23: ='1_Precios'!B23/'1_Precios'!B22-1 -> 0 | C23: ='1_Precios'!C23/'1_Precios'!C22-1 -> 0 | D23: ='1_Precios'!D23/'1_Precios'!D22-1 -> 0 | E23: ='1_Precios'!E23/'1_Precios'!E22-1 -> 0 | F23: ='1_Precios'!F23/'1_Precios'!F22-1 -> 0 | G23: ='1_Precios'!G23/'1_Precios'!G22-1 -> 0
A24: ='1_Precios'!A24 -> 0 | B24: ='1_Precios'!B24/'1_Precios'!B23-1 -> 0 | C24: ='1_Precios'!C24/'1_Precios'!C23-1 -> 0 | D24: ='1_Precios'!D24/'1_Precios'!D23-1 -> 0 | E24: ='1_Precios'!E24/'1_Precios'!E23-1 -> 0 | F24: ='1_Precios'!F24/'1_Precios'!F23-1 -> 0 | G24: ='1_Precios'!G24/'1_Precios'!G23-1 -> 0
A25: ='1_Precios'!A25 -> 0 | B25: ='1_Precios'!B25/'1_Precios'!B24-1 -> 0 | C25: ='1_Precios'!C25/'1_Precios'!C24-1 -> 0 | D25: ='1_Precios'!D25/'1_Precios'!D24-1 -> 0 | E25: ='1_Precios'!E25/'1_Precios'!E24-1 -> 0 | F25: ='1_Precios'!F25/'1_Precios'!F24-1 -> 0 | G25: ='1_Precios'!G25/'1_Precios'!G24-1 -> 0
A26: ='1_Precios'!A26 -> 0 | B26: ='1_Precios'!B26/'1_Precios'!B25-1 -> 0 | C26: ='1_Precios'!C26/'1_Precios'!C25-1 -> 0 | D26: ='1_Precios'!D26/'1_Precios'!D25-1 -> 0 | E26: ='1_Precios'!E26/'1_Precios'!E25-1 -> 0 | F26: ='1_Precios'!F26/'1_Precios'!F25-1 -> 0 | G26: ='1_Precios'!G26/'1_Precios'!G25-1 -> 0
A27: ='1_Precios'!A27 -> 0 | B27: ='1_Precios'!B27/'1_Precios'!B26-1 -> 0 | C27: ='1_Precios'!C27/'1_Precios'!C26-1 -> 0 | D27: ='1_Precios'!D27/'1_Precios'!D26-1 -> 0 | E27: ='1_Precios'!E27/'1_Precios'!E26-1 -> 0 | F27: ='1_Precios'!F27/'1_Precios'!F26-1 -> 0 | G27: ='1_Precios'!G27/'1_Precios'!G26-1 -> 0
A28: ='1_Precios'!A28 -> 0 | B28: ='1_Precios'!B28/'1_Precios'!B27-1 -> 0 | C28: ='1_Precios'!C28/'1_Precios'!C27-1 -> 0 | D28: ='1_Precios'!D28/'1_Precios'!D27-1 -> 0 | E28: ='1_Precios'!E28/'1_Precios'!E27-1 -> 0 | F28: ='1_Precios'!F28/'1_Precios'!F27-1 -> 0 | G28: ='1_Precios'!G28/'1_Precios'!G27-1 -> 0
A29: ='1_Precios'!A29 -> 0 | B29: ='1_Precios'!B29/'1_Precios'!B28-1 -> 0 | C29: ='1_Precios'!C29/'1_Precios'!C28-1 -> 0 | D29: ='1_Precios'!D29/'1_Precios'!D28-1 -> 0 | E29: ='1_Precios'!E29/'1_Precios'!E28-1 -> 0 | F29: ='1_Precios'!F29/'1_Precios'!F28-1 -> 0 | G29: ='1_Precios'!G29/'1_Precios'!G28-1 -> 0
A30: ='1_Precios'!A30 -> 0 | B30: ='1_Precios'!B30/'1_Precios'!B29-1 -> 0 | C30: ='1_Precios'!C30/'1_Precios'!C29-1 -> 0 | D30: ='1_Precios'!D30/'1_Precios'!D29-1 -> 0 | E30: ='1_Precios'!E30/'1_Precios'!E29-1 -> 0 | F30: ='1_Precios'!F30/'1_Precios'!F29-1 -> 0 | G30: ='1_Precios'!G30/'1_Precios'!G29-1 -> 0
A31: ='1_Precios'!A31 -> 0 | B31: ='1_Precios'!B31/'1_Precios'!B30-1 -> 0 | C31: ='1_Precios'!C31/'1_Precios'!C30-1 -> 0 | D31: ='1_Precios'!D31/'1_Precios'!D30-1 -> 0 | E31: ='1_Precios'!E31/'1_Precios'!E30-1 -> 0 | F31: ='1_Precios'!F31/'1_Precios'!F30-1 -> 0 | G31: ='1_Precios'!G31/'1_Precios'!G30-1 -> 0
... A252: ='1_Precios'!A252 -> 0 | B252: ='1_Precios'!B252/'1_Precios'!B251-1 -> 0 | C252: ='1_Precios'!C252/'1_Precios'!C251-1 -> 0 | D252: ='1_Precios'!D252/'1_Precios'!D251-1 -> 0 | E252: ='1_Precios'!E252/'1_Precios'!E251-1 -> 0 | F252: ='1_Precios'!F252/'1_Precios'!F251-1 -> 0 | G252: ='1_Precios'!G252/'1_Precios'!G251-1 -> 0

Sheet 3_Cov_Correl
A1: Matriz de COVARIANZAS anualizadas (x252)
B3: BANCO | C3: RETAIL | D3: MINERA | E3: ENERGIA | F3: CONSUMO | G3: IPSA | I3: Interpretacion
A4: BANCO | B4: =_xlfn.COVARIANCE.S('2_Retornos'!B$2:B$252,'2_Retornos'!B$2:B$252)*'2_Retornos'!$J$3 -> 0 | C4: =_xlfn.COVARIANCE.S('2_Retornos'!B$2:B$252,'2_Retornos'!C$2:C$252)*'2_Retornos'!$J$3 -> 0 | D4: =_xlfn.COVARIANCE.S('2_Retornos'!B$2:B$252,'2_Retornos'!D$2:D$252)*'2_Retornos'!$J$3 -> 0 | E4: =_xlfn.COVARIANCE.S('2_Retornos'!B$2:B$252,'2_Retornos'!E$2:E$252)*'2_Retornos'!$J$3 -> 0 | F4: =_xlfn.COVARIANCE.S('2_Retornos'!B$2:B$252,'2_Retornos'!F$2:F$252)*'2_Retornos'!$J$3 -> 0 | G4: =_xlfn.COVARIANCE.S('2_Retornos'!B$2:B$252,'2_Retornos'!G$2:G$252)*'2_Retornos'!$J$3 -> 0 | I4: Correlacion +1: se mueven igual (no diversifica). 0: independientes. -1: cobertura perfecta.
A5: RETAIL | B5: =_xlfn.COVARIANCE.S('2_Retornos'!C$2:C$252,'2_Retornos'!B$2:B$252)*'2_Retornos'!$J$3 -> 0 | C5: =_xlfn.COVARIANCE.S('2_Retornos'!C$2:C$252,'2_Retornos'!C$2:C$252)*'2_Retornos'!$J$3 -> 0 | D5: =_xlfn.COVARIANCE.S('2_Retornos'!C$2:C$252,'2_Retornos'!D$2:D$252)*'2_Retornos'!$J$3 -> 0 | E5: =_xlfn.COVARIANCE.S('2_Retornos'!C$2:C$252,'2_Retornos'!E$2:E$252)*'2_Retornos'!$J$3 -> 0 | F5: =_xlfn.COVARIANCE.S('2_Retornos'!C$2:C$252,'2_Retornos'!F$2:F$252)*'2_Retornos'!$J$3 -> 0 | G5: =_xlfn.COVARIANCE.S('2_Retornos'!C$2:C$252,'2_Retornos'!G$2:G$252)*'2_Retornos'!$J$3 -> 0 | I5: En Chile las acciones suelen tener correlaciones positivas entre si (todas dependen del ciclo local, el cobre y el dolar).
A6: MINERA | B6: =_xlfn.COVARIANCE.S('2_Retornos'!D$2:D$252,'2_Retornos'!B$2:B$252)*'2_Retornos'!$J$3 -> 0 | C6: =_xlfn.COVARIANCE.S('2_Retornos'!D$2:D$252,'2_Retornos'!C$2:C$252)*'2_Retornos'!$J$3 -> 0 | D6: =_xlfn.COVARIANCE.S('2_Retornos'!D$2:D$252,'2_Retornos'!D$2:D$252)*'2_Retornos'!$J$3 -> 0 | E6: =_xlfn.COVARIANCE.S('2_Retornos'!D$2:D$252,'2_Retornos'!E$2:E$252)*'2_Retornos'!$J$3 -> 0 | F6: =_xlfn.COVARIANCE.S('2_Retornos'!D$2:D$252,'2_Retornos'!F$2:F$252)*'2_Retornos'!$J$3 -> 0 | G6: =_xlfn.COVARIANCE.S('2_Retornos'!D$2:D$252,'2_Retornos'!G$2:G$252)*'2_Retornos'!$J$3 -> 0 | I6: Combinar sectores con correlacion baja (ej. utilities vs mineria) reduce el riesgo de la cartera sin sacrificar retorno esperado.
A7: ENERGIA | B7: =_xlfn.COVARIANCE.S('2_Retornos'!E$2:E$252,'2_Retornos'!B$2:B$252)*'2_Retornos'!$J$3 -> 0 | C7: =_xlfn.COVARIANCE.S('2_Retornos'!E$2:E$252,'2_Retornos'!C$2:C$252)*'2_Retornos'!$J$3 -> 0 | D7: =_xlfn.COVARIANCE.S('2_Retornos'!E$2:E$252,'2_Retornos'!D$2:D$252)*'2_Retornos'!$J$3 -> 0 | E7: =_xlfn.COVARIANCE.S('2_Retornos'!E$2:E$252,'2_Retornos'!E$2:E$252)*'2_Retornos'!$J$3 -> 0 | F7: =_xlfn.COVARIANCE.S('2_Retornos'!E$2:E$252,'2_Retornos'!F$2:F$252)*'2_Retornos'!$J$3 -> 0 | G7: =_xlfn.COVARIANCE.S('2_Retornos'!E$2:E$252,'2_Retornos'!G$2:G$252)*'2_Retornos'!$J$3 -> 0 | I7: Diagonal de la covarianza = varianza de cada activo (volatilidad^2).
A8: CONSUMO | B8: =_xlfn.COVARIANCE.S('2_Retornos'!F$2:F$252,'2_Retornos'!B$2:B$252)*'2_Retornos'!$J$3 -> 0 | C8: =_xlfn.COVARIANCE.S('2_Retornos'!F$2:F$252,'2_Retornos'!C$2:C$252)*'2_Retornos'!$J$3 -> 0 | D8: =_xlfn.COVARIANCE.S('2_Retornos'!F$2:F$252,'2_Retornos'!D$2:D$252)*'2_Retornos'!$J$3 -> 0 | E8: =_xlfn.COVARIANCE.S('2_Retornos'!F$2:F$252,'2_Retornos'!E$2:E$252)*'2_Retornos'!$J$3 -> 0 | F8: =_xlfn.COVARIANCE.S('2_Retornos'!F$2:F$252,'2_Retornos'!F$2:F$252)*'2_Retornos'!$J$3 -> 0 | G8: =_xlfn.COVARIANCE.S('2_Retornos'!F$2:F$252,'2_Retornos'!G$2:G$252)*'2_Retornos'!$J$3 -> 0 | I8: Ojo: las correlaciones cambian en crisis (tienden a subir hacia 1 justo cuando mas necesitas diversificar).
A9: IPSA | B9: =_xlfn.COVARIANCE.S('2_Retornos'!G$2:G$252,'2_Retornos'!B$2:B$252)*'2_Retornos'!$J$3 -> 0 | C9: =_xlfn.COVARIANCE.S('2_Retornos'!G$2:G$252,'2_Retornos'!C$2:C$252)*'2_Retornos'!$J$3 -> 0 | D9: =_xlfn.COVARIANCE.S('2_Retornos'!G$2:G$252,'2_Retornos'!D$2:D$252)*'2_Retornos'!$J$3 -> 0 | E9: =_xlfn.COVARIANCE.S('2_Retornos'!G$2:G$252,'2_Retornos'!E$2:E$252)*'2_Retornos'!$J$3 -> 0 | F9: =_xlfn.COVARIANCE.S('2_Retornos'!G$2:G$252,'2_Retornos'!F$2:F$252)*'2_Retornos'!$J$3 -> 0 | G9: =_xlfn.COVARIANCE.S('2_Retornos'!G$2:G$252,'2_Retornos'!G$2:G$252)*'2_Retornos'!$J$3 -> 0
A11: Matriz de CORRELACIONES
B13: BANCO | C13: RETAIL | D13: MINERA | E13: ENERGIA | F13: CONSUMO | G13: IPSA
A14: BANCO | B14: =CORREL('2_Retornos'!B$2:B$252,'2_Retornos'!B$2:B$252) -> 0 | C14: =CORREL('2_Retornos'!B$2:B$252,'2_Retornos'!C$2:C$252) -> 0 | D14: =CORREL('2_Retornos'!B$2:B$252,'2_Retornos'!D$2:D$252) -> 0 | E14: =CORREL('2_Retornos'!B$2:B$252,'2_Retornos'!E$2:E$252) -> 0 | F14: =CORREL('2_Retornos'!B$2:B$252,'2_Retornos'!F$2:F$252) -> 0 | G14: =CORREL('2_Retornos'!B$2:B$252,'2_Retornos'!G$2:G$252) -> 0
A15: RETAIL | B15: =CORREL('2_Retornos'!C$2:C$252,'2_Retornos'!B$2:B$252) -> 0 | C15: =CORREL('2_Retornos'!C$2:C$252,'2_Retornos'!C$2:C$252) -> 0 | D15: =CORREL('2_Retornos'!C$2:C$252,'2_Retornos'!D$2:D$252) -> 0 | E15: =CORREL('2_Retornos'!C$2:C$252,'2_Retornos'!E$2:E$252) -> 0 | F15: =CORREL('2_Retornos'!C$2:C$252,'2_Retornos'!F$2:F$252) -> 0 | G15: =CORREL('2_Retornos'!C$2:C$252,'2_Retornos'!G$2:G$252) -> 0
A16: MINERA | B16: =CORREL('2_Retornos'!D$2:D$252,'2_Retornos'!B$2:B$252) -> 0 | C16: =CORREL('2_Retornos'!D$2:D$252,'2_Retornos'!C$2:C$252) -> 0 | D16: =CORREL('2_Retornos'!D$2:D$252,'2_Retornos'!D$2:D$252) -> 0 | E16: =CORREL('2_Retornos'!D$2:D$252,'2_Retornos'!E$2:E$252) -> 0 | F16: =CORREL('2_Retornos'!D$2:D$252,'2_Retornos'!F$2:F$252) -> 0 | G16: =CORREL('2_Retornos'!D$2:D$252,'2_Retornos'!G$2:G$252) -> 0
A17: ENERGIA | B17: =CORREL('2_Retornos'!E$2:E$252,'2_Retornos'!B$2:B$252) -> 0 | C17: =CORREL('2_Retornos'!E$2:E$252,'2_Retornos'!C$2:C$252) -> 0 | D17: =CORREL('2_Retornos'!E$2:E$252,'2_Retornos'!D$2:D$252) -> 0 | E17: =CORREL('2_Retornos'!E$2:E$252,'2_Retornos'!E$2:E$252) -> 0 | F17: =CORREL('2_Retornos'!E$2:E$252,'2_Retornos'!F$2:F$252) -> 0 | G17: =CORREL('2_Retornos'!E$2:E$252,'2_Retornos'!G$2:G$252) -> 0
A18: CONSUMO | B18: =CORREL('2_Retornos'!F$2:F$252,'2_Retornos'!B$2:B$252) -> 0 | C18: =CORREL('2_Retornos'!F$2:F$252,'2_Retornos'!C$2:C$252) -> 0 | D18: =CORREL('2_Retornos'!F$2:F$252,'2_Retornos'!D$2:D$252) -> 0 | E18: =CORREL('2_Retornos'!F$2:F$252,'2_Retornos'!E$2:E$252) -> 0 | F18: =CORREL('2_Retornos'!F$2:F$252,'2_Retornos'!F$2:F$252) -> 0 | G18: =CORREL('2_Retornos'!F$2:F$252,'2_Retornos'!G$2:G$252) -> 0
A19: IPSA | B19: =CORREL('2_Retornos'!G$2:G$252,'2_Retornos'!B$2:B$252) -> 0 | C19: =CORREL('2_Retornos'!G$2:G$252,'2_Retornos'!C$2:C$252) -> 0 | D19: =CORREL('2_Retornos'!G$2:G$252,'2_Retornos'!D$2:D$252) -> 0 | E19: =CORREL('2_Retornos'!G$2:G$252,'2_Retornos'!E$2:E$252) -> 0 | F19: =CORREL('2_Retornos'!G$2:G$252,'2_Retornos'!F$2:F$252) -> 0 | G19: =CORREL('2_Retornos'!G$2:G$252,'2_Retornos'!G$2:G$252) -> 0

Sheet 4_Frontera_2A
A1: Frontera eficiente con 2 activos
A2: Cambia las celdas amarillas (sobre todo la correlacion) y observa el grafico.
A4: Retorno esperado activo 1 (E1) | B4: ='2_Retornos'!L7 -> 0 | C4: =MINERA (editable) -> 0
A5: Retorno esperado activo 2 (E2) | B5: ='2_Retornos'!M7 -> 0 | C5: =ENERGIA (editable) -> 0
A6: Volatilidad activo 1 (s1) | B6: ='2_Retornos'!L9 -> 0
A7: Volatilidad activo 2 (s2) | B7: ='2_Retornos'!M9 -> 0
A8: Correlacion (rho) | B8: ='3_Cov_Correl'!E16 -> 0 | C8: Prueba con -1, 0, 0,5 y 1
A10: Peso optimo minima varianza en activo 1 (w1*) | B10: =(B7^2-B8*B6*B7)/(B6^2+B7^2-2*B8*B6*B7) -> 0 | C10: w1* = (s2^2 - rho*s1*s2) / (s1^2 + s2^2 - 2*rho*s1*s2)
A11: Retorno de la cartera de minima varianza | B11: =B10*B4+(1-B10)*B5 -> 0
A12: Volatilidad de la cartera de minima varianza | B12: =SQRT(B10^2*B6^2+(1-B10)^2*B7^2+2*B10*(1-B10)*B8*B6*B7) -> 0
A15: w1 (activo 1) | B15: w2 (activo 2) | C15: Retorno E(Rp) | D15: Volatilidad sp | E15: Sharpe
A16: 0 | B16: =1-A16 -> 0 | C16: =A16*$B$4+B16*$B$5 -> 0 | D16: =SQRT(A16^2*$B$6^2+B16^2*$B$7^2+2*A16*B16*$B$8*$B$6*$B$7) -> 0 | E16: =(C16-'2_Retornos'!$J$2)/D16 -> 0
A17: 0.05 | B17: =1-A17 -> 0 | C17: =A17*$B$4+B17*$B$5 -> 0 | D17: =SQRT(A17^2*$B$6^2+B17^2*$B$7^2+2*A17*B17*$B$8*$B$6*$B$7) -> 0 | E17: =(C17-'2_Retornos'!$J$2)/D17 -> 0
A18: 0.1 | B18: =1-A18 -> 0 | C18: =A18*$B$4+B18*$B$5 -> 0 | D18: =SQRT(A18^2*$B$6^2+B18^2*$B$7^2+2*A18*B18*$B$8*$B$6*$B$7) -> 0 | E18: =(C18-'2_Retornos'!$J$2)/D18 -> 0
A19: 0.15 | B19: =1-A19 -> 0 | C19: =A19*$B$4+B19*$B$5 -> 0 | D19: =SQRT(A19^2*$B$6^2+B19^2*$B$7^2+2*A19*B19*$B$8*$B$6*$B$7) -> 0 | E19: =(C19-'2_Retornos'!$J$2)/D19 -> 0
A20: 0.2 | B20: =1-A20 -> 0 | C20: =A20*$B$4+B20*$B$5 -> 0 | D20: =SQRT(A20^2*$B$6^2+B20^2*$B$7^2+2*A20*B20*$B$8*$B$6*$B$7) -> 0 | E20: =(C20-'2_Retornos'!$J$2)/D20 -> 0
A21: 0.25 | B21: =1-A21 -> 0 | C21: =A21*$B$4+B21*$B$5 -> 0 | D21: =SQRT(A21^2*$B$6^2+B21^2*$B$7^2+2*A21*B21*$B$8*$B$6*$B$7) -> 0 | E21: =(C21-'2_Retornos'!$J$2)/D21 -> 0
A22: 0.3 | B22: =1-A22 -> 0 | C22: =A22*$B$4+B22*$B$5 -> 0 | D22: =SQRT(A22^2*$B$6^2+B22^2*$B$7^2+2*A22*B22*$B$8*$B$6*$B$7) -> 0 | E22: =(C22-'2_Retornos'!$J$2)/D22 -> 0
A23: 0.35 | B23: =1-A23 -> 0 | C23: =A23*$B$4+B23*$B$5 -> 0 | D23: =SQRT(A23^2*$B$6^2+B23^2*$B$7^2+2*A23*B23*$B$8*$B$6*$B$7) -> 0 | E23: =(C23-'2_Retornos'!$J$2)/D23 -> 0
A24: 0.4 | B24: =1-A24 -> 0 | C24: =A24*$B$4+B24*$B$5 -> 0 | D24: =SQRT(A24^2*$B$6^2+B24^2*$B$7^2+2*A24*B24*$B$8*$B$6*$B$7) -> 0 | E24: =(C24-'2_Retornos'!$J$2)/D24 -> 0
A25: 0.45 | B25: =1-A25 -> 0 | C25: =A25*$B$4+B25*$B$5 -> 0 | D25: =SQRT(A25^2*$B$6^2+B25^2*$B$7^2+2*A25*B25*$B$8*$B$6*$B$7) -> 0 | E25: =(C25-'2_Retornos'!$J$2)/D25 -> 0
A26: 0.5 | B26: =1-A26 -> 0 | C26: =A26*$B$4+B26*$B$5 -> 0 | D26: =SQRT(A26^2*$B$6^2+B26^2*$B$7^2+2*A26*B26*$B$8*$B$6*$B$7) -> 0 | E26: =(C26-'2_Retornos'!$J$2)/D26 -> 0 | G26: La parte de la curva SOBRE el punto rojo es la frontera eficiente: mas retorno para cada nivel de riesgo.
A27: 0.55 | B27: =1-A27 -> 0 | C27: =A27*$B$4+B27*$B$5 -> 0 | D27: =SQRT(A27^2*$B$6^2+B27^2*$B$7^2+2*A27*B27*$B$8*$B$6*$B$7) -> 0 | E27: =(C27-'2_Retornos'!$J$2)/D27 -> 0
A28: 0.6 | B28: =1-A28 -> 0 | C28: =A28*$B$4+B28*$B$5 -> 0 | D28: =SQRT(A28^2*$B$6^2+B28^2*$B$7^2+2*A28*B28*$B$8*$B$6*$B$7) -> 0 | E28: =(C28-'2_Retornos'!$J$2)/D28 -> 0
A29: 0.65 | B29: =1-A29 -> 0 | C29: =A29*$B$4+B29*$B$5 -> 0 | D29: =SQRT(A29^2*$B$6^2+B29^2*$B$7^2+2*A29*B29*$B$8*$B$6*$B$7) -> 0 | E29: =(C29-'2_Retornos'!$J$2)/D29 -> 0
A30: 0.7 | B30: =1-A30 -> 0 | C30: =A30*$B$4+B30*$B$5 -> 0 | D30: =SQRT(A30^2*$B$6^2+B30^2*$B$7^2+2*A30*B30*$B$8*$B$6*$B$7) -> 0 | E30: =(C30-'2_Retornos'!$J$2)/D30 -> 0
A31: 0.75 | B31: =1-A31 -> 0 | C31: =A31*$B$4+B31*$B$5 -> 0 | D31: =SQRT(A31^2*$B$6^2+B31^2*$B$7^2+2*A31*B31*$B$8*$B$6*$B$7) -> 0 | E31: =(C31-'2_Retornos'!$J$2)/D31 -> 0
A32: 0.8 | B32: =1-A32 -> 0 | C32: =A32*$B$4+B32*$B$5 -> 0 | D32: =SQRT(A32^2*$B$6^2+B32^2*$B$7^2+2*A32*B32*$B$8*$B$6*$B$7) -> 0 | E32: =(C32-'2_Retornos'!$J$2)/D32 -> 0
A33: 0.85 | B33: =1-A33 -> 0 | C33: =A33*$B$4+B33*$B$5 -> 0 | D33: =SQRT(A33^2*$B$6^2+B33^2*$B$7^2+2*A33*B33*$B$8*$B$6*$B$7) -> 0 | E33: =(C33-'2_Retornos'!$J$2)/D33 -> 0
A34: 0.9 | B34: =1-A34 -> 0 | C34: =A34*$B$4+B34*$B$5 -> 0 | D34: =SQRT(A34^2*$B$6^2+B34^2*$B$7^2+2*A34*B34*$B$8*$B$6*$B$7) -> 0 | E34: =(C34-'2_Retornos'!$J$2)/D34 -> 0
A35: 0.95 | B35: =1-A35 -> 0 | C35: =A35*$B$4+B35*$B$5 -> 0 | D35: =SQRT(A35^2*$B$6^2+B35^2*$B$7^2+2*A35*B35*$B$8*$B$6*$B$7) -> 0 | E35: =(C35-'2_Retornos'!$J$2)/D35 -> 0
A36: 1 | B36: =1-A36 -> 0 | C36: =A36*$B$4+B36*$B$5 -> 0 | D36: =SQRT(A36^2*$B$6^2+B36^2*$B$7^2+2*A36*B36*$B$8*$B$6*$B$7) -> 0 | E36: =(C36-'2_Retornos'!$J$2)/D36 -> 0

Sheet 5_Cartera
A1: Mi cartera de N acciones
A2: Ingresa los pesos (deben sumar 100%). Luego usa Solver para maximizar el Sharpe (ver instrucciones abajo). | I2: Fecha | J2: Ret. cartera | K2: Ret. IPSA | L2: Diferencia | M2: Indice cartera | N2: Drawdown | O2: Indice IPSA
I3: ='2_Retornos'!A2 -> 0 | J3: =SUMPRODUCT($B$5:$F$5,'2_Retornos'!B2:F2) -> 0 | K3: ='2_Retornos'!G2 -> 0 | L3: =J3-K3 -> 0 | M3: =100*(1+J3) -> 0 | N3: =M3/MAX($M$3:M3)-1 -> 0 | O3: =100*(1+K3) -> 0
B4: BANCO | C4: RETAIL | D4: MINERA | E4: ENERGIA | F4: CONSUMO | G4: SUMA | I4: ='2_Retornos'!A3 -> 0 | J4: =SUMPRODUCT($B$5:$F$5,'2_Retornos'!B3:F3) -> 0 | K4: ='2_Retornos'!G3 -> 0 | L4: =J4-K4 -> 0 | M4: =M3*(1+J4) -> 0 | N4: =M4/MAX($M$3:M4)-1 -> 0 | O4: =O3*(1+K4) -> 0
A5: Peso (w) | B5: 0.2 | C5: 0.2 | D5: 0.2 | E5: 0.2 | F5: 0.2 | G5: =SUM(B5:F5) -> 0 | H5: =IF(ROUND(G5,4)<>1,"LOS PESOS NO SUMAN 100%","OK") -> 0 | I5: ='2_Retornos'!A4 -> 0 | J5: =SUMPRODUCT($B$5:$F$5,'2_Retornos'!B4:F4) -> 0 | K5: ='2_Retornos'!G4 -> 0 | L5: =J5-K5 -> 0 | M5: =M4*(1+J5) -> 0 | N5: =M5/MAX($M$3:M5)-1 -> 0 | O5: =O4*(1+K5) -> 0
A6: Retorno anual del activo | B6: ='2_Retornos'!J7 -> 0 | C6: ='2_Retornos'!K7 -> 0 | D6: ='2_Retornos'!L7 -> 0 | E6: ='2_Retornos'!M7 -> 0 | F6: ='2_Retornos'!N7 -> 0 | I6: ='2_Retornos'!A5 -> 0 | J6: =SUMPRODUCT($B$5:$F$5,'2_Retornos'!B5:F5) -> 0 | K6: ='2_Retornos'!G5 -> 0 | L6: =J6-K6 -> 0 | M6: =M5*(1+J6) -> 0 | N6: =M6/MAX($M$3:M6)-1 -> 0 | O6: =O5*(1+K6) -> 0
A7: Volatilidad anual del activo | B7: ='2_Retornos'!J9 -> 0 | C7: ='2_Retornos'!K9 -> 0 | D7: ='2_Retornos'!L9 -> 0 | E7: ='2_Retornos'!M9 -> 0 | F7: ='2_Retornos'!N9 -> 0 | I7: ='2_Retornos'!A6 -> 0 | J7: =SUMPRODUCT($B$5:$F$5,'2_Retornos'!B6:F6) -> 0 | K7: ='2_Retornos'!G6 -> 0 | L7: =J7-K7 -> 0 | M7: =M6*(1+J7) -> 0 | N7: =M7/MAX($M$3:M7)-1 -> 0 | O7: =O6*(1+K7) -> 0
I8: ='2_Retornos'!A7 -> 0 | J8: =SUMPRODUCT($B$5:$F$5,'2_Retornos'!B7:F7) -> 0 | K8: ='2_Retornos'!G7 -> 0 | L8: =J8-K8 -> 0 | M8: =M7*(1+J8) -> 0 | N8: =M8/MAX($M$3:M8)-1 -> 0 | O8: =O7*(1+K8) -> 0
A9: Retorno anual de la cartera | B9: =(1+AVERAGE(J3:J253))^'2_Retornos'!$J$3-1 -> 0 | I9: ='2_Retornos'!A8 -> 0 | J9: =SUMPRODUCT($B$5:$F$5,'2_Retornos'!B8:F8) -> 0 | K9: ='2_Retornos'!G8 -> 0 | L9: =J9-K9 -> 0 | M9: =M8*(1+J9) -> 0 | N9: =M9/MAX($M$3:M9)-1 -> 0 | O9: =O8*(1+K9) -> 0
A10: Volatilidad anual de la cartera | B10: =_xlfn.STDEV.S(J3:J253)*SQRT('2_Retornos'!$J$3) -> 0 | I10: ='2_Retornos'!A9 -> 0 | J10: =SUMPRODUCT($B$5:$F$5,'2_Retornos'!B9:F9) -> 0 | K10: ='2_Retornos'!G9 -> 0 | L10: =J10-K10 -> 0 | M10: =M9*(1+J10) -> 0 | N10: =M10/MAX($M$3:M10)-1 -> 0 | O10: =O9*(1+K10) -> 0
A11: Ratio de Sharpe | B11: =(B9-'2_Retornos'!$J$2)/B10 -> 0 | C11: Retorno extra por unidad de riesgo total | I11: ='2_Retornos'!A10 -> 0 | J11: =SUMPRODUCT($B$5:$F$5,'2_Retornos'!B10:F10) -> 0 | K11: ='2_Retornos'!G10 -> 0 | L11: =J11-K11 -> 0 | M11: =M10*(1+J11) -> 0 | N11: =M11/MAX($M$3:M11)-1 -> 0 | O11: =O10*(1+K11) -> 0
A12: Beta de la cartera vs IPSA | B12: =SLOPE(J3:J253,K3:K253) -> 0 | C12: >1 mas agresiva que el mercado; <1 mas defensiva | I12: ='2_Retornos'!A11 -> 0 | J12: =SUMPRODUCT($B$5:$F$5,'2_Retornos'!B11:F11) -> 0 | K12: ='2_Retornos'!G11 -> 0 | L12: =J12-K12 -> 0 | M12: =M11*(1+J12) -> 0 | N12: =M12/MAX($M$3:M12)-1 -> 0 | O12: =O11*(1+K12) -> 0
A13: Ratio de Treynor | B13: =(B9-'2_Retornos'!$J$2)/B12 -> 0 | I13: ='2_Retornos'!A12 -> 0 | J13: =SUMPRODUCT($B$5:$F$5,'2_Retornos'!B12:F12) -> 0 | K13: ='2_Retornos'!G12 -> 0 | L13: =J13-K13 -> 0 | M13: =M12*(1+J13) -> 0 | N13: =M13/MAX($M$3:M13)-1 -> 0 | O13: =O12*(1+K13) -> 0
A14: Retorno anual IPSA | B14: ='2_Retornos'!O7 -> 0 | I14: ='2_Retornos'!A13 -> 0 | J14: =SUMPRODUCT($B$5:$F$5,'2_Retornos'!B13:F13) -> 0 | K14: ='2_Retornos'!G13 -> 0 | L14: =J14-K14 -> 0 | M14: =M13*(1+J14) -> 0 | N14: =M14/MAX($M$3:M14)-1 -> 0 | O14: =O13*(1+K14) -> 0
A15: Alfa de Jensen (anual) | B15: =B9-('2_Retornos'!$J$2+B12*(B14-'2_Retornos'!$J$2)) -> 0 | C15: Retorno sobre lo que exige el CAPM dado su beta | I15: ='2_Retornos'!A14 -> 0 | J15: =SUMPRODUCT($B$5:$F$5,'2_Retornos'!B14:F14) -> 0 | K15: ='2_Retornos'!G14 -> 0 | L15: =J15-K15 -> 0 | M15: =M14*(1+J15) -> 0 | N15: =M15/MAX($M$3:M15)-1 -> 0 | O15: =O14*(1+K15) -> 0
A16: Tracking error vs IPSA | B16: =_xlfn.STDEV.S(L3:L253)*SQRT('2_Retornos'!$J$3) -> 0 | I16: ='2_Retornos'!A15 -> 0 | J16: =SUMPRODUCT($B$5:$F$5,'2_Retornos'!B15:F15) -> 0 | K16: ='2_Retornos'!G15 -> 0 | L16: =J16-K16 -> 0 | M16: =M15*(1+J16) -> 0 | N16: =M16/MAX($M$3:M16)-1 -> 0 | O16: =O15*(1+K16) -> 0
A17: Information ratio | B17: =(B9-B14)/B16 -> 0 | I17: ='2_Retornos'!A16 -> 0 | J17: =SUMPRODUCT($B$5:$F$5,'2_Retornos'!B16:F16) -> 0 | K17: ='2_Retornos'!G16 -> 0 | L17: =J17-K17 -> 0 | M17: =M16*(1+J17) -> 0 | N17: =M17/MAX($M$3:M17)-1 -> 0 | O17: =O16*(1+K17) -> 0
A18: Volatilidad promedio ponderada (sin diversificar) | B18: =SUMPRODUCT(B5:F5,B7:F7) -> 0 | I18: ='2_Retornos'!A17 -> 0 | J18: =SUMPRODUCT($B$5:$F$5,'2_Retornos'!B17:F17) -> 0 | K18: ='2_Retornos'!G17 -> 0 | L18: =J18-K18 -> 0 | M18: =M17*(1+J18) -> 0 | N18: =M18/MAX($M$3:M18)-1 -> 0 | O18: =O17*(1+K18) -> 0
A19: Reduccion de riesgo por diversificacion | B19: =1-B10/B18 -> 0 | C19: Cuanto riesgo "gratis" eliminaste combinando acciones | I19: ='2_Retornos'!A18 -> 0 | J19: =SUMPRODUCT($B$5:$F$5,'2_Retornos'!B18:F18) -> 0 | K19: ='2_Retornos'!G18 -> 0 | L19: =J19-K19 -> 0 | M19: =M18*(1+J19) -> 0 | N19: =M19/MAX($M$3:M19)-1 -> 0 | O19: =O18*(1+K19) -> 0
A20: Max. drawdown de la cartera | B20: =MIN(N3:N253) -> 0 | I20: ='2_Retornos'!A19 -> 0 | J20: =SUMPRODUCT($B$5:$F$5,'2_Retornos'!B19:F19) -> 0 | K20: ='2_Retornos'!G19 -> 0 | L20: =J20-K20 -> 0 | M20: =M19*(1+J20) -> 0 | N20: =M20/MAX($M$3:M20)-1 -> 0 | O20: =O19*(1+K20) -> 0
I21: ='2_Retornos'!A20 -> 0 | J21: =SUMPRODUCT($B$5:$F$5,'2_Retornos'!B20:F20) -> 0 | K21: ='2_Retornos'!G20 -> 0 | L21: =J21-K21 -> 0 | M21: =M20*(1+J21) -> 0 | N21: =M21/MAX($M$3:M21)-1 -> 0 | O21: =O20*(1+K21) -> 0
A22: SOLVER (Datos > Solver; si no aparece: Archivo > Opciones > Complementos > Solver): | I22: ='2_Retornos'!A21 -> 0 | J22: =SUMPRODUCT($B$5:$F$5,'2_Retornos'!B21:F21) -> 0 | K22: ='2_Retornos'!G21 -> 0 | L22: =J22-K22 -> 0 | M22: =M21*(1+J22) -> 0 | N22: =M22/MAX($M$3:M22)-1 -> 0 | O22: =O21*(1+K22) -> 0
A23: Establecer objetivo: $B$11 (Sharpe) -> Max | I23: ='2_Retornos'!A22 -> 0 | J23: =SUMPRODUCT($B$5:$F$5,'2_Retornos'!B22:F22) -> 0 | K23: ='2_Retornos'!G22 -> 0 | L23: =J23-K23 -> 0 | M23: =M22*(1+J23) -> 0 | N23: =M23/MAX($M$3:M23)-1 -> 0 | O23: =O22*(1+K23) -> 0
A24: Cambiando las celdas: $B$5:$F$5 | I24: ='2_Retornos'!A23 -> 0 | J24: =SUMPRODUCT($B$5:$F$5,'2_Retornos'!B23:F23) -> 0 | K24: ='2_Retornos'!G23 -> 0 | L24: =J24-K24 -> 0 | M24: =M23*(1+J24) -> 0 | N24: =M24/MAX($M$3:M24)-1 -> 0 | O24: =O23*(1+K24) -> 0
A25: Restricciones: $G$5 = 1 y $B$5:$F$5 >= 0 (sin ventas cortas). Opcional: $B$5:$F$5 <= 0,35 (limite por accion) | I25: ='2_Retornos'!A24 -> 0 | J25: =SUMPRODUCT($B$5:$F$5,'2_Retornos'!B24:F24) -> 0 | K25: ='2_Retornos'!G24 -> 0 | L25: =J25-K25 -> 0 | M25: =M24*(1+J25) -> 0 | N25: =M25/MAX($M$3:M25)-1 -> 0 | O25: =O24*(1+K25) -> 0
A26: Metodo: GRG Nonlinear. Repite con objetivo $B$10 -> Min para la cartera de minima varianza. | I26: ='2_Retornos'!A25 -> 0 | J26: =SUMPRODUCT($B$5:$F$5,'2_Retornos'!B25:F25) -> 0 | K26: ='2_Retornos'!G25 -> 0 | L26: =J26-K26 -> 0 | M26: =M25*(1+J26) -> 0 | N26: =M26/MAX($M$3:M26)-1 -> 0 | O26: =O25*(1+K26) -> 0
I27: ='2_Retornos'!A26 -> 0 | J27: =SUMPRODUCT($B$5:$F$5,'2_Retornos'!B26:F26) -> 0 | K27: ='2_Retornos'!G26 -> 0 | L27: =J27-K27 -> 0 | M27: =M26*(1+J27) -> 0 | N27: =M27/MAX($M$3:M27)-1 -> 0 | O27: =O26*(1+K27) -> 0
I28: ='2_Retornos'!A27 -> 0 | J28: =SUMPRODUCT($B$5:$F$5,'2_Retornos'!B27:F27) -> 0 | K28: ='2_Retornos'!G27 -> 0 | L28: =J28-K28 -> 0 | M28: =M27*(1+J28) -> 0 | N28: =M28/MAX($M$3:M28)-1 -> 0 | O28: =O27*(1+K28) -> 0
I29: ='2_Retornos'!A28 -> 0 | J29: =SUMPRODUCT($B$5:$F$5,'2_Retornos'!B28:F28) -> 0 | K29: ='2_Retornos'!G28 -> 0 | L29: =J29-K29 -> 0 | M29: =M28*(1+J29) -> 0 | N29: =M29/MAX($M$3:M29)-1 -> 0 | O29: =O28*(1+K29) -> 0
I30: ='2_Retornos'!A29 -> 0 | J30: =SUMPRODUCT($B$5:$F$5,'2_Retornos'!B29:F29) -> 0 | K30: ='2_Retornos'!G29 -> 0 | L30: =J30-K30 -> 0 | M30: =M29*(1+J30) -> 0 | N30: =M30/MAX($M$3:M30)-1 -> 0 | O30: =O29*(1+K30) -> 0
I31: ='2_Retornos'!A30 -> 0 | J31: =SUMPRODUCT($B$5:$F$5,'2_Retornos'!B30:F30) -> 0 | K31: ='2_Retornos'!G30 -> 0 | L31: =J31-K31 -> 0 | M31: =M30*(1+J31) -> 0 | N31: =M31/MAX($M$3:M31)-1 -> 0 | O31: =O30*(1+K31) -> 0
I32: ='2_Retornos'!A31 -> 0 | J32: =SUMPRODUCT($B$5:$F$5,'2_Retornos'!B31:F31) -> 0 | K32: ='2_Retornos'!G31 -> 0 | L32: =J32-K32 -> 0 | M32: =M31*(1+J32) -> 0 | N32: =M32/MAX($M$3:M32)-1 -> 0 | O32: =O31*(1+K32) -> 0
I33: ='2_Retornos'!A32 -> 0 | J33: =SUMPRODUCT($B$5:$F$5,'2_Retornos'!B32:F32) -> 0 | K33: ='2_Retornos'!G32 -> 0 | L33: =J33-K33 -> 0 | M33: =M32*(1+J33) -> 0 | N33: =M33/MAX($M$3:M33)-1 -> 0 | O33: =O32*(1+K33) -> 0
I34: ='2_Retornos'!A33 -> 0 | J34: =SUMPRODUCT($B$5:$F$5,'2_Retornos'!B33:F33) -> 0 | K34: ='2_Retornos'!G33 -> 0 | L34: =J34-K34 -> 0 | M34: =M33*(1+J34) -> 0 | N34: =M34/MAX($M$3:M34)-1 -> 0 | O34: =O33*(1+K34) -> 0
I35: ='2_Retornos'!A34 -> 0 | J35: =SUMPRODUCT($B$5:$F$5,'2_Retornos'!B34:F34) -> 0 | K35: ='2_Retornos'!G34 -> 0 | L35: =J35-K35 -> 0 | M35: =M34*(1+J35) -> 0 | N35: =M35/MAX($M$3:M35)-1 -> 0 | O35: =O34*(1+K35) -> 0
I36: ='2_Retornos'!A35 -> 0 | J36: =SUMPRODUCT($B$5:$F$5,'2_Retornos'!B35:F35) -> 0 | K36: ='2_Retornos'!G35 -> 0 | L36: =J36-K36 -> 0 | M36: =M35*(1+J36) -> 0 | N36: =M36/MAX($M$3:M36)-1 -> 0 | O36: =O35*(1+K36) -> 0
I37: ='2_Retornos'!A36 -> 0 | J37: =SUMPRODUCT($B$5:$F$5,'2_Retornos'!B36:F36) -> 0 | K37: ='2_Retornos'!G36 -> 0 | L37: =J37-K37 -> 0 | M37: =M36*(1+J37) -> 0 | N37: =M37/MAX($M$3:M37)-1 -> 0 | O37: =O36*(1+K37) -> 0
I38: ='2_Retornos'!A37 -> 0 | J38: =SUMPRODUCT($B$5:$F$5,'2_Retornos'!B37:F37) -> 0 | K38: ='2_Retornos'!G37 -> 0 | L38: =J38-K38 -> 0 | M38: =M37*(1+J38) -> 0 | N38: =M38/MAX($M$3:M38)-1 -> 0 | O38: =O37*(1+K38) -> 0
... I253: ='2_Retornos'!A252 -> 0 | J253: =SUMPRODUCT($B$5:$F$5,'2_Retornos'!B252:F252) -> 0 | K253: ='2_Retornos'!G252 -> 0 | L253: =J253-K253 -> 0 | M253: =M252*(1+J253) -> 0 | N253: =M253/MAX($M$3:M253)-1 -> 0 | O253: =O252*(1+K253) -> 0

Sheet 6_Beta_CAPM
A1: Beta y CAPM
A3: Tasa libre de riesgo anual (rf) | B3: ='2_Retornos'!J2 -> 0
A4: Prima por riesgo de mercado (ERP) | B4: 0.0533 | C4: Ej.: prima total Chile Damodaran ene-2026 (verificar). Editable.
A7: Metrica | B7: BANCO | C7: RETAIL | D7: MINERA | E7: ENERGIA | F7: CONSUMO
A8: Beta (pendiente vs IPSA) | B8: =SLOPE('2_Retornos'!B$2:B$252,'2_Retornos'!$G$2:$G$252) -> 0 | C8: =SLOPE('2_Retornos'!C$2:C$252,'2_Retornos'!$G$2:$G$252) -> 0 | D8: =SLOPE('2_Retornos'!D$2:D$252,'2_Retornos'!$G$2:$G$252) -> 0 | E8: =SLOPE('2_Retornos'!E$2:E$252,'2_Retornos'!$G$2:$G$252) -> 0 | F8: =SLOPE('2_Retornos'!F$2:F$252,'2_Retornos'!$G$2:$G$252) -> 0
A9: R2 (riesgo explicado por el mercado) | B9: =RSQ('2_Retornos'!B$2:B$252,'2_Retornos'!$G$2:$G$252) -> 0 | C9: =RSQ('2_Retornos'!C$2:C$252,'2_Retornos'!$G$2:$G$252) -> 0 | D9: =RSQ('2_Retornos'!D$2:D$252,'2_Retornos'!$G$2:$G$252) -> 0 | E9: =RSQ('2_Retornos'!E$2:E$252,'2_Retornos'!$G$2:$G$252) -> 0 | F9: =RSQ('2_Retornos'!F$2:F$252,'2_Retornos'!$G$2:$G$252) -> 0
A10: Riesgo idiosincratico (1 - R2) | B10: =1-B9 -> 0 | C10: =1-C9 -> 0 | D10: =1-D9 -> 0 | E10: =1-E9 -> 0 | F10: =1-F9 -> 0
A11: Alfa diario (intercepto) | B11: =INTERCEPT('2_Retornos'!B$2:B$252,'2_Retornos'!$G$2:$G$252) -> 0 | C11: =INTERCEPT('2_Retornos'!C$2:C$252,'2_Retornos'!$G$2:$G$252) -> 0 | D11: =INTERCEPT('2_Retornos'!D$2:D$252,'2_Retornos'!$G$2:$G$252) -> 0 | E11: =INTERCEPT('2_Retornos'!E$2:E$252,'2_Retornos'!$G$2:$G$252) -> 0 | F11: =INTERCEPT('2_Retornos'!F$2:F$252,'2_Retornos'!$G$2:$G$252) -> 0
A12: Retorno exigido CAPM: rf + beta x ERP | B12: =$B$3+B8*$B$4 -> 0 | C12: =$B$3+C8*$B$4 -> 0 | D12: =$B$3+D8*$B$4 -> 0 | E12: =$B$3+E8*$B$4 -> 0 | F12: =$B$3+F8*$B$4 -> 0
A13: Retorno observado anual | B13: ='2_Retornos'!J7 -> 0 | C13: ='2_Retornos'!K7 -> 0 | D13: ='2_Retornos'!L7 -> 0 | E13: ='2_Retornos'!M7 -> 0 | F13: ='2_Retornos'!N7 -> 0
A14: Diferencia (observado - CAPM) | B14: =B13-B12 -> 0 | C14: =C13-C12 -> 0 | D14: =D13-D12 -> 0 | E14: =E13-E12 -> 0 | F14: =F13-F12 -> 0
A16: Lectura: beta 1,4 => si el IPSA sube 1%, la accion tiende a subir 1,4%. En un torneo, las betas altas amplifican el resultado (para bien y para mal).

Sheet 7_Tecnico
A1: Accion: | B1: MINERA | C1: <- elige la accion (lista desplegable) | E1: Ultima senal: | F1: =IFERROR(LOOKUP(2,1/(E4:E255<>""),E4:E255),"sin senal") -> 0 | H1: ="RSI actual: "&TEXT(H255,"0.0")&IF(H255>70," (sobrecompra)",IF(H255<30," (sobreventa)","")) -> 0
A3: Fecha | B3: Precio | C3: SMA 20 | D3: SMA 50 | E3: Senal cruce | F3: Ganancia | G3: Perdida | H3: RSI 14 | I3: Bollinger sup | J3: Bollinger inf
A4: ='1_Precios'!A2 -> 0 | B4: =INDEX('1_Precios'!$B$2:$F$2,MATCH($B$1,'1_Precios'!$B$1:$F$1,0)) -> 0
A5: ='1_Precios'!A3 -> 0 | B5: =INDEX('1_Precios'!$B$3:$F$3,MATCH($B$1,'1_Precios'!$B$1:$F$1,0)) -> 0 | F5: =MAX(B5-B4,0) -> 0 | G5: =MAX(B4-B5,0) -> 0
A6: ='1_Precios'!A4 -> 0 | B6: =INDEX('1_Precios'!$B$4:$F$4,MATCH($B$1,'1_Precios'!$B$1:$F$1,0)) -> 0 | F6: =MAX(B6-B5,0) -> 0 | G6: =MAX(B5-B6,0) -> 0
A7: ='1_Precios'!A5 -> 0 | B7: =INDEX('1_Precios'!$B$5:$F$5,MATCH($B$1,'1_Precios'!$B$1:$F$1,0)) -> 0 | F7: =MAX(B7-B6,0) -> 0 | G7: =MAX(B6-B7,0) -> 0
A8: ='1_Precios'!A6 -> 0 | B8: =INDEX('1_Precios'!$B$6:$F$6,MATCH($B$1,'1_Precios'!$B$1:$F$1,0)) -> 0 | F8: =MAX(B8-B7,0) -> 0 | G8: =MAX(B7-B8,0) -> 0
A9: ='1_Precios'!A7 -> 0 | B9: =INDEX('1_Precios'!$B$7:$F$7,MATCH($B$1,'1_Precios'!$B$1:$F$1,0)) -> 0 | F9: =MAX(B9-B8,0) -> 0 | G9: =MAX(B8-B9,0) -> 0
A10: ='1_Precios'!A8 -> 0 | B10: =INDEX('1_Precios'!$B$8:$F$8,MATCH($B$1,'1_Precios'!$B$1:$F$1,0)) -> 0 | F10: =MAX(B10-B9,0) -> 0 | G10: =MAX(B9-B10,0) -> 0
A11: ='1_Precios'!A9 -> 0 | B11: =INDEX('1_Precios'!$B$9:$F$9,MATCH($B$1,'1_Precios'!$B$1:$F$1,0)) -> 0 | F11: =MAX(B11-B10,0) -> 0 | G11: =MAX(B10-B11,0) -> 0
A12: ='1_Precios'!A10 -> 0 | B12: =INDEX('1_Precios'!$B$10:$F$10,MATCH($B$1,'1_Precios'!$B$1:$F$1,0)) -> 0 | F12: =MAX(B12-B11,0) -> 0 | G12: =MAX(B11-B12,0) -> 0
A13: ='1_Precios'!A11 -> 0 | B13: =INDEX('1_Precios'!$B$11:$F$11,MATCH($B$1,'1_Precios'!$B$1:$F$1,0)) -> 0 | F13: =MAX(B13-B12,0) -> 0 | G13: =MAX(B12-B13,0) -> 0
A14: ='1_Precios'!A12 -> 0 | B14: =INDEX('1_Precios'!$B$12:$F$12,MATCH($B$1,'1_Precios'!$B$1:$F$1,0)) -> 0 | F14: =MAX(B14-B13,0) -> 0 | G14: =MAX(B13-B14,0) -> 0
A15: ='1_Precios'!A13 -> 0 | B15: =INDEX('1_Precios'!$B$13:$F$13,MATCH($B$1,'1_Precios'!$B$1:$F$1,0)) -> 0 | F15: =MAX(B15-B14,0) -> 0 | G15: =MAX(B14-B15,0) -> 0
A16: ='1_Precios'!A14 -> 0 | B16: =INDEX('1_Precios'!$B$14:$F$14,MATCH($B$1,'1_Precios'!$B$1:$F$1,0)) -> 0 | F16: =MAX(B16-B15,0) -> 0 | G16: =MAX(B15-B16,0) -> 0
A17: ='1_Precios'!A15 -> 0 | B17: =INDEX('1_Precios'!$B$15:$F$15,MATCH($B$1,'1_Precios'!$B$1:$F$1,0)) -> 0 | F17: =MAX(B17-B16,0) -> 0 | G17: =MAX(B16-B17,0) -> 0
A18: ='1_Precios'!A16 -> 0 | B18: =INDEX('1_Precios'!$B$16:$F$16,MATCH($B$1,'1_Precios'!$B$1:$F$1,0)) -> 0 | F18: =MAX(B18-B17,0) -> 0 | G18: =MAX(B17-B18,0) -> 0 | H18: =IF(SUM(G5:G18)=0,100,100-100/(1+AVERAGE(F5:F18)/AVERAGE(G5:G18))) -> 0
A19: ='1_Precios'!A17 -> 0 | B19: =INDEX('1_Precios'!$B$17:$F$17,MATCH($B$1,'1_Precios'!$B$1:$F$1,0)) -> 0 | F19: =MAX(B19-B18,0) -> 0 | G19: =MAX(B18-B19,0) -> 0 | H19: =IF(SUM(G6:G19)=0,100,100-100/(1+AVERAGE(F6:F19)/AVERAGE(G6:G19))) -> 0
A20: ='1_Precios'!A18 -> 0 | B20: =INDEX('1_Precios'!$B$18:$F$18,MATCH($B$1,'1_Precios'!$B$1:$F$1,0)) -> 0 | F20: =MAX(B20-B19,0) -> 0 | G20: =MAX(B19-B20,0) -> 0 | H20: =IF(SUM(G7:G20)=0,100,100-100/(1+AVERAGE(F7:F20)/AVERAGE(G7:G20))) -> 0
A21: ='1_Precios'!A19 -> 0 | B21: =INDEX('1_Precios'!$B$19:$F$19,MATCH($B$1,'1_Precios'!$B$1:$F$1,0)) -> 0 | F21: =MAX(B21-B20,0) -> 0 | G21: =MAX(B20-B21,0) -> 0 | H21: =IF(SUM(G8:G21)=0,100,100-100/(1+AVERAGE(F8:F21)/AVERAGE(G8:G21))) -> 0
A22: ='1_Precios'!A20 -> 0 | B22: =INDEX('1_Precios'!$B$20:$F$20,MATCH($B$1,'1_Precios'!$B$1:$F$1,0)) -> 0 | F22: =MAX(B22-B21,0) -> 0 | G22: =MAX(B21-B22,0) -> 0 | H22: =IF(SUM(G9:G22)=0,100,100-100/(1+AVERAGE(F9:F22)/AVERAGE(G9:G22))) -> 0
A23: ='1_Precios'!A21 -> 0 | B23: =INDEX('1_Precios'!$B$21:$F$21,MATCH($B$1,'1_Precios'!$B$1:$F$1,0)) -> 0 | C23: =AVERAGE(B4:B23) -> 0 | F23: =MAX(B23-B22,0) -> 0 | G23: =MAX(B22-B23,0) -> 0 | H23: =IF(SUM(G10:G23)=0,100,100-100/(1+AVERAGE(F10:F23)/AVERAGE(G10:G23))) -> 0 | I23: =C23+2*_xlfn.STDEV.S(B4:B23) -> 0 | J23: =C23-2*_xlfn.STDEV.S(B4:B23) -> 0
A24: ='1_Precios'!A22 -> 0 | B24: =INDEX('1_Precios'!$B$22:$F$22,MATCH($B$1,'1_Precios'!$B$1:$F$1,0)) -> 0 | C24: =AVERAGE(B5:B24) -> 0 | F24: =MAX(B24-B23,0) -> 0 | G24: =MAX(B23-B24,0) -> 0 | H24: =IF(SUM(G11:G24)=0,100,100-100/(1+AVERAGE(F11:F24)/AVERAGE(G11:G24))) -> 0 | I24: =C24+2*_xlfn.STDEV.S(B5:B24) -> 0 | J24: =C24-2*_xlfn.STDEV.S(B5:B24) -> 0
A25: ='1_Precios'!A23 -> 0 | B25: =INDEX('1_Precios'!$B$23:$F$23,MATCH($B$1,'1_Precios'!$B$1:$F$1,0)) -> 0 | C25: =AVERAGE(B6:B25) -> 0 | F25: =MAX(B25-B24,0) -> 0 | G25: =MAX(B24-B25,0) -> 0 | H25: =IF(SUM(G12:G25)=0,100,100-100/(1+AVERAGE(F12:F25)/AVERAGE(G12:G25))) -> 0 | I25: =C25+2*_xlfn.STDEV.S(B6:B25) -> 0 | J25: =C25-2*_xlfn.STDEV.S(B6:B25) -> 0
A26: ='1_Precios'!A24 -> 0 | B26: =INDEX('1_Precios'!$B$24:$F$24,MATCH($B$1,'1_Precios'!$B$1:$F$1,0)) -> 0 | C26: =AVERAGE(B7:B26) -> 0 | F26: =MAX(B26-B25,0) -> 0 | G26: =MAX(B25-B26,0) -> 0 | H26: =IF(SUM(G13:G26)=0,100,100-100/(1+AVERAGE(F13:F26)/AVERAGE(G13:G26))) -> 0 | I26: =C26+2*_xlfn.STDEV.S(B7:B26) -> 0 | J26: =C26-2*_xlfn.STDEV.S(B7:B26) -> 0
A27: ='1_Precios'!A25 -> 0 | B27: =INDEX('1_Precios'!$B$25:$F$25,MATCH($B$1,'1_Precios'!$B$1:$F$1,0)) -> 0 | C27: =AVERAGE(B8:B27) -> 0 | F27: =MAX(B27-B26,0) -> 0 | G27: =MAX(B26-B27,0) -> 0 | H27: =IF(SUM(G14:G27)=0,100,100-100/(1+AVERAGE(F14:F27)/AVERAGE(G14:G27))) -> 0 | I27: =C27+2*_xlfn.STDEV.S(B8:B27) -> 0 | J27: =C27-2*_xlfn.STDEV.S(B8:B27) -> 0
A28: ='1_Precios'!A26 -> 0 | B28: =INDEX('1_Precios'!$B$26:$F$26,MATCH($B$1,'1_Precios'!$B$1:$F$1,0)) -> 0 | C28: =AVERAGE(B9:B28) -> 0 | F28: =MAX(B28-B27,0) -> 0 | G28: =MAX(B27-B28,0) -> 0 | H28: =IF(SUM(G15:G28)=0,100,100-100/(1+AVERAGE(F15:F28)/AVERAGE(G15:G28))) -> 0 | I28: =C28+2*_xlfn.STDEV.S(B9:B28) -> 0 | J28: =C28-2*_xlfn.STDEV.S(B9:B28) -> 0
A29: ='1_Precios'!A27 -> 0 | B29: =INDEX('1_Precios'!$B$27:$F$27,MATCH($B$1,'1_Precios'!$B$1:$F$1,0)) -> 0 | C29: =AVERAGE(B10:B29) -> 0 | F29: =MAX(B29-B28,0) -> 0 | G29: =MAX(B28-B29,0) -> 0 | H29: =IF(SUM(G16:G29)=0,100,100-100/(1+AVERAGE(F16:F29)/AVERAGE(G16:G29))) -> 0 | I29: =C29+2*_xlfn.STDEV.S(B10:B29) -> 0 | J29: =C29-2*_xlfn.STDEV.S(B10:B29) -> 0
A30: ='1_Precios'!A28 -> 0 | B30: =INDEX('1_Precios'!$B$28:$F$28,MATCH($B$1,'1_Precios'!$B$1:$F$1,0)) -> 0 | C30: =AVERAGE(B11:B30) -> 0 | F30: =MAX(B30-B29,0) -> 0 | G30: =MAX(B29-B30,0) -> 0 | H30: =IF(SUM(G17:G30)=0,100,100-100/(1+AVERAGE(F17:F30)/AVERAGE(G17:G30))) -> 0 | I30: =C30+2*_xlfn.STDEV.S(B11:B30) -> 0 | J30: =C30-2*_xlfn.STDEV.S(B11:B30) -> 0
A31: ='1_Precios'!A29 -> 0 | B31: =INDEX('1_Precios'!$B$29:$F$29,MATCH($B$1,'1_Precios'!$B$1:$F$1,0)) -> 0 | C31: =AVERAGE(B12:B31) -> 0 | F31: =MAX(B31-B30,0) -> 0 | G31: =MAX(B30-B31,0) -> 0 | H31: =IF(SUM(G18:G31)=0,100,100-100/(1+AVERAGE(F18:F31)/AVERAGE(G18:G31))) -> 0 | I31: =C31+2*_xlfn.STDEV.S(B12:B31) -> 0 | J31: =C31-2*_xlfn.STDEV.S(B12:B31) -> 0
A32: ='1_Precios'!A30 -> 0 | B32: =INDEX('1_Precios'!$B$30:$F$30,MATCH($B$1,'1_Precios'!$B$1:$F$1,0)) -> 0 | C32: =AVERAGE(B13:B32) -> 0 | F32: =MAX(B32-B31,0) -> 0 | G32: =MAX(B31-B32,0) -> 0 | H32: =IF(SUM(G19:G32)=0,100,100-100/(1+AVERAGE(F19:F32)/AVERAGE(G19:G32))) -> 0 | I32: =C32+2*_xlfn.STDEV.S(B13:B32) -> 0 | J32: =C32-2*_xlfn.STDEV.S(B13:B32) -> 0
A33: ='1_Precios'!A31 -> 0 | B33: =INDEX('1_Precios'!$B$31:$F$31,MATCH($B$1,'1_Precios'!$B$1:$F$1,0)) -> 0 | C33: =AVERAGE(B14:B33) -> 0 | F33: =MAX(B33-B32,0) -> 0 | G33: =MAX(B32-B33,0) -> 0 | H33: =IF(SUM(G20:G33)=0,100,100-100/(1+AVERAGE(F20:F33)/AVERAGE(G20:G33))) -> 0 | I33: =C33+2*_xlfn.STDEV.S(B14:B33) -> 0 | J33: =C33-2*_xlfn.STDEV.S(B14:B33) -> 0
A34: ='1_Precios'!A32 -> 0 | B34: =INDEX('1_Precios'!$B$32:$F$32,MATCH($B$1,'1_Precios'!$B$1:$F$1,0)) -> 0 | C34: =AVERAGE(B15:B34) -> 0 | F34: =MAX(B34-B33,0) -> 0 | G34: =MAX(B33-B34,0) -> 0 | H34: =IF(SUM(G21:G34)=0,100,100-100/(1+AVERAGE(F21:F34)/AVERAGE(G21:G34))) -> 0 | I34: =C34+2*_xlfn.STDEV.S(B15:B34) -> 0 | J34: =C34-2*_xlfn.STDEV.S(B15:B34) -> 0
A35: ='1_Precios'!A33 -> 0 | B35: =INDEX('1_Precios'!$B$33:$F$33,MATCH($B$1,'1_Precios'!$B$1:$F$1,0)) -> 0 | C35: =AVERAGE(B16:B35) -> 0 | F35: =MAX(B35-B34,0) -> 0 | G35: =MAX(B34-B35,0) -> 0 | H35: =IF(SUM(G22:G35)=0,100,100-100/(1+AVERAGE(F22:F35)/AVERAGE(G22:G35))) -> 0 | I35: =C35+2*_xlfn.STDEV.S(B16:B35) -> 0 | J35: =C35-2*_xlfn.STDEV.S(B16:B35) -> 0
A36: ='1_Precios'!A34 -> 0 | B36: =INDEX('1_Precios'!$B$34:$F$34,MATCH($B$1,'1_Precios'!$B$1:$F$1,0)) -> 0 | C36: =AVERAGE(B17:B36) -> 0 | F36: =MAX(B36-B35,0) -> 0 | G36: =MAX(B35-B36,0) -> 0 | H36: =IF(SUM(G23:G36)=0,100,100-100/(1+AVERAGE(F23:F36)/AVERAGE(G23:G36))) -> 0 | I36: =C36+2*_xlfn.STDEV.S(B17:B36) -> 0 | J36: =C36-2*_xlfn.STDEV.S(B17:B36) -> 0
A37: ='1_Precios'!A35 -> 0 | B37: =INDEX('1_Precios'!$B$35:$F$35,MATCH($B$1,'1_Precios'!$B$1:$F$1,0)) -> 0 | C37: =AVERAGE(B18:B37) -> 0 | F37: =MAX(B37-B36,0) -> 0 | G37: =MAX(B36-B37,0) -> 0 | H37: =IF(SUM(G24:G37)=0,100,100-100/(1+AVERAGE(F24:F37)/AVERAGE(G24:G37))) -> 0 | I37: =C37+2*_xlfn.STDEV.S(B18:B37) -> 0 | J37: =C37-2*_xlfn.STDEV.S(B18:B37) -> 0
A38: ='1_Precios'!A36 -> 0 | B38: =INDEX('1_Precios'!$B$36:$F$36,MATCH($B$1,'1_Precios'!$B$1:$F$1,0)) -> 0 | C38: =AVERAGE(B19:B38) -> 0 | F38: =MAX(B38-B37,0) -> 0 | G38: =MAX(B37-B38,0) -> 0 | H38: =IF(SUM(G25:G38)=0,100,100-100/(1+AVERAGE(F25:F38)/AVERAGE(G25:G38))) -> 0 | I38: =C38+2*_xlfn.STDEV.S(B19:B38) -> 0 | J38: =C38-2*_xlfn.STDEV.S(B19:B38) -> 0
A39: ='1_Precios'!A37 -> 0 | B39: =INDEX('1_Precios'!$B$37:$F$37,MATCH($B$1,'1_Precios'!$B$1:$F$1,0)) -> 0 | C39: =AVERAGE(B20:B39) -> 0 | F39: =MAX(B39-B38,0) -> 0 | G39: =MAX(B38-B39,0) -> 0 | H39: =IF(SUM(G26:G39)=0,100,100-100/(1+AVERAGE(F26:F39)/AVERAGE(G26:G39))) -> 0 | I39: =C39+2*_xlfn.STDEV.S(B20:B39) -> 0 | J39: =C39-2*_xlfn.STDEV.S(B20:B39) -> 0
A40: ='1_Precios'!A38 -> 0 | B40: =INDEX('1_Precios'!$B$38:$F$38,MATCH($B$1,'1_Precios'!$B$1:$F$1,0)) -> 0 | C40: =AVERAGE(B21:B40) -> 0 | F40: =MAX(B40-B39,0) -> 0 | G40: =MAX(B39-B40,0) -> 0 | H40: =IF(SUM(G27:G40)=0,100,100-100/(1+AVERAGE(F27:F40)/AVERAGE(G27:G40))) -> 0 | I40: =C40+2*_xlfn.STDEV.S(B21:B40) -> 0 | J40: =C40-2*_xlfn.STDEV.S(B21:B40) -> 0
A41: ='1_Precios'!A39 -> 0 | B41: =INDEX('1_Precios'!$B$39:$F$39,MATCH($B$1,'1_Precios'!$B$1:$F$1,0)) -> 0 | C41: =AVERAGE(B22:B41) -> 0 | F41: =MAX(B41-B40,0) -> 0 | G41: =MAX(B40-B41,0) -> 0 | H41: =IF(SUM(G28:G41)=0,100,100-100/(1+AVERAGE(F28:F41)/AVERAGE(G28:G41))) -> 0 | I41: =C41+2*_xlfn.STDEV.S(B22:B41) -> 0 | J41: =C41-2*_xlfn.STDEV.S(B22:B41) -> 0
A42: ='1_Precios'!A40 -> 0 | B42: =INDEX('1_Precios'!$B$40:$F$40,MATCH($B$1,'1_Precios'!$B$1:$F$1,0)) -> 0 | C42: =AVERAGE(B23:B42) -> 0 | F42: =MAX(B42-B41,0) -> 0 | G42: =MAX(B41-B42,0) -> 0 | H42: =IF(SUM(G29:G42)=0,100,100-100/(1+AVERAGE(F29:F42)/AVERAGE(G29:G42))) -> 0 | I42: =C42+2*_xlfn.STDEV.S(B23:B42) -> 0 | J42: =C42-2*_xlfn.STDEV.S(B23:B42) -> 0
A43: ='1_Precios'!A41 -> 0 | B43: =INDEX('1_Precios'!$B$41:$F$41,MATCH($B$1,'1_Precios'!$B$1:$F$1,0)) -> 0 | C43: =AVERAGE(B24:B43) -> 0 | F43: =MAX(B43-B42,0) -> 0 | G43: =MAX(B42-B43,0) -> 0 | H43: =IF(SUM(G30:G43)=0,100,100-100/(1+AVERAGE(F30:F43)/AVERAGE(G30:G43))) -> 0 | I43: =C43+2*_xlfn.STDEV.S(B24:B43) -> 0 | J43: =C43-2*_xlfn.STDEV.S(B24:B43) -> 0
A44: ='1_Precios'!A42 -> 0 | B44: =INDEX('1_Precios'!$B$42:$F$42,MATCH($B$1,'1_Precios'!$B$1:$F$1,0)) -> 0 | C44: =AVERAGE(B25:B44) -> 0 | F44: =MAX(B44-B43,0) -> 0 | G44: =MAX(B43-B44,0) -> 0 | H44: =IF(SUM(G31:G44)=0,100,100-100/(1+AVERAGE(F31:F44)/AVERAGE(G31:G44))) -> 0 | I44: =C44+2*_xlfn.STDEV.S(B25:B44) -> 0 | J44: =C44-2*_xlfn.STDEV.S(B25:B44) -> 0
A45: ='1_Precios'!A43 -> 0 | B45: =INDEX('1_Precios'!$B$43:$F$43,MATCH($B$1,'1_Precios'!$B$1:$F$1,0)) -> 0 | C45: =AVERAGE(B26:B45) -> 0 | F45: =MAX(B45-B44,0) -> 0 | G45: =MAX(B44-B45,0) -> 0 | H45: =IF(SUM(G32:G45)=0,100,100-100/(1+AVERAGE(F32:F45)/AVERAGE(G32:G45))) -> 0 | I45: =C45+2*_xlfn.STDEV.S(B26:B45) -> 0 | J45: =C45-2*_xlfn.STDEV.S(B26:B45) -> 0
A46: ='1_Precios'!A44 -> 0 | B46: =INDEX('1_Precios'!$B$44:$F$44,MATCH($B$1,'1_Precios'!$B$1:$F$1,0)) -> 0 | C46: =AVERAGE(B27:B46) -> 0 | F46: =MAX(B46-B45,0) -> 0 | G46: =MAX(B45-B46,0) -> 0 | H46: =IF(SUM(G33:G46)=0,100,100-100/(1+AVERAGE(F33:F46)/AVERAGE(G33:G46))) -> 0 | I46: =C46+2*_xlfn.STDEV.S(B27:B46) -> 0 | J46: =C46-2*_xlfn.STDEV.S(B27:B46) -> 0
A47: ='1_Precios'!A45 -> 0 | B47: =INDEX('1_Precios'!$B$45:$F$45,MATCH($B$1,'1_Precios'!$B$1:$F$1,0)) -> 0 | C47: =AVERAGE(B28:B47) -> 0 | F47: =MAX(B47-B46,0) -> 0 | G47: =MAX(B46-B47,0) -> 0 | H47: =IF(SUM(G34:G47)=0,100,100-100/(1+AVERAGE(F34:F47)/AVERAGE(G34:G47))) -> 0 | I47: =C47+2*_xlfn.STDEV.S(B28:B47) -> 0 | J47: =C47-2*_xlfn.STDEV.S(B28:B47) -> 0
A48: ='1_Precios'!A46 -> 0 | B48: =INDEX('1_Precios'!$B$46:$F$46,MATCH($B$1,'1_Precios'!$B$1:$F$1,0)) -> 0 | C48: =AVERAGE(B29:B48) -> 0 | F48: =MAX(B48-B47,0) -> 0 | G48: =MAX(B47-B48,0) -> 0 | H48: =IF(SUM(G35:G48)=0,100,100-100/(1+AVERAGE(F35:F48)/AVERAGE(G35:G48))) -> 0 | I48: =C48+2*_xlfn.STDEV.S(B29:B48) -> 0 | J48: =C48-2*_xlfn.STDEV.S(B29:B48) -> 0
A49: ='1_Precios'!A47 -> 0 | B49: =INDEX('1_Precios'!$B$47:$F$47,MATCH($B$1,'1_Precios'!$B$1:$F$1,0)) -> 0 | C49: =AVERAGE(B30:B49) -> 0 | F49: =MAX(B49-B48,0) -> 0 | G49: =MAX(B48-B49,0) -> 0 | H49: =IF(SUM(G36:G49)=0,100,100-100/(1+AVERAGE(F36:F49)/AVERAGE(G36:G49))) -> 0 | I49: =C49+2*_xlfn.STDEV.S(B30:B49) -> 0 | J49: =C49-2*_xlfn.STDEV.S(B30:B49) -> 0
A50: ='1_Precios'!A48 -> 0 | B50: =INDEX('1_Precios'!$B$48:$F$48,MATCH($B$1,'1_Precios'!$B$1:$F$1,0)) -> 0 | C50: =AVERAGE(B31:B50) -> 0 | F50: =MAX(B50-B49,0) -> 0 | G50: =MAX(B49-B50,0) -> 0 | H50: =IF(SUM(G37:G50)=0,100,100-100/(1+AVERAGE(F37:F50)/AVERAGE(G37:G50))) -> 0 | I50: =C50+2*_xlfn.STDEV.S(B31:B50) -> 0 | J50: =C50-2*_xlfn.STDEV.S(B31:B50) -> 0
A51: ='1_Precios'!A49 -> 0 | B51: =INDEX('1_Precios'!$B$49:$F$49,MATCH($B$1,'1_Precios'!$B$1:$F$1,0)) -> 0 | C51: =AVERAGE(B32:B51) -> 0 | F51: =MAX(B51-B50,0) -> 0 | G51: =MAX(B50-B51,0) -> 0 | H51: =IF(SUM(G38:G51)=0,100,100-100/(1+AVERAGE(F38:F51)/AVERAGE(G38:G51))) -> 0 | I51: =C51+2*_xlfn.STDEV.S(B32:B51) -> 0 | J51: =C51-2*_xlfn.STDEV.S(B32:B51) -> 0
A52: ='1_Precios'!A50 -> 0 | B52: =INDEX('1_Precios'!$B$50:$F$50,MATCH($B$1,'1_Precios'!$B$1:$F$1,0)) -> 0 | C52: =AVERAGE(B33:B52) -> 0 | F52: =MAX(B52-B51,0) -> 0 | G52: =MAX(B51-B52,0) -> 0 | H52: =IF(SUM(G39:G52)=0,100,100-100/(1+AVERAGE(F39:F52)/AVERAGE(G39:G52))) -> 0 | I52: =C52+2*_xlfn.STDEV.S(B33:B52) -> 0 | J52: =C52-2*_xlfn.STDEV.S(B33:B52) -> 0
A53: ='1_Precios'!A51 -> 0 | B53: =INDEX('1_Precios'!$B$51:$F$51,MATCH($B$1,'1_Precios'!$B$1:$F$1,0)) -> 0 | C53: =AVERAGE(B34:B53) -> 0 | D53: =AVERAGE(B4:B53) -> 0 | F53: =MAX(B53-B52,0) -> 0 | G53: =MAX(B52-B53,0) -> 0 | H53: =IF(SUM(G40:G53)=0,100,100-100/(1+AVERAGE(F40:F53)/AVERAGE(G40:G53))) -> 0 | I53: =C53+2*_xlfn.STDEV.S(B34:B53) -> 0 | J53: =C53-2*_xlfn.STDEV.S(B34:B53) -> 0
A54: ='1_Precios'!A52 -> 0 | B54: =INDEX('1_Precios'!$B$52:$F$52,MATCH($B$1,'1_Precios'!$B$1:$F$1,0)) -> 0 | C54: =AVERAGE(B35:B54) -> 0 | D54: =AVERAGE(B5:B54) -> 0 | E54: =IF(AND(C54>D54,C53<=D53),"COMPRA (cruce alcista)",IF(AND(C54<D54,C53>=D53),"VENTA (cruce bajista)","")) -> 0 | F54: =MAX(B54-B53,0) -> 0 | G54: =MAX(B53-B54,0) -> 0 | H54: =IF(SUM(G41:G54)=0,100,100-100/(1+AVERAGE(F41:F54)/AVERAGE(G41:G54))) -> 0 | I54: =C54+2*_xlfn.STDEV.S(B35:B54) -> 0 | J54: =C54-2*_xlfn.STDEV.S(B35:B54) -> 0
A55: ='1_Precios'!A53 -> 0 | B55: =INDEX('1_Precios'!$B$53:$F$53,MATCH($B$1,'1_Precios'!$B$1:$F$1,0)) -> 0 | C55: =AVERAGE(B36:B55) -> 0 | D55: =AVERAGE(B6:B55) -> 0 | E55: =IF(AND(C55>D55,C54<=D54),"COMPRA (cruce alcista)",IF(AND(C55<D55,C54>=D54),"VENTA (cruce bajista)","")) -> 0 | F55: =MAX(B55-B54,0) -> 0 | G55: =MAX(B54-B55,0) -> 0 | H55: =IF(SUM(G42:G55)=0,100,100-100/(1+AVERAGE(F42:F55)/AVERAGE(G42:G55))) -> 0 | I55: =C55+2*_xlfn.STDEV.S(B36:B55) -> 0 | J55: =C55-2*_xlfn.STDEV.S(B36:B55) -> 0
A56: ='1_Precios'!A54 -> 0 | B56: =INDEX('1_Precios'!$B$54:$F$54,MATCH($B$1,'1_Precios'!$B$1:$F$1,0)) -> 0 | C56: =AVERAGE(B37:B56) -> 0 | D56: =AVERAGE(B7:B56) -> 0 | E56: =IF(AND(C56>D56,C55<=D55),"COMPRA (cruce alcista)",IF(AND(C56<D56,C55>=D55),"VENTA (cruce bajista)","")) -> 0 | F56: =MAX(B56-B55,0) -> 0 | G56: =MAX(B55-B56,0) -> 0 | H56: =IF(SUM(G43:G56)=0,100,100-100/(1+AVERAGE(F43:F56)/AVERAGE(G43:G56))) -> 0 | I56: =C56+2*_xlfn.STDEV.S(B37:B56) -> 0 | J56: =C56-2*_xlfn.STDEV.S(B37:B56) -> 0
A57: ='1_Precios'!A55 -> 0 | B57: =INDEX('1_Precios'!$B$55:$F$55,MATCH($B$1,'1_Precios'!$B$1:$F$1,0)) -> 0 | C57: =AVERAGE(B38:B57) -> 0 | D57: =AVERAGE(B8:B57) -> 0 | E57: =IF(AND(C57>D57,C56<=D56),"COMPRA (cruce alcista)",IF(AND(C57<D57,C56>=D56),"VENTA (cruce bajista)","")) -> 0 | F57: =MAX(B57-B56,0) -> 0 | G57: =MAX(B56-B57,0) -> 0 | H57: =IF(SUM(G44:G57)=0,100,100-100/(1+AVERAGE(F44:F57)/AVERAGE(G44:G57))) -> 0 | I57: =C57+2*_xlfn.STDEV.S(B38:B57) -> 0 | J57: =C57-2*_xlfn.STDEV.S(B38:B57) -> 0
A58: ='1_Precios'!A56 -> 0 | B58: =INDEX('1_Precios'!$B$56:$F$56,MATCH($B$1,'1_Precios'!$B$1:$F$1,0)) -> 0 | C58: =AVERAGE(B39:B58) -> 0 | D58: =AVERAGE(B9:B58) -> 0 | E58: =IF(AND(C58>D58,C57<=D57),"COMPRA (cruce alcista)",IF(AND(C58<D58,C57>=D57),"VENTA (cruce bajista)","")) -> 0 | F58: =MAX(B58-B57,0) -> 0 | G58: =MAX(B57-B58,0) -> 0 | H58: =IF(SUM(G45:G58)=0,100,100-100/(1+AVERAGE(F45:F58)/AVERAGE(G45:G58))) -> 0 | I58: =C58+2*_xlfn.STDEV.S(B39:B58) -> 0 | J58: =C58-2*_xlfn.STDEV.S(B39:B58) -> 0
A59: ='1_Precios'!A57 -> 0 | B59: =INDEX('1_Precios'!$B$57:$F$57,MATCH($B$1,'1_Precios'!$B$1:$F$1,0)) -> 0 | C59: =AVERAGE(B40:B59) -> 0 | D59: =AVERAGE(B10:B59) -> 0 | E59: =IF(AND(C59>D59,C58<=D58),"COMPRA (cruce alcista)",IF(AND(C59<D59,C58>=D58),"VENTA (cruce bajista)","")) -> 0 | F59: =MAX(B59-B58,0) -> 0 | G59: =MAX(B58-B59,0) -> 0 | H59: =IF(SUM(G46:G59)=0,100,100-100/(1+AVERAGE(F46:F59)/AVERAGE(G46:G59))) -> 0 | I59: =C59+2*_xlfn.STDEV.S(B40:B59) -> 0 | J59: =C59-2*_xlfn.STDEV.S(B40:B59) -> 0
A60: ='1_Precios'!A58 -> 0 | B60: =INDEX('1_Precios'!$B$58:$F$58,MATCH($B$1,'1_Precios'!$B$1:$F$1,0)) -> 0 | C60: =AVERAGE(B41:B60) -> 0 | D60: =AVERAGE(B11:B60) -> 0 | E60: =IF(AND(C60>D60,C59<=D59),"COMPRA (cruce alcista)",IF(AND(C60<D60,C59>=D59),"VENTA (cruce bajista)","")) -> 0 | F60: =MAX(B60-B59,0) -> 0 | G60: =MAX(B59-B60,0) -> 0 | H60: =IF(SUM(G47:G60)=0,100,100-100/(1+AVERAGE(F47:F60)/AVERAGE(G47:G60))) -> 0 | I60: =C60+2*_xlfn.STDEV.S(B41:B60) -> 0 | J60: =C60-2*_xlfn.STDEV.S(B41:B60) -> 0
A61: ='1_Precios'!A59 -> 0 | B61: =INDEX('1_Precios'!$B$59:$F$59,MATCH($B$1,'1_Precios'!$B$1:$F$1,0)) -> 0 | C61: =AVERAGE(B42:B61) -> 0 | D61: =AVERAGE(B12:B61) -> 0 | E61: =IF(AND(C61>D61,C60<=D60),"COMPRA (cruce alcista)",IF(AND(C61<D61,C60>=D60),"VENTA (cruce bajista)","")) -> 0 | F61: =MAX(B61-B60,0) -> 0 | G61: =MAX(B60-B61,0) -> 0 | H61: =IF(SUM(G48:G61)=0,100,100-100/(1+AVERAGE(F48:F61)/AVERAGE(G48:G61))) -> 0 | I61: =C61+2*_xlfn.STDEV.S(B42:B61) -> 0 | J61: =C61-2*_xlfn.STDEV.S(B42:B61) -> 0
A62: ='1_Precios'!A60 -> 0 | B62: =INDEX('1_Precios'!$B$60:$F$60,MATCH($B$1,'1_Precios'!$B$1:$F$1,0)) -> 0 | C62: =AVERAGE(B43:B62) -> 0 | D62: =AVERAGE(B13:B62) -> 0 | E62: =IF(AND(C62>D62,C61<=D61),"COMPRA (cruce alcista)",IF(AND(C62<D62,C61>=D61),"VENTA (cruce bajista)","")) -> 0 | F62: =MAX(B62-B61,0) -> 0 | G62: =MAX(B61-B62,0) -> 0 | H62: =IF(SUM(G49:G62)=0,100,100-100/(1+AVERAGE(F49:F62)/AVERAGE(G49:G62))) -> 0 | I62: =C62+2*_xlfn.STDEV.S(B43:B62) -> 0 | J62: =C62-2*_xlfn.STDEV.S(B43:B62) -> 0
A63: ='1_Precios'!A61 -> 0 | B63: =INDEX('1_Precios'!$B$61:$F$61,MATCH($B$1,'1_Precios'!$B$1:$F$1,0)) -> 0 | C63: =AVERAGE(B44:B63) -> 0 | D63: =AVERAGE(B14:B63) -> 0 | E63: =IF(AND(C63>D63,C62<=D62),"COMPRA (cruce alcista)",IF(AND(C63<D63,C62>=D62),"VENTA (cruce bajista)","")) -> 0 | F63: =MAX(B63-B62,0) -> 0 | G63: =MAX(B62-B63,0) -> 0 | H63: =IF(SUM(G50:G63)=0,100,100-100/(1+AVERAGE(F50:F63)/AVERAGE(G50:G63))) -> 0 | I63: =C63+2*_xlfn.STDEV.S(B44:B63) -> 0 | J63: =C63-2*_xlfn.STDEV.S(B44:B63) -> 0
A64: ='1_Precios'!A62 -> 0 | B64: =INDEX('1_Precios'!$B$62:$F$62,MATCH($B$1,'1_Precios'!$B$1:$F$1,0)) -> 0 | C64: =AVERAGE(B45:B64) -> 0 | D64: =AVERAGE(B15:B64) -> 0 | E64: =IF(AND(C64>D64,C63<=D63),"COMPRA (cruce alcista)",IF(AND(C64<D64,C63>=D63),"VENTA (cruce bajista)","")) -> 0 | F64: =MAX(B64-B63,0) -> 0 | G64: =MAX(B63-B64,0) -> 0 | H64: =IF(SUM(G51:G64)=0,100,100-100/(1+AVERAGE(F51:F64)/AVERAGE(G51:G64))) -> 0 | I64: =C64+2*_xlfn.STDEV.S(B45:B64) -> 0 | J64: =C64-2*_xlfn.STDEV.S(B45:B64) -> 0
A65: ='1_Precios'!A63 -> 0 | B65: =INDEX('1_Precios'!$B$63:$F$63,MATCH($B$1,'1_Precios'!$B$1:$F$1,0)) -> 0 | C65: =AVERAGE(B46:B65) -> 0 | D65: =AVERAGE(B16:B65) -> 0 | E65: =IF(AND(C65>D65,C64<=D64),"COMPRA (cruce alcista)",IF(AND(C65<D65,C64>=D64),"VENTA (cruce bajista)","")) -> 0 | F65: =MAX(B65-B64,0) -> 0 | G65: =MAX(B64-B65,0) -> 0 | H65: =IF(SUM(G52:G65)=0,100,100-100/(1+AVERAGE(F52:F65)/AVERAGE(G52:G65))) -> 0 | I65: =C65+2*_xlfn.STDEV.S(B46:B65) -> 0 | J65: =C65-2*_xlfn.STDEV.S(B46:B65) -> 0
A66: ='1_Precios'!A64 -> 0 | B66: =INDEX('1_Precios'!$B$64:$F$64,MATCH($B$1,'1_Precios'!$B$1:$F$1,0)) -> 0 | C66: =AVERAGE(B47:B66) -> 0 | D66: =AVERAGE(B17:B66) -> 0 | E66: =IF(AND(C66>D66,C65<=D65),"COMPRA (cruce alcista)",IF(AND(C66<D66,C65>=D65),"VENTA (cruce bajista)","")) -> 0 | F66: =MAX(B66-B65,0) -> 0 | G66: =MAX(B65-B66,0) -> 0 | H66: =IF(SUM(G53:G66)=0,100,100-100/(1+AVERAGE(F53:F66)/AVERAGE(G53:G66))) -> 0 | I66: =C66+2*_xlfn.STDEV.S(B47:B66) -> 0 | J66: =C66-2*_xlfn.STDEV.S(B47:B66) -> 0
A67: ='1_Precios'!A65 -> 0 | B67: =INDEX('1_Precios'!$B$65:$F$65,MATCH($B$1,'1_Precios'!$B$1:$F$1,0)) -> 0 | C67: =AVERAGE(B48:B67) -> 0 | D67: =AVERAGE(B18:B67) -> 0 | E67: =IF(AND(C67>D67,C66<=D66),"COMPRA (cruce alcista)",IF(AND(C67<D67,C66>=D66),"VENTA (cruce bajista)","")) -> 0 | F67: =MAX(B67-B66,0) -> 0 | G67: =MAX(B66-B67,0) -> 0 | H67: =IF(SUM(G54:G67)=0,100,100-100/(1+AVERAGE(F54:F67)/AVERAGE(G54:G67))) -> 0 | I67: =C67+2*_xlfn.STDEV.S(B48:B67) -> 0 | J67: =C67-2*_xlfn.STDEV.S(B48:B67) -> 0
A68: ='1_Precios'!A66 -> 0 | B68: =INDEX('1_Precios'!$B$66:$F$66,MATCH($B$1,'1_Precios'!$B$1:$F$1,0)) -> 0 | C68: =AVERAGE(B49:B68) -> 0 | D68: =AVERAGE(B19:B68) -> 0 | E68: =IF(AND(C68>D68,C67<=D67),"COMPRA (cruce alcista)",IF(AND(C68<D68,C67>=D67),"VENTA (cruce bajista)","")) -> 0 | F68: =MAX(B68-B67,0) -> 0 | G68: =MAX(B67-B68,0) -> 0 | H68: =IF(SUM(G55:G68)=0,100,100-100/(1+AVERAGE(F55:F68)/AVERAGE(G55:G68))) -> 0 | I68: =C68+2*_xlfn.STDEV.S(B49:B68) -> 0 | J68: =C68-2*_xlfn.STDEV.S(B49:B68) -> 0
A69: ='1_Precios'!A67 -> 0 | B69: =INDEX('1_Precios'!$B$67:$F$67,MATCH($B$1,'1_Precios'!$B$1:$F$1,0)) -> 0 | C69: =AVERAGE(B50:B69) -> 0 | D69: =AVERAGE(B20:B69) -> 0 | E69: =IF(AND(C69>D69,C68<=D68),"COMPRA (cruce alcista)",IF(AND(C69<D69,C68>=D68),"VENTA (cruce bajista)","")) -> 0 | F69: =MAX(B69-B68,0) -> 0 | G69: =MAX(B68-B69,0) -> 0 | H69: =IF(SUM(G56:G69)=0,100,100-100/(1+AVERAGE(F56:F69)/AVERAGE(G56:G69))) -> 0 | I69: =C69+2*_xlfn.STDEV.S(B50:B69) -> 0 | J69: =C69-2*_xlfn.STDEV.S(B50:B69) -> 0
A70: ='1_Precios'!A68 -> 0 | B70: =INDEX('1_Precios'!$B$68:$F$68,MATCH($B$1,'1_Precios'!$B$1:$F$1,0)) -> 0 | C70: =AVERAGE(B51:B70) -> 0 | D70: =AVERAGE(B21:B70) -> 0 | E70: =IF(AND(C70>D70,C69<=D69),"COMPRA (cruce alcista)",IF(AND(C70<D70,C69>=D69),"VENTA (cruce bajista)","")) -> 0 | F70: =MAX(B70-B69,0) -> 0 | G70: =MAX(B69-B70,0) -> 0 | H70: =IF(SUM(G57:G70)=0,100,100-100/(1+AVERAGE(F57:F70)/AVERAGE(G57:G70))) -> 0 | I70: =C70+2*_xlfn.STDEV.S(B51:B70) -> 0 | J70: =C70-2*_xlfn.STDEV.S(B51:B70) -> 0
A71: ='1_Precios'!A69 -> 0 | B71: =INDEX('1_Precios'!$B$69:$F$69,MATCH($B$1,'1_Precios'!$B$1:$F$1,0)) -> 0 | C71: =AVERAGE(B52:B71) -> 0 | D71: =AVERAGE(B22:B71) -> 0 | E71: =IF(AND(C71>D71,C70<=D70),"COMPRA (cruce alcista)",IF(AND(C71<D71,C70>=D70),"VENTA (cruce bajista)","")) -> 0 | F71: =MAX(B71-B70,0) -> 0 | G71: =MAX(B70-B71,0) -> 0 | H71: =IF(SUM(G58:G71)=0,100,100-100/(1+AVERAGE(F58:F71)/AVERAGE(G58:G71))) -> 0 | I71: =C71+2*_xlfn.STDEV.S(B52:B71) -> 0 | J71: =C71-2*_xlfn.STDEV.S(B52:B71) -> 0
A72: ='1_Precios'!A70 -> 0 | B72: =INDEX('1_Precios'!$B$70:$F$70,MATCH($B$1,'1_Precios'!$B$1:$F$1,0)) -> 0 | C72: =AVERAGE(B53:B72) -> 0 | D72: =AVERAGE(B23:B72) -> 0 | E72: =IF(AND(C72>D72,C71<=D71),"COMPRA (cruce alcista)",IF(AND(C72<D72,C71>=D71),"VENTA (cruce bajista)","")) -> 0 | F72: =MAX(B72-B71,0) -> 0 | G72: =MAX(B71-B72,0) -> 0 | H72: =IF(SUM(G59:G72)=0,100,100-100/(1+AVERAGE(F59:F72)/AVERAGE(G59:G72))) -> 0 | I72: =C72+2*_xlfn.STDEV.S(B53:B72) -> 0 | J72: =C72-2*_xlfn.STDEV.S(B53:B72) -> 0
A73: ='1_Precios'!A71 -> 0 | B73: =INDEX('1_Precios'!$B$71:$F$71,MATCH($B$1,'1_Precios'!$B$1:$F$1,0)) -> 0 | C73: =AVERAGE(B54:B73) -> 0 | D73: =AVERAGE(B24:B73) -> 0 | E73: =IF(AND(C73>D73,C72<=D72),"COMPRA (cruce alcista)",IF(AND(C73<D73,C72>=D72),"VENTA (cruce bajista)","")) -> 0 | F73: =MAX(B73-B72,0) -> 0 | G73: =MAX(B72-B73,0) -> 0 | H73: =IF(SUM(G60:G73)=0,100,100-100/(1+AVERAGE(F60:F73)/AVERAGE(G60:G73))) -> 0 | I73: =C73+2*_xlfn.STDEV.S(B54:B73) -> 0 | J73: =C73-2*_xlfn.STDEV.S(B54:B73) -> 0
A74: ='1_Precios'!A72 -> 0 | B74: =INDEX('1_Precios'!$B$72:$F$72,MATCH($B$1,'1_Precios'!$B$1:$F$1,0)) -> 0 | C74: =AVERAGE(B55:B74) -> 0 | D74: =AVERAGE(B25:B74) -> 0 | E74: =IF(AND(C74>D74,C73<=D73),"COMPRA (cruce alcista)",IF(AND(C74<D74,C73>=D73),"VENTA (cruce bajista)","")) -> 0 | F74: =MAX(B74-B73,0) -> 0 | G74: =MAX(B73-B74,0) -> 0 | H74: =IF(SUM(G61:G74)=0,100,100-100/(1+AVERAGE(F61:F74)/AVERAGE(G61:G74))) -> 0 | I74: =C74+2*_xlfn.STDEV.S(B55:B74) -> 0 | J74: =C74-2*_xlfn.STDEV.S(B55:B74) -> 0
A75: ='1_Precios'!A73 -> 0 | B75: =INDEX('1_Precios'!$B$73:$F$73,MATCH($B$1,'1_Precios'!$B$1:$F$1,0)) -> 0 | C75: =AVERAGE(B56:B75) -> 0 | D75: =AVERAGE(B26:B75) -> 0 | E75: =IF(AND(C75>D75,C74<=D74),"COMPRA (cruce alcista)",IF(AND(C75<D75,C74>=D74),"VENTA (cruce bajista)","")) -> 0 | F75: =MAX(B75-B74,0) -> 0 | G75: =MAX(B74-B75,0) -> 0 | H75: =IF(SUM(G62:G75)=0,100,100-100/(1+AVERAGE(F62:F75)/AVERAGE(G62:G75))) -> 0 | I75: =C75+2*_xlfn.STDEV.S(B56:B75) -> 0 | J75: =C75-2*_xlfn.STDEV.S(B56:B75) -> 0
A76: ='1_Precios'!A74 -> 0 | B76: =INDEX('1_Precios'!$B$74:$F$74,MATCH($B$1,'1_Precios'!$B$1:$F$1,0)) -> 0 | C76: =AVERAGE(B57:B76) -> 0 | D76: =AVERAGE(B27:B76) -> 0 | E76: =IF(AND(C76>D76,C75<=D75),"COMPRA (cruce alcista)",IF(AND(C76<D76,C75>=D75),"VENTA (cruce bajista)","")) -> 0 | F76: =MAX(B76-B75,0) -> 0 | G76: =MAX(B75-B76,0) -> 0 | H76: =IF(SUM(G63:G76)=0,100,100-100/(1+AVERAGE(F63:F76)/AVERAGE(G63:G76))) -> 0 | I76: =C76+2*_xlfn.STDEV.S(B57:B76) -> 0 | J76: =C76-2*_xlfn.STDEV.S(B57:B76) -> 0
A77: ='1_Precios'!A75 -> 0 | B77: =INDEX('1_Precios'!$B$75:$F$75,MATCH($B$1,'1_Precios'!$B$1:$F$1,0)) -> 0 | C77: =AVERAGE(B58:B77) -> 0 | D77: =AVERAGE(B28:B77) -> 0 | E77: =IF(AND(C77>D77,C76<=D76),"COMPRA (cruce alcista)",IF(AND(C77<D77,C76>=D76),"VENTA (cruce bajista)","")) -> 0 | F77: =MAX(B77-B76,0) -> 0 | G77: =MAX(B76-B77,0) -> 0 | H77: =IF(SUM(G64:G77)=0,100,100-100/(1+AVERAGE(F64:F77)/AVERAGE(G64:G77))) -> 0 | I77: =C77+2*_xlfn.STDEV.S(B58:B77) -> 0 | J77: =C77-2*_xlfn.STDEV.S(B58:B77) -> 0
A78: ='1_Precios'!A76 -> 0 | B78: =INDEX('1_Precios'!$B$76:$F$76,MATCH($B$1,'1_Precios'!$B$1:$F$1,0)) -> 0 | C78: =AVERAGE(B59:B78) -> 0 | D78: =AVERAGE(B29:B78) -> 0 | E78: =IF(AND(C78>D78,C77<=D77),"COMPRA (cruce alcista)",IF(AND(C78<D78,C77>=D77),"VENTA (cruce bajista)","")) -> 0 | F78: =MAX(B78-B77,0) -> 0 | G78: =MAX(B77-B78,0) -> 0 | H78: =IF(SUM(G65:G78)=0,100,100-100/(1+AVERAGE(F65:F78)/AVERAGE(G65:G78))) -> 0 | I78: =C78+2*_xlfn.STDEV.S(B59:B78) -> 0 | J78: =C78-2*_xlfn.STDEV.S(B59:B78) -> 0
A79: ='1_Precios'!A77 -> 0 | B79: =INDEX('1_Precios'!$B$77:$F$77,MATCH($B$1,'1_Precios'!$B$1:$F$1,0)) -> 0 | C79: =AVERAGE(B60:B79) -> 0 | D79: =AVERAGE(B30:B79) -> 0 | E79: =IF(AND(C79>D79,C78<=D78),"COMPRA (cruce alcista)",IF(AND(C79<D79,C78>=D78),"VENTA (cruce bajista)","")) -> 0 | F79: =MAX(B79-B78,0) -> 0 | G79: =MAX(B78-B79,0) -> 0 | H79: =IF(SUM(G66:G79)=0,100,100-100/(1+AVERAGE(F66:F79)/AVERAGE(G66:G79))) -> 0 | I79: =C79+2*_xlfn.STDEV.S(B60:B79) -> 0 | J79: =C79-2*_xlfn.STDEV.S(B60:B79) -> 0
A80: ='1_Precios'!A78 -> 0 | B80: =INDEX('1_Precios'!$B$78:$F$78,MATCH($B$1,'1_Precios'!$B$1:$F$1,0)) -> 0 | C80: =AVERAGE(B61:B80) -> 0 | D80: =AVERAGE(B31:B80) -> 0 | E80: =IF(AND(C80>D80,C79<=D79),"COMPRA (cruce alcista)",IF(AND(C80<D80,C79>=D79),"VENTA (cruce bajista)","")) -> 0 | F80: =MAX(B80-B79,0) -> 0 | G80: =MAX(B79-B80,0) -> 0 | H80: =IF(SUM(G67:G80)=0,100,100-100/(1+AVERAGE(F67:F80)/AVERAGE(G67:G80))) -> 0 | I80: =C80+2*_xlfn.STDEV.S(B61:B80) -> 0 | J80: =C80-2*_xlfn.STDEV.S(B61:B80) -> 0
A81: ='1_Precios'!A79 -> 0 | B81: =INDEX('1_Precios'!$B$79:$F$79,MATCH($B$1,'1_Precios'!$B$1:$F$1,0)) -> 0 | C81: =AVERAGE(B62:B81) -> 0 | D81: =AVERAGE(B32:B81) -> 0 | E81: =IF(AND(C81>D81,C80<=D80),"COMPRA (cruce alcista)",IF(AND(C81<D81,C80>=D80),"VENTA (cruce bajista)","")) -> 0 | F81: =MAX(B81-B80,0) -> 0 | G81: =MAX(B80-B81,0) -> 0 | H81: =IF(SUM(G68:G81)=0,100,100-100/(1+AVERAGE(F68:F81)/AVERAGE(G68:G81))) -> 0 | I81: =C81+2*_xlfn.STDEV.S(B62:B81) -> 0 | J81: =C81-2*_xlfn.STDEV.S(B62:B81) -> 0
A82: ='1_Precios'!A80 -> 0 | B82: =INDEX('1_Precios'!$B$80:$F$80,MATCH($B$1,'1_Precios'!$B$1:$F$1,0)) -> 0 | C82: =AVERAGE(B63:B82) -> 0 | D82: =AVERAGE(B33:B82) -> 0 | E82: =IF(AND(C82>D82,C81<=D81),"COMPRA (cruce alcista)",IF(AND(C82<D82,C81>=D81),"VENTA (cruce bajista)","")) -> 0 | F82: =MAX(B82-B81,0) -> 0 | G82: =MAX(B81-B82,0) -> 0 | H82: =IF(SUM(G69:G82)=0,100,100-100/(1+AVERAGE(F69:F82)/AVERAGE(G69:G82))) -> 0 | I82: =C82+2*_xlfn.STDEV.S(B63:B82) -> 0 | J82: =C82-2*_xlfn.STDEV.S(B63:B82) -> 0
A83: ='1_Precios'!A81 -> 0 | B83: =INDEX('1_Precios'!$B$81:$F$81,MATCH($B$1,'1_Precios'!$B$1:$F$1,0)) -> 0 | C83: =AVERAGE(B64:B83) -> 0 | D83: =AVERAGE(B34:B83) -> 0 | E83: =IF(AND(C83>D83,C82<=D82),"COMPRA (cruce alcista)",IF(AND(C83<D83,C82>=D82),"VENTA (cruce bajista)","")) -> 0 | F83: =MAX(B83-B82,0) -> 0 | G83: =MAX(B82-B83,0) -> 0 | H83: =IF(SUM(G70:G83)=0,100,100-100/(1+AVERAGE(F70:F83)/AVERAGE(G70:G83))) -> 0 | I83: =C83+2*_xlfn.STDEV.S(B64:B83) -> 0 | J83: =C83-2*_xlfn.STDEV.S(B64:B83) -> 0
A84: ='1_Precios'!A82 -> 0 | B84: =INDEX('1_Precios'!$B$82:$F$82,MATCH($B$1,'1_Precios'!$B$1:$F$1,0)) -> 0 | C84: =AVERAGE(B65:B84) -> 0 | D84: =AVERAGE(B35:B84) -> 0 | E84: =IF(AND(C84>D84,C83<=D83),"COMPRA (cruce alcista)",IF(AND(C84<D84,C83>=D83),"VENTA (cruce bajista)","")) -> 0 | F84: =MAX(B84-B83,0) -> 0 | G84: =MAX(B83-B84,0) -> 0 | H84: =IF(SUM(G71:G84)=0,100,100-100/(1+AVERAGE(F71:F84)/AVERAGE(G71:G84))) -> 0 | I84: =C84+2*_xlfn.STDEV.S(B65:B84) -> 0 | J84: =C84-2*_xlfn.STDEV.S(B65:B84) -> 0
A85: ='1_Precios'!A83 -> 0 | B85: =INDEX('1_Precios'!$B$83:$F$83,MATCH($B$1,'1_Precios'!$B$1:$F$1,0)) -> 0 | C85: =AVERAGE(B66:B85) -> 0 | D85: =AVERAGE(B36:B85) -> 0 | E85: =IF(AND(C85>D85,C84<=D84),"COMPRA (cruce alcista)",IF(AND(C85<D85,C84>=D84),"VENTA (cruce bajista)","")) -> 0 | F85: =MAX(B85-B84,0) -> 0 | G85: =MAX(B84-B85,0) -> 0 | H85: =IF(SUM(G72:G85)=0,100,100-100/(1+AVERAGE(F72:F85)/AVERAGE(G72:G85))) -> 0 | I85: =C85+2*_xlfn.STDEV.S(B66:B85) -> 0 | J85: =C85-2*_xlfn.STDEV.S(B66:B85) -> 0
A86: ='1_Precios'!A84 -> 0 | B86: =INDEX('1_Precios'!$B$84:$F$84,MATCH($B$1,'1_Precios'!$B$1:$F$1,0)) -> 0 | C86: =AVERAGE(B67:B86) -> 0 | D86: =AVERAGE(B37:B86) -> 0 | E86: =IF(AND(C86>D86,C85<=D85),"COMPRA (cruce alcista)",IF(AND(C86<D86,C85>=D85),"VENTA (cruce bajista)","")) -> 0 | F86: =MAX(B86-B85,0) -> 0 | G86: =MAX(B85-B86,0) -> 0 | H86: =IF(SUM(G73:G86)=0,100,100-100/(1+AVERAGE(F73:F86)/AVERAGE(G73:G86))) -> 0 | I86: =C86+2*_xlfn.STDEV.S(B67:B86) -> 0 | J86: =C86-2*_xlfn.STDEV.S(B67:B86) -> 0
A87: ='1_Precios'!A85 -> 0 | B87: =INDEX('1_Precios'!$B$85:$F$85,MATCH($B$1,'1_Precios'!$B$1:$F$1,0)) -> 0 | C87: =AVERAGE(B68:B87) -> 0 | D87: =AVERAGE(B38:B87) -> 0 | E87: =IF(AND(C87>D87,C86<=D86),"COMPRA (cruce alcista)",IF(AND(C87<D87,C86>=D86),"VENTA (cruce bajista)","")) -> 0 | F87: =MAX(B87-B86,0) -> 0 | G87: =MAX(B86-B87,0) -> 0 | H87: =IF(SUM(G74:G87)=0,100,100-100/(1+AVERAGE(F74:F87)/AVERAGE(G74:G87))) -> 0 | I87: =C87+2*_xlfn.STDEV.S(B68:B87) -> 0 | J87: =C87-2*_xlfn.STDEV.S(B68:B87) -> 0
A88: ='1_Precios'!A86 -> 0 | B88: =INDEX('1_Precios'!$B$86:$F$86,MATCH($B$1,'1_Precios'!$B$1:$F$1,0)) -> 0 | C88: =AVERAGE(B69:B88) -> 0 | D88: =AVERAGE(B39:B88) -> 0 | E88: =IF(AND(C88>D88,C87<=D87),"COMPRA (cruce alcista)",IF(AND(C88<D88,C87>=D87),"VENTA (cruce bajista)","")) -> 0 | F88: =MAX(B88-B87,0) -> 0 | G88: =MAX(B87-B88,0) -> 0 | H88: =IF(SUM(G75:G88)=0,100,100-100/(1+AVERAGE(F75:F88)/AVERAGE(G75:G88))) -> 0 | I88: =C88+2*_xlfn.STDEV.S(B69:B88) -> 0 | J88: =C88-2*_xlfn.STDEV.S(B69:B88) -> 0
A89: ='1_Precios'!A87 -> 0 | B89: =INDEX('1_Precios'!$B$87:$F$87,MATCH($B$1,'1_Precios'!$B$1:$F$1,0)) -> 0 | C89: =AVERAGE(B70:B89) -> 0 | D89: =AVERAGE(B40:B89) -> 0 | E89: =IF(AND(C89>D89,C88<=D88),"COMPRA (cruce alcista)",IF(AND(C89<D89,C88>=D88),"VENTA (cruce bajista)","")) -> 0 | F89: =MAX(B89-B88,0) -> 0 | G89: =MAX(B88-B89,0) -> 0 | H89: =IF(SUM(G76:G89)=0,100,100-100/(1+AVERAGE(F76:F89)/AVERAGE(G76:G89))) -> 0 | I89: =C89+2*_xlfn.STDEV.S(B70:B89) -> 0 | J89: =C89-2*_xlfn.STDEV.S(B70:B89) -> 0
A90: ='1_Precios'!A88 -> 0 | B90: =INDEX('1_Precios'!$B$88:$F$88,MATCH($B$1,'1_Precios'!$B$1:$F$1,0)) -> 0 | C90: =AVERAGE(B71:B90) -> 0 | D90: =AVERAGE(B41:B90) -> 0 | E90: =IF(AND(C90>D90,C89<=D89),"COMPRA (cruce alcista)",IF(AND(C90<D90,C89>=D89),"VENTA (cruce bajista)","")) -> 0 | F90: =MAX(B90-B89,0) -> 0 | G90: =MAX(B89-B90,0) -> 0 | H90: =IF(SUM(G77:G90)=0,100,100-100/(1+AVERAGE(F77:F90)/AVERAGE(G77:G90))) -> 0 | I90: =C90+2*_xlfn.STDEV.S(B71:B90) -> 0 | J90: =C90-2*_xlfn.STDEV.S(B71:B90) -> 0
A91: ='1_Precios'!A89 -> 0 | B91: =INDEX('1_Precios'!$B$89:$F$89,MATCH($B$1,'1_Precios'!$B$1:$F$1,0)) -> 0 | C91: =AVERAGE(B72:B91) -> 0 | D91: =AVERAGE(B42:B91) -> 0 | E91: =IF(AND(C91>D91,C90<=D90),"COMPRA (cruce alcista)",IF(AND(C91<D91,C90>=D90),"VENTA (cruce bajista)","")) -> 0 | F91: =MAX(B91-B90,0) -> 0 | G91: =MAX(B90-B91,0) -> 0 | H91: =IF(SUM(G78:G91)=0,100,100-100/(1+AVERAGE(F78:F91)/AVERAGE(G78:G91))) -> 0 | I91: =C91+2*_xlfn.STDEV.S(B72:B91) -> 0 | J91: =C91-2*_xlfn.STDEV.S(B72:B91) -> 0
A92: ='1_Precios'!A90 -> 0 | B92: =INDEX('1_Precios'!$B$90:$F$90,MATCH($B$1,'1_Precios'!$B$1:$F$1,0)) -> 0 | C92: =AVERAGE(B73:B92) -> 0 | D92: =AVERAGE(B43:B92) -> 0 | E92: =IF(AND(C92>D92,C91<=D91),"COMPRA (cruce alcista)",IF(AND(C92<D92,C91>=D91),"VENTA (cruce bajista)","")) -> 0 | F92: =MAX(B92-B91,0) -> 0 | G92: =MAX(B91-B92,0) -> 0 | H92: =IF(SUM(G79:G92)=0,100,100-100/(1+AVERAGE(F79:F92)/AVERAGE(G79:G92))) -> 0 | I92: =C92+2*_xlfn.STDEV.S(B73:B92) -> 0 | J92: =C92-2*_xlfn.STDEV.S(B73:B92) -> 0
A93: ='1_Precios'!A91 -> 0 | B93: =INDEX('1_Precios'!$B$91:$F$91,MATCH($B$1,'1_Precios'!$B$1:$F$1,0)) -> 0 | C93: =AVERAGE(B74:B93) -> 0 | D93: =AVERAGE(B44:B93) -> 0 | E93: =IF(AND(C93>D93,C92<=D92),"COMPRA (cruce alcista)",IF(AND(C93<D93,C92>=D92),"VENTA (cruce bajista)","")) -> 0 | F93: =MAX(B93-B92,0) -> 0 | G93: =MAX(B92-B93,0) -> 0 | H93: =IF(SUM(G80:G93)=0,100,100-100/(1+AVERAGE(F80:F93)/AVERAGE(G80:G93))) -> 0 | I93: =C93+2*_xlfn.STDEV.S(B74:B93) -> 0 | J93: =C93-2*_xlfn.STDEV.S(B74:B93) -> 0
A94: ='1_Precios'!A92 -> 0 | B94: =INDEX('1_Precios'!$B$92:$F$92,MATCH($B$1,'1_Precios'!$B$1:$F$1,0)) -> 0 | C94: =AVERAGE(B75:B94) -> 0 | D94: =AVERAGE(B45:B94) -> 0 | E94: =IF(AND(C94>D94,C93<=D93),"COMPRA (cruce alcista)",IF(AND(C94<D94,C93>=D93),"VENTA (cruce bajista)","")) -> 0 | F94: =MAX(B94-B93,0) -> 0 | G94: =MAX(B93-B94,0) -> 0 | H94: =IF(SUM(G81:G94)=0,100,100-100/(1+AVERAGE(F81:F94)/AVERAGE(G81:G94))) -> 0 | I94: =C94+2*_xlfn.STDEV.S(B75:B94) -> 0 | J94: =C94-2*_xlfn.STDEV.S(B75:B94) -> 0
A95: ='1_Precios'!A93 -> 0 | B95: =INDEX('1_Precios'!$B$93:$F$93,MATCH($B$1,'1_Precios'!$B$1:$F$1,0)) -> 0 | C95: =AVERAGE(B76:B95) -> 0 | D95: =AVERAGE(B46:B95) -> 0 | E95: =IF(AND(C95>D95,C94<=D94),"COMPRA (cruce alcista)",IF(AND(C95<D95,C94>=D94),"VENTA (cruce bajista)","")) -> 0 | F95: =MAX(B95-B94,0) -> 0 | G95: =MAX(B94-B95,0) -> 0 | H95: =IF(SUM(G82:G95)=0,100,100-100/(1+AVERAGE(F82:F95)/AVERAGE(G82:G95))) -> 0 | I95: =C95+2*_xlfn.STDEV.S(B76:B95) -> 0 | J95: =C95-2*_xlfn.STDEV.S(B76:B95) -> 0
A96: ='1_Precios'!A94 -> 0 | B96: =INDEX('1_Precios'!$B$94:$F$94,MATCH($B$1,'1_Precios'!$B$1:$F$1,0)) -> 0 | C96: =AVERAGE(B77:B96) -> 0 | D96: =AVERAGE(B47:B96) -> 0 | E96: =IF(AND(C96>D96,C95<=D95),"COMPRA (cruce alcista)",IF(AND(C96<D96,C95>=D95),"VENTA (cruce bajista)","")) -> 0 | F96: =MAX(B96-B95,0) -> 0 | G96: =MAX(B95-B96,0) -> 0 | H96: =IF(SUM(G83:G96)=0,100,100-100/(1+AVERAGE(F83:F96)/AVERAGE(G83:G96))) -> 0 | I96: =C96+2*_xlfn.STDEV.S(B77:B96) -> 0 | J96: =C96-2*_xlfn.STDEV.S(B77:B96) -> 0
A97: ='1_Precios'!A95 -> 0 | B97: =INDEX('1_Precios'!$B$95:$F$95,MATCH($B$1,'1_Precios'!$B$1:$F$1,0)) -> 0 | C97: =AVERAGE(B78:B97) -> 0 | D97: =AVERAGE(B48:B97) -> 0 | E97: =IF(AND(C97>D97,C96<=D96),"COMPRA (cruce alcista)",IF(AND(C97<D97,C96>=D96),"VENTA (cruce bajista)","")) -> 0 | F97: =MAX(B97-B96,0) -> 0 | G97: =MAX(B96-B97,0) -> 0 | H97: =IF(SUM(G84:G97)=0,100,100-100/(1+AVERAGE(F84:F97)/AVERAGE(G84:G97))) -> 0 | I97: =C97+2*_xlfn.STDEV.S(B78:B97) -> 0 | J97: =C97-2*_xlfn.STDEV.S(B78:B97) -> 0
A98: ='1_Precios'!A96 -> 0 | B98: =INDEX('1_Precios'!$B$96:$F$96,MATCH($B$1,'1_Precios'!$B$1:$F$1,0)) -> 0 | C98: =AVERAGE(B79:B98) -> 0 | D98: =AVERAGE(B49:B98) -> 0 | E98: =IF(AND(C98>D98,C97<=D97),"COMPRA (cruce alcista)",IF(AND(C98<D98,C97>=D97),"VENTA (cruce bajista)","")) -> 0 | F98: =MAX(B98-B97,0) -> 0 | G98: =MAX(B97-B98,0) -> 0 | H98: =IF(SUM(G85:G98)=0,100,100-100/(1+AVERAGE(F85:F98)/AVERAGE(G85:G98))) -> 0 | I98: =C98+2*_xlfn.STDEV.S(B79:B98) -> 0 | J98: =C98-2*_xlfn.STDEV.S(B79:B98) -> 0
A99: ='1_Precios'!A97 -> 0 | B99: =INDEX('1_Precios'!$B$97:$F$97,MATCH($B$1,'1_Precios'!$B$1:$F$1,0)) -> 0 | C99: =AVERAGE(B80:B99) -> 0 | D99: =AVERAGE(B50:B99) -> 0 | E99: =IF(AND(C99>D99,C98<=D98),"COMPRA (cruce alcista)",IF(AND(C99<D99,C98>=D98),"VENTA (cruce bajista)","")) -> 0 | F99: =MAX(B99-B98,0) -> 0 | G99: =MAX(B98-B99,0) -> 0 | H99: =IF(SUM(G86:G99)=0,100,100-100/(1+AVERAGE(F86:F99)/AVERAGE(G86:G99))) -> 0 | I99: =C99+2*_xlfn.STDEV.S(B80:B99) -> 0 | J99: =C99-2*_xlfn.STDEV.S(B80:B99) -> 0
A100: ='1_Precios'!A98 -> 0 | B100: =INDEX('1_Precios'!$B$98:$F$98,MATCH($B$1,'1_Precios'!$B$1:$F$1,0)) -> 0 | C100: =AVERAGE(B81:B100) -> 0 | D100: =AVERAGE(B51:B100) -> 0 | E100: =IF(AND(C100>D100,C99<=D99),"COMPRA (cruce alcista)",IF(AND(C100<D100,C99>=D99),"VENTA (cruce bajista)","")) -> 0 | F100: =MAX(B100-B99,0) -> 0 | G100: =MAX(B99-B100,0) -> 0 | H100: =IF(SUM(G87:G100)=0,100,100-100/(1+AVERAGE(F87:F100)/AVERAGE(G87:G100))) -> 0 | I100: =C100+2*_xlfn.STDEV.S(B81:B100) -> 0 | J100: =C100-2*_xlfn.STDEV.S(B81:B100) -> 0
A101: ='1_Precios'!A99 -> 0 | B101: =INDEX('1_Precios'!$B$99:$F$99,MATCH($B$1,'1_Precios'!$B$1:$F$1,0)) -> 0 | C101: =AVERAGE(B82:B101) -> 0 | D101: =AVERAGE(B52:B101) -> 0 | E101: =IF(AND(C101>D101,C100<=D100),"COMPRA (cruce alcista)",IF(AND(C101<D101,C100>=D100),"VENTA (cruce bajista)","")) -> 0 | F101: =MAX(B101-B100,0) -> 0 | G101: =MAX(B100-B101,0) -> 0 | H101: =IF(SUM(G88:G101)=0,100,100-100/(1+AVERAGE(F88:F101)/AVERAGE(G88:G101))) -> 0 | I101: =C101+2*_xlfn.STDEV.S(B82:B101) -> 0 | J101: =C101-2*_xlfn.STDEV.S(B82:B101) -> 0
...

Sheet 8_Drawdown
A1: Fecha | B1: DD BANCO | C1: DD RETAIL | D1: DD MINERA | E1: DD ENERGIA | F1: DD CONSUMO | G1: DD IPSA | I1: MAXIMO DRAWDOWN
A2: ='1_Precios'!A2 -> 0 | B2: ='1_Precios'!B2/MAX('1_Precios'!B$2:B2)-1 -> 0 | C2: ='1_Precios'!C2/MAX('1_Precios'!C$2:C2)-1 -> 0 | D2: ='1_Precios'!D2/MAX('1_Precios'!D$2:D2)-1 -> 0 | E2: ='1_Precios'!E2/MAX('1_Precios'!E$2:E2)-1 -> 0 | F2: ='1_Precios'!F2/MAX('1_Precios'!F$2:F2)-1 -> 0 | G2: ='1_Precios'!G2/MAX('1_Precios'!G$2:G2)-1 -> 0 | I2: BANCO | J2: =MIN(B2:B253) -> 0
A3: ='1_Precios'!A3 -> 0 | B3: ='1_Precios'!B3/MAX('1_Precios'!B$2:B3)-1 -> 0 | C3: ='1_Precios'!C3/MAX('1_Precios'!C$2:C3)-1 -> 0 | D3: ='1_Precios'!D3/MAX('1_Precios'!D$2:D3)-1 -> 0 | E3: ='1_Precios'!E3/MAX('1_Precios'!E$2:E3)-1 -> 0 | F3: ='1_Precios'!F3/MAX('1_Precios'!F$2:F3)-1 -> 0 | G3: ='1_Precios'!G3/MAX('1_Precios'!G$2:G3)-1 -> 0 | I3: RETAIL | J3: =MIN(C2:C253) -> 0
A4: ='1_Precios'!A4 -> 0 | B4: ='1_Precios'!B4/MAX('1_Precios'!B$2:B4)-1 -> 0 | C4: ='1_Precios'!C4/MAX('1_Precios'!C$2:C4)-1 -> 0 | D4: ='1_Precios'!D4/MAX('1_Precios'!D$2:D4)-1 -> 0 | E4: ='1_Precios'!E4/MAX('1_Precios'!E$2:E4)-1 -> 0 | F4: ='1_Precios'!F4/MAX('1_Precios'!F$2:F4)-1 -> 0 | G4: ='1_Precios'!G4/MAX('1_Precios'!G$2:G4)-1 -> 0 | I4: MINERA | J4: =MIN(D2:D253) -> 0
A5: ='1_Precios'!A5 -> 0 | B5: ='1_Precios'!B5/MAX('1_Precios'!B$2:B5)-1 -> 0 | C5: ='1_Precios'!C5/MAX('1_Precios'!C$2:C5)-1 -> 0 | D5: ='1_Precios'!D5/MAX('1_Precios'!D$2:D5)-1 -> 0 | E5: ='1_Precios'!E5/MAX('1_Precios'!E$2:E5)-1 -> 0 | F5: ='1_Precios'!F5/MAX('1_Precios'!F$2:F5)-1 -> 0 | G5: ='1_Precios'!G5/MAX('1_Precios'!G$2:G5)-1 -> 0 | I5: ENERGIA | J5: =MIN(E2:E253) -> 0
A6: ='1_Precios'!A6 -> 0 | B6: ='1_Precios'!B6/MAX('1_Precios'!B$2:B6)-1 -> 0 | C6: ='1_Precios'!C6/MAX('1_Precios'!C$2:C6)-1 -> 0 | D6: ='1_Precios'!D6/MAX('1_Precios'!D$2:D6)-1 -> 0 | E6: ='1_Precios'!E6/MAX('1_Precios'!E$2:E6)-1 -> 0 | F6: ='1_Precios'!F6/MAX('1_Precios'!F$2:F6)-1 -> 0 | G6: ='1_Precios'!G6/MAX('1_Precios'!G$2:G6)-1 -> 0 | I6: CONSUMO | J6: =MIN(F2:F253) -> 0
A7: ='1_Precios'!A7 -> 0 | B7: ='1_Precios'!B7/MAX('1_Precios'!B$2:B7)-1 -> 0 | C7: ='1_Precios'!C7/MAX('1_Precios'!C$2:C7)-1 -> 0 | D7: ='1_Precios'!D7/MAX('1_Precios'!D$2:D7)-1 -> 0 | E7: ='1_Precios'!E7/MAX('1_Precios'!E$2:E7)-1 -> 0 | F7: ='1_Precios'!F7/MAX('1_Precios'!F$2:F7)-1 -> 0 | G7: ='1_Precios'!G7/MAX('1_Precios'!G$2:G7)-1 -> 0 | I7: IPSA | J7: =MIN(G2:G253) -> 0
A8: ='1_Precios'!A8 -> 0 | B8: ='1_Precios'!B8/MAX('1_Precios'!B$2:B8)-1 -> 0 | C8: ='1_Precios'!C8/MAX('1_Precios'!C$2:C8)-1 -> 0 | D8: ='1_Precios'!D8/MAX('1_Precios'!D$2:D8)-1 -> 0 | E8: ='1_Precios'!E8/MAX('1_Precios'!E$2:E8)-1 -> 0 | F8: ='1_Precios'!F8/MAX('1_Precios'!F$2:F8)-1 -> 0 | G8: ='1_Precios'!G8/MAX('1_Precios'!G$2:G8)-1 -> 0
A9: ='1_Precios'!A9 -> 0 | B9: ='1_Precios'!B9/MAX('1_Precios'!B$2:B9)-1 -> 0 | C9: ='1_Precios'!C9/MAX('1_Precios'!C$2:C9)-1 -> 0 | D9: ='1_Precios'!D9/MAX('1_Precios'!D$2:D9)-1 -> 0 | E9: ='1_Precios'!E9/MAX('1_Precios'!E$2:E9)-1 -> 0 | F9: ='1_Precios'!F9/MAX('1_Precios'!F$2:F9)-1 -> 0 | G9: ='1_Precios'!G9/MAX('1_Precios'!G$2:G9)-1 -> 0 | I9: Drawdown = caida desde el maximo previo. Una caida de -50% exige +100% para recuperarse.
A10: ='1_Precios'!A10 -> 0 | B10: ='1_Precios'!B10/MAX('1_Precios'!B$2:B10)-1 -> 0 | C10: ='1_Precios'!C10/MAX('1_Precios'!C$2:C10)-1 -> 0 | D10: ='1_Precios'!D10/MAX('1_Precios'!D$2:D10)-1 -> 0 | E10: ='1_Precios'!E10/MAX('1_Precios'!E$2:E10)-1 -> 0 | F10: ='1_Precios'!F10/MAX('1_Precios'!F$2:F10)-1 -> 0 | G10: ='1_Precios'!G10/MAX('1_Precios'!G$2:G10)-1 -> 0
A11: ='1_Precios'!A11 -> 0 | B11: ='1_Precios'!B11/MAX('1_Precios'!B$2:B11)-1 -> 0 | C11: ='1_Precios'!C11/MAX('1_Precios'!C$2:C11)-1 -> 0 | D11: ='1_Precios'!D11/MAX('1_Precios'!D$2:D11)-1 -> 0 | E11: ='1_Precios'!E11/MAX('1_Precios'!E$2:E11)-1 -> 0 | F11: ='1_Precios'!F11/MAX('1_Precios'!F$2:F11)-1 -> 0 | G11: ='1_Precios'!G11/MAX('1_Precios'!G$2:G11)-1 -> 0
A12: ='1_Precios'!A12 -> 0 | B12: ='1_Precios'!B12/MAX('1_Precios'!B$2:B12)-1 -> 0 | C12: ='1_Precios'!C12/MAX('1_Precios'!C$2:C12)-1 -> 0 | D12: ='1_Precios'!D12/MAX('1_Precios'!D$2:D12)-1 -> 0 | E12: ='1_Precios'!E12/MAX('1_Precios'!E$2:E12)-1 -> 0 | F12: ='1_Precios'!F12/MAX('1_Precios'!F$2:F12)-1 -> 0 | G12: ='1_Precios'!G12/MAX('1_Precios'!G$2:G12)-1 -> 0
A13: ='1_Precios'!A13 -> 0 | B13: ='1_Precios'!B13/MAX('1_Precios'!B$2:B13)-1 -> 0 | C13: ='1_Precios'!C13/MAX('1_Precios'!C$2:C13)-1 -> 0 | D13: ='1_Precios'!D13/MAX('1_Precios'!D$2:D13)-1 -> 0 | E13: ='1_Precios'!E13/MAX('1_Precios'!E$2:E13)-1 -> 0 | F13: ='1_Precios'!F13/MAX('1_Precios'!F$2:F13)-1 -> 0 | G13: ='1_Precios'!G13/MAX('1_Precios'!G$2:G13)-1 -> 0
A14: ='1_Precios'!A14 -> 0 | B14: ='1_Precios'!B14/MAX('1_Precios'!B$2:B14)-1 -> 0 | C14: ='1_Precios'!C14/MAX('1_Precios'!C$2:C14)-1 -> 0 | D14: ='1_Precios'!D14/MAX('1_Precios'!D$2:D14)-1 -> 0 | E14: ='1_Precios'!E14/MAX('1_Precios'!E$2:E14)-1 -> 0 | F14: ='1_Precios'!F14/MAX('1_Precios'!F$2:F14)-1 -> 0 | G14: ='1_Precios'!G14/MAX('1_Precios'!G$2:G14)-1 -> 0
A15: ='1_Precios'!A15 -> 0 | B15: ='1_Precios'!B15/MAX('1_Precios'!B$2:B15)-1 -> 0 | C15: ='1_Precios'!C15/MAX('1_Precios'!C$2:C15)-1 -> 0 | D15: ='1_Precios'!D15/MAX('1_Precios'!D$2:D15)-1 -> 0 | E15: ='1_Precios'!E15/MAX('1_Precios'!E$2:E15)-1 -> 0 | F15: ='1_Precios'!F15/MAX('1_Precios'!F$2:F15)-1 -> 0 | G15: ='1_Precios'!G15/MAX('1_Precios'!G$2:G15)-1 -> 0
A16: ='1_Precios'!A16 -> 0 | B16: ='1_Precios'!B16/MAX('1_Precios'!B$2:B16)-1 -> 0 | C16: ='1_Precios'!C16/MAX('1_Precios'!C$2:C16)-1 -> 0 | D16: ='1_Precios'!D16/MAX('1_Precios'!D$2:D16)-1 -> 0 | E16: ='1_Precios'!E16/MAX('1_Precios'!E$2:E16)-1 -> 0 | F16: ='1_Precios'!F16/MAX('1_Precios'!F$2:F16)-1 -> 0 | G16: ='1_Precios'!G16/MAX('1_Precios'!G$2:G16)-1 -> 0
A17: ='1_Precios'!A17 -> 0 | B17: ='1_Precios'!B17/MAX('1_Precios'!B$2:B17)-1 -> 0 | C17: ='1_Precios'!C17/MAX('1_Precios'!C$2:C17)-1 -> 0 | D17: ='1_Precios'!D17/MAX('1_Precios'!D$2:D17)-1 -> 0 | E17: ='1_Precios'!E17/MAX('1_Precios'!E$2:E17)-1 -> 0 | F17: ='1_Precios'!F17/MAX('1_Precios'!F$2:F17)-1 -> 0 | G17: ='1_Precios'!G17/MAX('1_Precios'!G$2:G17)-1 -> 0
A18: ='1_Precios'!A18 -> 0 | B18: ='1_Precios'!B18/MAX('1_Precios'!B$2:B18)-1 -> 0 | C18: ='1_Precios'!C18/MAX('1_Precios'!C$2:C18)-1 -> 0 | D18: ='1_Precios'!D18/MAX('1_Precios'!D$2:D18)-1 -> 0 | E18: ='1_Precios'!E18/MAX('1_Precios'!E$2:E18)-1 -> 0 | F18: ='1_Precios'!F18/MAX('1_Precios'!F$2:F18)-1 -> 0 | G18: ='1_Precios'!G18/MAX('1_Precios'!G$2:G18)-1 -> 0
A19: ='1_Precios'!A19 -> 0 | B19: ='1_Precios'!B19/MAX('1_Precios'!B$2:B19)-1 -> 0 | C19: ='1_Precios'!C19/MAX('1_Precios'!C$2:C19)-1 -> 0 | D19: ='1_Precios'!D19/MAX('1_Precios'!D$2:D19)-1 -> 0 | E19: ='1_Precios'!E19/MAX('1_Precios'!E$2:E19)-1 -> 0 | F19: ='1_Precios'!F19/MAX('1_Precios'!F$2:F19)-1 -> 0 | G19: ='1_Precios'!G19/MAX('1_Precios'!G$2:G19)-1 -> 0
A20: ='1_Precios'!A20 -> 0 | B20: ='1_Precios'!B20/MAX('1_Precios'!B$2:B20)-1 -> 0 | C20: ='1_Precios'!C20/MAX('1_Precios'!C$2:C20)-1 -> 0 | D20: ='1_Precios'!D20/MAX('1_Precios'!D$2:D20)-1 -> 0 | E20: ='1_Precios'!E20/MAX('1_Precios'!E$2:E20)-1 -> 0 | F20: ='1_Precios'!F20/MAX('1_Precios'!F$2:F20)-1 -> 0 | G20: ='1_Precios'!G20/MAX('1_Precios'!G$2:G20)-1 -> 0
A21: ='1_Precios'!A21 -> 0 | B21: ='1_Precios'!B21/MAX('1_Precios'!B$2:B21)-1 -> 0 | C21: ='1_Precios'!C21/MAX('1_Precios'!C$2:C21)-1 -> 0 | D21: ='1_Precios'!D21/MAX('1_Precios'!D$2:D21)-1 -> 0 | E21: ='1_Precios'!E21/MAX('1_Precios'!E$2:E21)-1 -> 0 | F21: ='1_Precios'!F21/MAX('1_Precios'!F$2:F21)-1 -> 0 | G21: ='1_Precios'!G21/MAX('1_Precios'!G$2:G21)-1 -> 0
... A253: ='1_Precios'!A253 -> 0 | B253: ='1_Precios'!B253/MAX('1_Precios'!B$2:B253)-1 -> 0 | C253: ='1_Precios'!C253/MAX('1_Precios'!C$2:C253)-1 -> 0 | D253: ='1_Precios'!D253/MAX('1_Precios'!D$2:D253)-1 -> 0 | E253: ='1_Precios'!E253/MAX('1_Precios'!E$2:E253)-1 -> 0 | F253: ='1_Precios'!F253/MAX('1_Precios'!F$2:F253)-1 -> 0 | G253: ='1_Precios'!G253/MAX('1_Precios'!G$2:G253)-1 -> 0

Sheet 9_Simulador_CCI
A1: CUADERNO DE OPERACIONES - CCI
A2: Registra cada operacion tal como la hiciste en el simulador. Las filas de ejemplo son ficticias: borralas antes de empezar.
A4: Capital inicial | C4: 20000000 | F4: IPSA al inicio | H4: 10000 | N4: RESUMEN DE LA CARTERA
A5: Comision por operacion | C5: 0.005 | D5: Confirmar en bases vigentes | F5: IPSA hoy | H5: 10250 | N5: Caja disponible | O5: =$C$4+SUM(H11:H110) -> 0 | P5: Alerta
A6: Limite de peso por accion | C6: 0.35 | D6: Tu regla de riesgo | N6: Valor de mercado acciones | O6: =SUM(T13:T27) -> 0 | P6: =IF(O5<0,"CAJA NEGATIVA",IF(MAX(V13:V27)>$C$6,"CONCENTRACION > limite","OK")) -> 0
N7: VALOR TOTAL CARTERA | O7: =O5+O6 -> 0
N8: Rentabilidad acumulada | O8: =O7/$C$4-1 -> 0
N9: Rentabilidad IPSA mismo periodo | O9: =$H$5/$H$4-1 -> 0
A10: Fecha | B10: Ticker | C10: Tipo | D10: Cantidad | E10: Precio | F10: Monto bruto | G10: Comision | H10: Flujo de caja | I10: Cant. +/- | J10: Tesis / motivo | K10: Stop | L10: Objetivo | N10: Exceso sobre IPSA | O10: =O8-O9 -> 0
A11: 46309 | B11: BANCO | C11: Compra | D11: 600 | E11: 5400 | F11: =IF(OR(D11="",E11=""),"",D11*E11) -> 0 | G11: =IF(F11="","",F11*$C$5) -> 0 | H11: =IF(F11="","",IF(C11="Compra",-(F11+G11),F11-G11)) -> 0 | I11: =IF(D11="","",IF(C11="Compra",D11,-D11)) -> 0 | J11: Ciclo de tasas: TPM a la baja mejora credito | K11: 4950 | L11: 6200 | N11: Comisiones pagadas (total) | O11: =SUM(G11:G110) -> 0
A12: 46309 | B12: MINERA | C12: Compra | D12: 110 | E12: 43000 | F12: =IF(OR(D12="",E12=""),"",D12*E12) -> 0 | G12: =IF(F12="","",F12*$C$5) -> 0 | H12: =IF(F12="","",IF(C12="Compra",-(F12+G12),F12-G12)) -> 0 | I12: =IF(D12="","",IF(C12="Compra",D12,-D12)) -> 0 | J12: Cobre al alza + resultados 3T esperados fuertes | K12: 39500 | L12: 50000 | N12: Comisiones como % del capital | O12: =O11/$C$4 -> 0 | P12: Ticker | Q12: Cantidad | R12: Precio medio compra | S12: Precio actual | T12: Valor mercado | U12: P&L no realizado | V12: Peso
A13: 46310 | B13: ENERGIA | C13: Compra | D13: 25000 | E13: 98 | F13: =IF(OR(D13="",E13=""),"",D13*E13) -> 0 | G13: =IF(F13="","",F13*$C$5) -> 0 | H13: =IF(F13="","",IF(C13="Compra",-(F13+G13),F13-G13)) -> 0 | I13: =IF(D13="","",IF(C13="Compra",D13,-D13)) -> 0 | J13: Defensiva, baja correlacion con mineria | K13: 90 | L13: 110 | P13: BANCO | Q13: =IF(P13="","",SUMIF($B$11:$B$110,P13,$I$11:$I$110)) -> 0 | R13: =IF(P13="","",IFERROR(SUMIFS($F$11:$F$110,$B$11:$B$110,P13,$C$11:$C$110,"Compra")/SUMIFS($D$11:$D$110,$B$11:$B$110,P13,$C$11:$C$110,"Compra"),0)) -> 0 | S13: 5550 | T13: =IF(OR(P13="",S13=""),"",Q13*S13) -> 0 | U13: =IF(T13="","",T13-Q13*R13) -> 0 | V13: =IF(T13="","",T13/$O$7) -> 0
A14: 46323 | B14: MINERA | C14: Venta | D14: 50 | E14: 47200 | F14: =IF(OR(D14="",E14=""),"",D14*E14) -> 0 | G14: =IF(F14="","",F14*$C$5) -> 0 | H14: =IF(F14="","",IF(C14="Compra",-(F14+G14),F14-G14)) -> 0 | I14: =IF(D14="","",IF(C14="Compra",D14,-D14)) -> 0 | J14: Toma de ganancia parcial tras resultados | P14: MINERA | Q14: =IF(P14="","",SUMIF($B$11:$B$110,P14,$I$11:$I$110)) -> 0 | R14: =IF(P14="","",IFERROR(SUMIFS($F$11:$F$110,$B$11:$B$110,P14,$C$11:$C$110,"Compra")/SUMIFS($D$11:$D$110,$B$11:$B$110,P14,$C$11:$C$110,"Compra"),0)) -> 0 | S14: 46100 | T14: =IF(OR(P14="",S14=""),"",Q14*S14) -> 0 | U14: =IF(T14="","",T14-Q14*R14) -> 0 | V14: =IF(T14="","",T14/$O$7) -> 0
F15: =IF(OR(D15="",E15=""),"",D15*E15) -> 0 | G15: =IF(F15="","",F15*$C$5) -> 0 | H15: =IF(F15="","",IF(C15="Compra",-(F15+G15),F15-G15)) -> 0 | I15: =IF(D15="","",IF(C15="Compra",D15,-D15)) -> 0 | P15: ENERGIA | Q15: =IF(P15="","",SUMIF($B$11:$B$110,P15,$I$11:$I$110)) -> 0 | R15: =IF(P15="","",IFERROR(SUMIFS($F$11:$F$110,$B$11:$B$110,P15,$C$11:$C$110,"Compra")/SUMIFS($D$11:$D$110,$B$11:$B$110,P15,$C$11:$C$110,"Compra"),0)) -> 0 | S15: 101 | T15: =IF(OR(P15="",S15=""),"",Q15*S15) -> 0 | U15: =IF(T15="","",T15-Q15*R15) -> 0 | V15: =IF(T15="","",T15/$O$7) -> 0
F16: =IF(OR(D16="",E16=""),"",D16*E16) -> 0 | G16: =IF(F16="","",F16*$C$5) -> 0 | H16: =IF(F16="","",IF(C16="Compra",-(F16+G16),F16-G16)) -> 0 | I16: =IF(D16="","",IF(C16="Compra",D16,-D16)) -> 0 | Q16: =IF(P16="","",SUMIF($B$11:$B$110,P16,$I$11:$I$110)) -> 0 | R16: =IF(P16="","",IFERROR(SUMIFS($F$11:$F$110,$B$11:$B$110,P16,$C$11:$C$110,"Compra")/SUMIFS($D$11:$D$110,$B$11:$B$110,P16,$C$11:$C$110,"Compra"),0)) -> 0 | T16: =IF(OR(P16="",S16=""),"",Q16*S16) -> 0 | U16: =IF(T16="","",T16-Q16*R16) -> 0 | V16: =IF(T16="","",T16/$O$7) -> 0
F17: =IF(OR(D17="",E17=""),"",D17*E17) -> 0 | G17: =IF(F17="","",F17*$C$5) -> 0 | H17: =IF(F17="","",IF(C17="Compra",-(F17+G17),F17-G17)) -> 0 | I17: =IF(D17="","",IF(C17="Compra",D17,-D17)) -> 0 | Q17: =IF(P17="","",SUMIF($B$11:$B$110,P17,$I$11:$I$110)) -> 0 | R17: =IF(P17="","",IFERROR(SUMIFS($F$11:$F$110,$B$11:$B$110,P17,$C$11:$C$110,"Compra")/SUMIFS($D$11:$D$110,$B$11:$B$110,P17,$C$11:$C$110,"Compra"),0)) -> 0 | T17: =IF(OR(P17="",S17=""),"",Q17*S17) -> 0 | U17: =IF(T17="","",T17-Q17*R17) -> 0 | V17: =IF(T17="","",T17/$O$7) -> 0
F18: =IF(OR(D18="",E18=""),"",D18*E18) -> 0 | G18: =IF(F18="","",F18*$C$5) -> 0 | H18: =IF(F18="","",IF(C18="Compra",-(F18+G18),F18-G18)) -> 0 | I18: =IF(D18="","",IF(C18="Compra",D18,-D18)) -> 0 | Q18: =IF(P18="","",SUMIF($B$11:$B$110,P18,$I$11:$I$110)) -> 0 | R18: =IF(P18="","",IFERROR(SUMIFS($F$11:$F$110,$B$11:$B$110,P18,$C$11:$C$110,"Compra")/SUMIFS($D$11:$D$110,$B$11:$B$110,P18,$C$11:$C$110,"Compra"),0)) -> 0 | T18: =IF(OR(P18="",S18=""),"",Q18*S18) -> 0 | U18: =IF(T18="","",T18-Q18*R18) -> 0 | V18: =IF(T18="","",T18/$O$7) -> 0
F19: =IF(OR(D19="",E19=""),"",D19*E19) -> 0 | G19: =IF(F19="","",F19*$C$5) -> 0 | H19: =IF(F19="","",IF(C19="Compra",-(F19+G19),F19-G19)) -> 0 | I19: =IF(D19="","",IF(C19="Compra",D19,-D19)) -> 0 | Q19: =IF(P19="","",SUMIF($B$11:$B$110,P19,$I$11:$I$110)) -> 0 | R19: =IF(P19="","",IFERROR(SUMIFS($F$11:$F$110,$B$11:$B$110,P19,$C$11:$C$110,"Compra")/SUMIFS($D$11:$D$110,$B$11:$B$110,P19,$C$11:$C$110,"Compra"),0)) -> 0 | T19: =IF(OR(P19="",S19=""),"",Q19*S19) -> 0 | U19: =IF(T19="","",T19-Q19*R19) -> 0 | V19: =IF(T19="","",T19/$O$7) -> 0
F20: =IF(OR(D20="",E20=""),"",D20*E20) -> 0 | G20: =IF(F20="","",F20*$C$5) -> 0 | H20: =IF(F20="","",IF(C20="Compra",-(F20+G20),F20-G20)) -> 0 | I20: =IF(D20="","",IF(C20="Compra",D20,-D20)) -> 0 | Q20: =IF(P20="","",SUMIF($B$11:$B$110,P20,$I$11:$I$110)) -> 0 | R20: =IF(P20="","",IFERROR(SUMIFS($F$11:$F$110,$B$11:$B$110,P20,$C$11:$C$110,"Compra")/SUMIFS($D$11:$D$110,$B$11:$B$110,P20,$C$11:$C$110,"Compra"),0)) -> 0 | T20: =IF(OR(P20="",S20=""),"",Q20*S20) -> 0 | U20: =IF(T20="","",T20-Q20*R20) -> 0 | V20: =IF(T20="","",T20/$O$7) -> 0
F21: =IF(OR(D21="",E21=""),"",D21*E21) -> 0 | G21: =IF(F21="","",F21*$C$5) -> 0 | H21: =IF(F21="","",IF(C21="Compra",-(F21+G21),F21-G21)) -> 0 | I21: =IF(D21="","",IF(C21="Compra",D21,-D21)) -> 0 | Q21: =IF(P21="","",SUMIF($B$11:$B$110,P21,$I$11:$I$110)) -> 0 | R21: =IF(P21="","",IFERROR(SUMIFS($F$11:$F$110,$B$11:$B$110,P21,$C$11:$C$110,"Compra")/SUMIFS($D$11:$D$110,$B$11:$B$110,P21,$C$11:$C$110,"Compra"),0)) -> 0 | T21: =IF(OR(P21="",S21=""),"",Q21*S21) -> 0 | U21: =IF(T21="","",T21-Q21*R21) -> 0 | V21: =IF(T21="","",T21/$O$7) -> 0
F22: =IF(OR(D22="",E22=""),"",D22*E22) -> 0 | G22: =IF(F22="","",F22*$C$5) -> 0 | H22: =IF(F22="","",IF(C22="Compra",-(F22+G22),F22-G22)) -> 0 | I22: =IF(D22="","",IF(C22="Compra",D22,-D22)) -> 0 | Q22: =IF(P22="","",SUMIF($B$11:$B$110,P22,$I$11:$I$110)) -> 0 | R22: =IF(P22="","",IFERROR(SUMIFS($F$11:$F$110,$B$11:$B$110,P22,$C$11:$C$110,"Compra")/SUMIFS($D$11:$D$110,$B$11:$B$110,P22,$C$11:$C$110,"Compra"),0)) -> 0 | T22: =IF(OR(P22="",S22=""),"",Q22*S22) -> 0 | U22: =IF(T22="","",T22-Q22*R22) -> 0 | V22: =IF(T22="","",T22/$O$7) -> 0
F23: =IF(OR(D23="",E23=""),"",D23*E23) -> 0 | G23: =IF(F23="","",F23*$C$5) -> 0 | H23: =IF(F23="","",IF(C23="Compra",-(F23+G23),F23-G23)) -> 0 | I23: =IF(D23="","",IF(C23="Compra",D23,-D23)) -> 0 | Q23: =IF(P23="","",SUMIF($B$11:$B$110,P23,$I$11:$I$110)) -> 0 | R23: =IF(P23="","",IFERROR(SUMIFS($F$11:$F$110,$B$11:$B$110,P23,$C$11:$C$110,"Compra")/SUMIFS($D$11:$D$110,$B$11:$B$110,P23,$C$11:$C$110,"Compra"),0)) -> 0 | T23: =IF(OR(P23="",S23=""),"",Q23*S23) -> 0 | U23: =IF(T23="","",T23-Q23*R23) -> 0 | V23: =IF(T23="","",T23/$O$7) -> 0
F24: =IF(OR(D24="",E24=""),"",D24*E24) -> 0 | G24: =IF(F24="","",F24*$C$5) -> 0 | H24: =IF(F24="","",IF(C24="Compra",-(F24+G24),F24-G24)) -> 0 | I24: =IF(D24="","",IF(C24="Compra",D24,-D24)) -> 0 | Q24: =IF(P24="","",SUMIF($B$11:$B$110,P24,$I$11:$I$110)) -> 0 | R24: =IF(P24="","",IFERROR(SUMIFS($F$11:$F$110,$B$11:$B$110,P24,$C$11:$C$110,"Compra")/SUMIFS($D$11:$D$110,$B$11:$B$110,P24,$C$11:$C$110,"Compra"),0)) -> 0 | T24: =IF(OR(P24="",S24=""),"",Q24*S24) -> 0 | U24: =IF(T24="","",T24-Q24*R24) -> 0 | V24: =IF(T24="","",T24/$O$7) -> 0
F25: =IF(OR(D25="",E25=""),"",D25*E25) -> 0 | G25: =IF(F25="","",F25*$C$5) -> 0 | H25: =IF(F25="","",IF(C25="Compra",-(F25+G25),F25-G25)) -> 0 | I25: =IF(D25="","",IF(C25="Compra",D25,-D25)) -> 0 | Q25: =IF(P25="","",SUMIF($B$11:$B$110,P25,$I$11:$I$110)) -> 0 | R25: =IF(P25="","",IFERROR(SUMIFS($F$11:$F$110,$B$11:$B$110,P25,$C$11:$C$110,"Compra")/SUMIFS($D$11:$D$110,$B$11:$B$110,P25,$C$11:$C$110,"Compra"),0)) -> 0 | T25: =IF(OR(P25="",S25=""),"",Q25*S25) -> 0 | U25: =IF(T25="","",T25-Q25*R25) -> 0 | V25: =IF(T25="","",T25/$O$7) -> 0
F26: =IF(OR(D26="",E26=""),"",D26*E26) -> 0 | G26: =IF(F26="","",F26*$C$5) -> 0 | H26: =IF(F26="","",IF(C26="Compra",-(F26+G26),F26-G26)) -> 0 | I26: =IF(D26="","",IF(C26="Compra",D26,-D26)) -> 0 | Q26: =IF(P26="","",SUMIF($B$11:$B$110,P26,$I$11:$I$110)) -> 0 | R26: =IF(P26="","",IFERROR(SUMIFS($F$11:$F$110,$B$11:$B$110,P26,$C$11:$C$110,"Compra")/SUMIFS($D$11:$D$110,$B$11:$B$110,P26,$C$11:$C$110,"Compra"),0)) -> 0 | T26: =IF(OR(P26="",S26=""),"",Q26*S26) -> 0 | U26: =IF(T26="","",T26-Q26*R26) -> 0 | V26: =IF(T26="","",T26/$O$7) -> 0
F27: =IF(OR(D27="",E27=""),"",D27*E27) -> 0 | G27: =IF(F27="","",F27*$C$5) -> 0 | H27: =IF(F27="","",IF(C27="Compra",-(F27+G27),F27-G27)) -> 0 | I27: =IF(D27="","",IF(C27="Compra",D27,-D27)) -> 0 | Q27: =IF(P27="","",SUMIF($B$11:$B$110,P27,$I$11:$I$110)) -> 0 | R27: =IF(P27="","",IFERROR(SUMIFS($F$11:$F$110,$B$11:$B$110,P27,$C$11:$C$110,"Compra")/SUMIFS($D$11:$D$110,$B$11:$B$110,P27,$C$11:$C$110,"Compra"),0)) -> 0 | T27: =IF(OR(P27="",S27=""),"",Q27*S27) -> 0 | U27: =IF(T27="","",T27-Q27*R27) -> 0 | V27: =IF(T27="","",T27/$O$7) -> 0
F28: =IF(OR(D28="",E28=""),"",D28*E28) -> 0 | G28: =IF(F28="","",F28*$C$5) -> 0 | H28: =IF(F28="","",IF(C28="Compra",-(F28+G28),F28-G28)) -> 0 | I28: =IF(D28="","",IF(C28="Compra",D28,-D28)) -> 0
F29: =IF(OR(D29="",E29=""),"",D29*E29) -> 0 | G29: =IF(F29="","",F29*$C$5) -> 0 | H29: =IF(F29="","",IF(C29="Compra",-(F29+G29),F29-G29)) -> 0 | I29: =IF(D29="","",IF(C29="Compra",D29,-D29)) -> 0 | P29: Precio actual: copialo del simulador cada dia. El P&L no realizado usa el precio medio de compra.
F30: =IF(OR(D30="",E30=""),"",D30*E30) -> 0 | G30: =IF(F30="","",F30*$C$5) -> 0 | H30: =IF(F30="","",IF(C30="Compra",-(F30+G30),F30-G30)) -> 0 | I30: =IF(D30="","",IF(C30="Compra",D30,-D30)) -> 0
F31: =IF(OR(D31="",E31=""),"",D31*E31) -> 0 | G31: =IF(F31="","",F31*$C$5) -> 0 | H31: =IF(F31="","",IF(C31="Compra",-(F31+G31),F31-G31)) -> 0 | I31: =IF(D31="","",IF(C31="Compra",D31,-D31)) -> 0
F32: =IF(OR(D32="",E32=""),"",D32*E32) -> 0 | G32: =IF(F32="","",F32*$C$5) -> 0 | H32: =IF(F32="","",IF(C32="Compra",-(F32+G32),F32-G32)) -> 0 | I32: =IF(D32="","",IF(C32="Compra",D32,-D32)) -> 0
F33: =IF(OR(D33="",E33=""),"",D33*E33) -> 0 | G33: =IF(F33="","",F33*$C$5) -> 0 | H33: =IF(F33="","",IF(C33="Compra",-(F33+G33),F33-G33)) -> 0 | I33: =IF(D33="","",IF(C33="Compra",D33,-D33)) -> 0
F34: =IF(OR(D34="",E34=""),"",D34*E34) -> 0 | G34: =IF(F34="","",F34*$C$5) -> 0 | H34: =IF(F34="","",IF(C34="Compra",-(F34+G34),F34-G34)) -> 0 | I34: =IF(D34="","",IF(C34="Compra",D34,-D34)) -> 0
F35: =IF(OR(D35="",E35=""),"",D35*E35) -> 0 | G35: =IF(F35="","",F35*$C$5) -> 0 | H35: =IF(F35="","",IF(C35="Compra",-(F35+G35),F35-G35)) -> 0 | I35: =IF(D35="","",IF(C35="Compra",D35,-D35)) -> 0
F36: =IF(OR(D36="",E36=""),"",D36*E36) -> 0 | G36: =IF(F36="","",F36*$C$5) -> 0 | H36: =IF(F36="","",IF(C36="Compra",-(F36+G36),F36-G36)) -> 0 | I36: =IF(D36="","",IF(C36="Compra",D36,-D36)) -> 0
F37: =IF(OR(D37="",E37=""),"",D37*E37) -> 0 | G37: =IF(F37="","",F37*$C$5) -> 0 | H37: =IF(F37="","",IF(C37="Compra",-(F37+G37),F37-G37)) -> 0 | I37: =IF(D37="","",IF(C37="Compra",D37,-D37)) -> 0
F38: =IF(OR(D38="",E38=""),"",D38*E38) -> 0 | G38: =IF(F38="","",F38*$C$5) -> 0 | H38: =IF(F38="","",IF(C38="Compra",-(F38+G38),F38-G38)) -> 0 | I38: =IF(D38="","",IF(C38="Compra",D38,-D38)) -> 0
F39: =IF(OR(D39="",E39=""),"",D39*E39) -> 0 | G39: =IF(F39="","",F39*$C$5) -> 0 | H39: =IF(F39="","",IF(C39="Compra",-(F39+G39),F39-G39)) -> 0 | I39: =IF(D39="","",IF(C39="Compra",D39,-D39)) -> 0
F40: =IF(OR(D40="",E40=""),"",D40*E40) -> 0 | G40: =IF(F40="","",F40*$C$5) -> 0 | H40: =IF(F40="","",IF(C40="Compra",-(F40+G40),F40-G40)) -> 0 | I40: =IF(D40="","",IF(C40="Compra",D40,-D40)) -> 0
F41: =IF(OR(D41="",E41=""),"",D41*E41) -> 0 | G41: =IF(F41="","",F41*$C$5) -> 0 | H41: =IF(F41="","",IF(C41="Compra",-(F41+G41),F41-G41)) -> 0 | I41: =IF(D41="","",IF(C41="Compra",D41,-D41)) -> 0
... F110: =IF(OR(D110="",E110=""),"",D110*E110) -> 0 | G110: =IF(F110="","",F110*$C$5) -> 0 | H110: =IF(F110="","",IF(C110="Compra",-(F110+G110),F110-G110)) -> 0 | I110: =IF(D110="","",IF(C110="Compra",D110,-D110)) -> 0

Sheet 10_Torneo
A1: Economia del torneo: costos y probabilidades
A3: A) COSTO DE ROTAR LA CARTERA
A4: Comision por operacion | B4: ='9_Simulador_CCI'!C5 -> 0
A5: Alza minima para empatar una compra+venta | B5: =(1+B4)/(1-B4)-1 -> 0 | C5: Con 0,5% por lado necesitas ~1,005% de alza solo para no perder.
A7: N de rotaciones completas de TODA la cartera | B7: Costo acumulado | C7: Comentario
A8: 1 | B8: =1-((1-$B$4)/(1+$B$4))^A8 -> 0 | C8: Un "day trader" que rota todo 20 veces pierde ~18% solo en comisiones.
A9: 2 | B9: =1-((1-$B$4)/(1+$B$4))^A9 -> 0
A10: 4 | B10: =1-((1-$B$4)/(1+$B$4))^A10 -> 0
A11: 6 | B11: =1-((1-$B$4)/(1+$B$4))^A11 -> 0
A12: 8 | B12: =1-((1-$B$4)/(1+$B$4))^A12 -> 0
A13: 10 | B13: =1-((1-$B$4)/(1+$B$4))^A13 -> 0
A14: 15 | B14: =1-((1-$B$4)/(1+$B$4))^A14 -> 0
A15: 20 | B15: =1-((1-$B$4)/(1+$B$4))^A15 -> 0
A17: B) PROBABILIDAD DE SUPERAR UNA META (modelo lognormal)
A18: Duracion del concurso (semanas) | B18: 8
A19: Retorno esperado anual de la cartera (mu) | B19: 0.1
A20: Supuesto clave | B20: Sin habilidad especial: el retorno es aleatorio alrededor de mu
A22: Volatilidad anual de la cartera | B22: P(R > 5%) | C22: P(R > 10%) | D22: P(R > 20%) | E22: P(R > 30%) | F22: P(R > 50%) | G22: P(R < -10%)
A23: 0.1 | B23: =1-_xlfn.NORM.DIST(LN(1+0.05),($B$19-A23^2/2)*$B$18/52,A23*SQRT($B$18/52),TRUE) -> 0 | C23: =1-_xlfn.NORM.DIST(LN(1+0.1),($B$19-A23^2/2)*$B$18/52,A23*SQRT($B$18/52),TRUE) -> 0 | D23: =1-_xlfn.NORM.DIST(LN(1+0.2),($B$19-A23^2/2)*$B$18/52,A23*SQRT($B$18/52),TRUE) -> 0 | E23: =1-_xlfn.NORM.DIST(LN(1+0.3),($B$19-A23^2/2)*$B$18/52,A23*SQRT($B$18/52),TRUE) -> 0 | F23: =1-_xlfn.NORM.DIST(LN(1+0.5),($B$19-A23^2/2)*$B$18/52,A23*SQRT($B$18/52),TRUE) -> 0 | G23: =_xlfn.NORM.DIST(LN(0.9),($B$19-A23^2/2)*$B$18/52,A23*SQRT($B$18/52),TRUE) -> 0
A24: 0.15 | B24: =1-_xlfn.NORM.DIST(LN(1+0.05),($B$19-A24^2/2)*$B$18/52,A24*SQRT($B$18/52),TRUE) -> 0 | C24: =1-_xlfn.NORM.DIST(LN(1+0.1),($B$19-A24^2/2)*$B$18/52,A24*SQRT($B$18/52),TRUE) -> 0 | D24: =1-_xlfn.NORM.DIST(LN(1+0.2),($B$19-A24^2/2)*$B$18/52,A24*SQRT($B$18/52),TRUE) -> 0 | E24: =1-_xlfn.NORM.DIST(LN(1+0.3),($B$19-A24^2/2)*$B$18/52,A24*SQRT($B$18/52),TRUE) -> 0 | F24: =1-_xlfn.NORM.DIST(LN(1+0.5),($B$19-A24^2/2)*$B$18/52,A24*SQRT($B$18/52),TRUE) -> 0 | G24: =_xlfn.NORM.DIST(LN(0.9),($B$19-A24^2/2)*$B$18/52,A24*SQRT($B$18/52),TRUE) -> 0
A25: 0.2 | B25: =1-_xlfn.NORM.DIST(LN(1+0.05),($B$19-A25^2/2)*$B$18/52,A25*SQRT($B$18/52),TRUE) -> 0 | C25: =1-_xlfn.NORM.DIST(LN(1+0.1),($B$19-A25^2/2)*$B$18/52,A25*SQRT($B$18/52),TRUE) -> 0 | D25: =1-_xlfn.NORM.DIST(LN(1+0.2),($B$19-A25^2/2)*$B$18/52,A25*SQRT($B$18/52),TRUE) -> 0 | E25: =1-_xlfn.NORM.DIST(LN(1+0.3),($B$19-A25^2/2)*$B$18/52,A25*SQRT($B$18/52),TRUE) -> 0 | F25: =1-_xlfn.NORM.DIST(LN(1+0.5),($B$19-A25^2/2)*$B$18/52,A25*SQRT($B$18/52),TRUE) -> 0 | G25: =_xlfn.NORM.DIST(LN(0.9),($B$19-A25^2/2)*$B$18/52,A25*SQRT($B$18/52),TRUE) -> 0
A26: 0.3 | B26: =1-_xlfn.NORM.DIST(LN(1+0.05),($B$19-A26^2/2)*$B$18/52,A26*SQRT($B$18/52),TRUE) -> 0 | C26: =1-_xlfn.NORM.DIST(LN(1+0.1),($B$19-A26^2/2)*$B$18/52,A26*SQRT($B$18/52),TRUE) -> 0 | D26: =1-_xlfn.NORM.DIST(LN(1+0.2),($B$19-A26^2/2)*$B$18/52,A26*SQRT($B$18/52),TRUE) -> 0 | E26: =1-_xlfn.NORM.DIST(LN(1+0.3),($B$19-A26^2/2)*$B$18/52,A26*SQRT($B$18/52),TRUE) -> 0 | F26: =1-_xlfn.NORM.DIST(LN(1+0.5),($B$19-A26^2/2)*$B$18/52,A26*SQRT($B$18/52),TRUE) -> 0 | G26: =_xlfn.NORM.DIST(LN(0.9),($B$19-A26^2/2)*$B$18/52,A26*SQRT($B$18/52),TRUE) -> 0
A27: 0.4 | B27: =1-_xlfn.NORM.DIST(LN(1+0.05),($B$19-A27^2/2)*$B$18/52,A27*SQRT($B$18/52),TRUE) -> 0 | C27: =1-_xlfn.NORM.DIST(LN(1+0.1),($B$19-A27^2/2)*$B$18/52,A27*SQRT($B$18/52),TRUE) -> 0 | D27: =1-_xlfn.NORM.DIST(LN(1+0.2),($B$19-A27^2/2)*$B$18/52,A27*SQRT($B$18/52),TRUE) -> 0 | E27: =1-_xlfn.NORM.DIST(LN(1+0.3),($B$19-A27^2/2)*$B$18/52,A27*SQRT($B$18/52),TRUE) -> 0 | F27: =1-_xlfn.NORM.DIST(LN(1+0.5),($B$19-A27^2/2)*$B$18/52,A27*SQRT($B$18/52),TRUE) -> 0 | G27: =_xlfn.NORM.DIST(LN(0.9),($B$19-A27^2/2)*$B$18/52,A27*SQRT($B$18/52),TRUE) -> 0
A28: 0.5 | B28: =1-_xlfn.NORM.DIST(LN(1+0.05),($B$19-A28^2/2)*$B$18/52,A28*SQRT($B$18/52),TRUE) -> 0 | C28: =1-_xlfn.NORM.DIST(LN(1+0.1),($B$19-A28^2/2)*$B$18/52,A28*SQRT($B$18/52),TRUE) -> 0 | D28: =1-_xlfn.NORM.DIST(LN(1+0.2),($B$19-A28^2/2)*$B$18/52,A28*SQRT($B$18/52),TRUE) -> 0 | E28: =1-_xlfn.NORM.DIST(LN(1+0.3),($B$19-A28^2/2)*$B$18/52,A28*SQRT($B$18/52),TRUE) -> 0 | F28: =1-_xlfn.NORM.DIST(LN(1+0.5),($B$19-A28^2/2)*$B$18/52,A28*SQRT($B$18/52),TRUE) -> 0 | G28: =_xlfn.NORM.DIST(LN(0.9),($B$19-A28^2/2)*$B$18/52,A28*SQRT($B$18/52),TRUE) -> 0
A29: 0.6 | B29: =1-_xlfn.NORM.DIST(LN(1+0.05),($B$19-A29^2/2)*$B$18/52,A29*SQRT($B$18/52),TRUE) -> 0 | C29: =1-_xlfn.NORM.DIST(LN(1+0.1),($B$19-A29^2/2)*$B$18/52,A29*SQRT($B$18/52),TRUE) -> 0 | D29: =1-_xlfn.NORM.DIST(LN(1+0.2),($B$19-A29^2/2)*$B$18/52,A29*SQRT($B$18/52),TRUE) -> 0 | E29: =1-_xlfn.NORM.DIST(LN(1+0.3),($B$19-A29^2/2)*$B$18/52,A29*SQRT($B$18/52),TRUE) -> 0 | F29: =1-_xlfn.NORM.DIST(LN(1+0.5),($B$19-A29^2/2)*$B$18/52,A29*SQRT($B$18/52),TRUE) -> 0 | G29: =_xlfn.NORM.DIST(LN(0.9),($B$19-A29^2/2)*$B$18/52,A29*SQRT($B$18/52),TRUE) -> 0
A30: 0.8 | B30: =1-_xlfn.NORM.DIST(LN(1+0.05),($B$19-A30^2/2)*$B$18/52,A30*SQRT($B$18/52),TRUE) -> 0 | C30: =1-_xlfn.NORM.DIST(LN(1+0.1),($B$19-A30^2/2)*$B$18/52,A30*SQRT($B$18/52),TRUE) -> 0 | D30: =1-_xlfn.NORM.DIST(LN(1+0.2),($B$19-A30^2/2)*$B$18/52,A30*SQRT($B$18/52),TRUE) -> 0 | E30: =1-_xlfn.NORM.DIST(LN(1+0.3),($B$19-A30^2/2)*$B$18/52,A30*SQRT($B$18/52),TRUE) -> 0 | F30: =1-_xlfn.NORM.DIST(LN(1+0.5),($B$19-A30^2/2)*$B$18/52,A30*SQRT($B$18/52),TRUE) -> 0 | G30: =_xlfn.NORM.DIST(LN(0.9),($B$19-A30^2/2)*$B$18/52,A30*SQRT($B$18/52),TRUE) -> 0
A33: LECCION: los ganadores historicos del CCI universitario rentaron 30%-65% en ~8 semanas. Con volatilidad del IPSA (~15-20%) la probabilidad de lograrlo es casi cero.
A34: Para aspirar al primer lugar entre miles hay que aceptar mas volatilidad (concentracion, betas altas). Pero la misma tabla muestra que sube la probabilidad de perder mucho.
A35: La habilidad (buen analisis) desplaza mu hacia arriba; la volatilidad abre el abanico. El objetivo es combinar ambas sin arriesgar la "ruina" temprana.
A36: Supuesto simplificado (retornos lognormales, sin saltos). Sirve para intuicion, no como prediccion.

Sheet 11_Screener
A1: Screener fundamental (plantilla)
A2: Datos de ejemplo FICTICIOS. Llena con datos reales de los estados financieros (CMF) y precios del dia.
A4: Empresa | B4: Sector | C4: Precio | D4: UPA (12m) | E4: VL por accion | F4: Dividendo por accion | G4: EBITDA (MM$) | H4: Deuda neta (MM$) | I4: N acciones (MM) | J4: Var. precio 3M | K4: P/U | L4: P/VL | M4: Div. yield | N4: Cap. bursatil (MM$) | O4: EV (MM$) | P4: EV/EBITDA | Q4: ROE | R4: Rank P/U | S4: Rank DivY | T4: Rank Momentum | U4: Rank ROE | V4: PUNTAJE | W4: POSICION
A5: BANCO | B5: Financiero | C5: 5400 | D5: 520 | E5: 3600 | F5: 300 | G5: 0 | H5: 0 | I5: 1000 | J5: 0.06 | K5: =IFERROR(C5/D5,"") -> 0 | L5: =IFERROR(C5/E5,"") -> 0 | M5: =IFERROR(F5/C5,"") -> 0 | N5: =C5*I5 -> 0 | O5: =N5+H5 -> 0 | P5: =IF(G5=0,"n/a",O5/G5) -> 0 | Q5: =IFERROR(D5/E5,"") -> 0 | R5: =RANK(K5,$K$5:$K$12,1) -> 0 | S5: =RANK(M5,$M$5:$M$12,0) -> 0 | T5: =RANK(J5,$J$5:$J$12,0) -> 0 | U5: =RANK(Q5,$Q$5:$Q$12,0) -> 0 | V5: =AVERAGE(R5:U5) -> 0 | W5: =RANK(V5,$V$5:$V$12,1) -> 0
A6: RETAIL | B6: Consumo | C6: 2150 | D6: 140 | E6: 2400 | F6: 45 | G6: 900 | H6: 2500 | I6: 2500 | J6: 0.12 | K6: =IFERROR(C6/D6,"") -> 0 | L6: =IFERROR(C6/E6,"") -> 0 | M6: =IFERROR(F6/C6,"") -> 0 | N6: =C6*I6 -> 0 | O6: =N6+H6 -> 0 | P6: =IF(G6=0,"n/a",O6/G6) -> 0 | Q6: =IFERROR(D6/E6,"") -> 0 | R6: =RANK(K6,$K$5:$K$12,1) -> 0 | S6: =RANK(M6,$M$5:$M$12,0) -> 0 | T6: =RANK(J6,$J$5:$J$12,0) -> 0 | U6: =RANK(Q6,$Q$5:$Q$12,0) -> 0 | V6: =AVERAGE(R6:U6) -> 0 | W6: =RANK(V6,$V$5:$V$12,1) -> 0
A7: MINERA | B7: Materiales | C7: 43000 | D7: 2600 | E7: 17000 | F7: 1100 | G7: 3200 | H7: 1500 | I7: 280 | J7: 0.18 | K7: =IFERROR(C7/D7,"") -> 0 | L7: =IFERROR(C7/E7,"") -> 0 | M7: =IFERROR(F7/C7,"") -> 0 | N7: =C7*I7 -> 0 | O7: =N7+H7 -> 0 | P7: =IF(G7=0,"n/a",O7/G7) -> 0 | Q7: =IFERROR(D7/E7,"") -> 0 | R7: =RANK(K7,$K$5:$K$12,1) -> 0 | S7: =RANK(M7,$M$5:$M$12,0) -> 0 | T7: =RANK(J7,$J$5:$J$12,0) -> 0 | U7: =RANK(Q7,$Q$5:$Q$12,0) -> 0 | V7: =AVERAGE(R7:U7) -> 0 | W7: =RANK(V7,$V$5:$V$12,1) -> 0
A8: ENERGIA | B8: Utilities | C8: 98 | D8: 7.5 | E8: 70 | F8: 6 | G8: 1800 | H8: 4000 | I8: 69000 | J8: 0.02 | K8: =IFERROR(C8/D8,"") -> 0 | L8: =IFERROR(C8/E8,"") -> 0 | M8: =IFERROR(F8/C8,"") -> 0 | N8: =C8*I8 -> 0 | O8: =N8+H8 -> 0 | P8: =IF(G8=0,"n/a",O8/G8) -> 0 | Q8: =IFERROR(D8/E8,"") -> 0 | R8: =RANK(K8,$K$5:$K$12,1) -> 0 | S8: =RANK(M8,$M$5:$M$12,0) -> 0 | T8: =RANK(J8,$J$5:$J$12,0) -> 0 | U8: =RANK(Q8,$Q$5:$Q$12,0) -> 0 | V8: =AVERAGE(R8:U8) -> 0 | W8: =RANK(V8,$V$5:$V$12,1) -> 0
A9: CONSUMO | B9: Consumo basico | C9: 6800 | D9: 410 | E9: 3900 | F9: 240 | G9: 700 | H9: 900 | I9: 370 | J9: -0.03 | K9: =IFERROR(C9/D9,"") -> 0 | L9: =IFERROR(C9/E9,"") -> 0 | M9: =IFERROR(F9/C9,"") -> 0 | N9: =C9*I9 -> 0 | O9: =N9+H9 -> 0 | P9: =IF(G9=0,"n/a",O9/G9) -> 0 | Q9: =IFERROR(D9/E9,"") -> 0 | R9: =RANK(K9,$K$5:$K$12,1) -> 0 | S9: =RANK(M9,$M$5:$M$12,0) -> 0 | T9: =RANK(J9,$J$5:$J$12,0) -> 0 | U9: =RANK(Q9,$Q$5:$Q$12,0) -> 0 | V9: =AVERAGE(R9:U9) -> 0 | W9: =RANK(V9,$V$5:$V$12,1) -> 0
A10: FORESTAL | B10: Materiales | C10: 1650 | D10: 80 | E10: 2100 | F10: 30 | G10: 1400 | H10: 3500 | I10: 2500 | J10: -0.08 | K10: =IFERROR(C10/D10,"") -> 0 | L10: =IFERROR(C10/E10,"") -> 0 | M10: =IFERROR(F10/C10,"") -> 0 | N10: =C10*I10 -> 0 | O10: =N10+H10 -> 0 | P10: =IF(G10=0,"n/a",O10/G10) -> 0 | Q10: =IFERROR(D10/E10,"") -> 0 | R10: =RANK(K10,$K$5:$K$12,1) -> 0 | S10: =RANK(M10,$M$5:$M$12,0) -> 0 | T10: =RANK(J10,$J$5:$J$12,0) -> 0 | U10: =RANK(Q10,$Q$5:$Q$12,0) -> 0 | V10: =AVERAGE(R10:U10) -> 0 | W10: =RANK(V10,$V$5:$V$12,1) -> 0
A11: AEROLINEA | B11: Transporte | C11: 18 | D11: 1.9 | E11: 9 | F11: 0.2 | G11: 2500 | H11: 6000 | I11: 600000 | J11: 0.25 | K11: =IFERROR(C11/D11,"") -> 0 | L11: =IFERROR(C11/E11,"") -> 0 | M11: =IFERROR(F11/C11,"") -> 0 | N11: =C11*I11 -> 0 | O11: =N11+H11 -> 0 | P11: =IF(G11=0,"n/a",O11/G11) -> 0 | Q11: =IFERROR(D11/E11,"") -> 0 | R11: =RANK(K11,$K$5:$K$12,1) -> 0 | S11: =RANK(M11,$M$5:$M$12,0) -> 0 | T11: =RANK(J11,$J$5:$J$12,0) -> 0 | U11: =RANK(Q11,$Q$5:$Q$12,0) -> 0 | V11: =AVERAGE(R11:U11) -> 0 | W11: =RANK(V11,$V$5:$V$12,1) -> 0
A12: TELECOM | B12: Comunicaciones | C12: 3100 | D12: 150 | E12: 2800 | F12: 120 | G12: 600 | H12: 1300 | I12: 300 | J12: 0.01 | K12: =IFERROR(C12/D12,"") -> 0 | L12: =IFERROR(C12/E12,"") -> 0 | M12: =IFERROR(F12/C12,"") -> 0 | N12: =C12*I12 -> 0 | O12: =N12+H12 -> 0 | P12: =IF(G12=0,"n/a",O12/G12) -> 0 | Q12: =IFERROR(D12/E12,"") -> 0 | R12: =RANK(K12,$K$5:$K$12,1) -> 0 | S12: =RANK(M12,$M$5:$M$12,0) -> 0 | T12: =RANK(J12,$J$5:$J$12,0) -> 0 | U12: =RANK(Q12,$Q$5:$Q$12,0) -> 0 | V12: =AVERAGE(R12:U12) -> 0 | W12: =RANK(V12,$V$5:$V$12,1) -> 0
A15: Notas:
A16: P/U bajo y P/VL bajo = "barata" (value). P/VL = 1/BME de tu tesina: el BME alto se asocia a menos opciones de crecimiento.
A17: EV/EBITDA no aplica a bancos (su deuda es materia prima). Para bancos usa P/U, P/VL y ROE.
A18: El puntaje promedia rankings (1 = mejor). Cambia los criterios segun tu estrategia (value, dividendos, momentum, calidad).
A19: En 8 semanas pesan mas los CATALIZADORES (resultados, dividendos, noticias) y el momentum que el valor de largo plazo.

Sheet 12_Calendario
A1: Planificador semanal del concurso
A3: Inicio oficial: | C3: 46314 | D3: Cambia por la fecha real de las bases
A6: Semana | B6: Desde | C6: Hasta | D6: Eventos macro (BCCh, IPC, Fed, cobre) | E6: Resultados / dividendos de empresas | F6: Plan de la semana | G6: Revision (que funciono / que no)
A7: S1 | B7: =$C$3+0 -> 0 | C7: =B7+4 -> 0 | D7: Ej.: Reunion de Politica Monetaria; IPC (INE, ~dia 8) | E7: Ej.: temporada de resultados 3T (fines oct - nov)
A8: S2 | B8: =$C$3+7 -> 0 | C8: =B8+4 -> 0
A9: S3 | B9: =$C$3+14 -> 0 | C9: =B9+4 -> 0
A10: S4 | B10: =$C$3+21 -> 0 | C10: =B10+4 -> 0
A11: S5 | B11: =$C$3+28 -> 0 | C11: =B11+4 -> 0
A12: S6 | B12: =$C$3+35 -> 0 | C12: =B12+4 -> 0
A13: S7 | B13: =$C$3+42 -> 0 | C13: =B13+4 -> 0
A14: S8 | B14: =$C$3+49 -> 0 | C14: =B14+4 -> 0
A15: S9 | B15: =$C$3+56 -> 0 | C15: =B15+4 -> 0
A16: Final | B16: =$C$3+63 -> 0 | C16: =B16+4 -> 0
D18: CHECKLIST ANTES DE CADA OPERACION | E18: Si / No | F18: =IF(COUNTIF(E19:E28,"Si")=10,"LISTO PARA OPERAR",IF(COUNTIF(E19:E28,"No")>0,"NO OPERAR AUN","completa el checklist")) -> 0
D19: Tengo una tesis escrita en 1-2 frases (por que subira o bajara)
D20: Se cual es el catalizador y cuando ocurre
D21: Revise noticias y hechos esenciales (CMF) de hoy
D22: El tamano de la posicion respeta mi limite por accion
D23: Calcule cuanto debe moverse para cubrir la comision (~1%)
D24: Defini precio de salida si me equivoco (stop)
D25: Defini precio objetivo / condicion de toma de ganancia
D26: No estoy operando por impulso (FOMO o recuperar perdidas)
D27: Revise la correlacion con lo que ya tengo
D28: Registre la operacion en 9_Simulador_CCI

Sheet 13_Plan_Estudio
A1: Plan de estudio: 21 dias para dominar el CCI
A3: Dia | B3: Tema | C3: Material | D3: Hecho | F3: AVANCE
A4: 1 | B4: Que es el CCI, reglas y logica de torneo | C4: Guia cap. 1-2 + Resumen Express | F4: =COUNTIF(D4:D24,"Si")/21 -> 0
A5: 2 | B5: Bolsa de Santiago, nuam, IPSA, ordenes y costos | C5: Guia cap. 3
A6: 3 | B6: Sectores del IPSA y empresas clave | C6: Guia cap. 3 + Screener
A7: 4 | B7: Macro Chile: cobre, dolar, TPM, inflacion | C7: Guia cap. 4 + Mapas (cadena macro)
A8: 5 | B8: Retorno, riesgo, anualizacion, drawdown | C8: Guia cap. 5 + hojas 2 y 8
A9: 6 | B9: Covarianza, correlacion y diversificacion | C9: Guia cap. 6 + hoja 3
A10: 7 | B10: Markowitz y frontera eficiente | C10: Guia cap. 6 + hoja 4 + Ejercicios 4-6
A11: 8 | B11: CAPM, beta, SML; repaso tesina | C11: Guia cap. 7 + hoja 6
A12: 9 | B12: Sharpe, Treynor, Jensen, info ratio | C12: Guia cap. 7 + hoja 5 + Ejercicios 7-9
A13: 10 | B13: Repaso + Quiz (bloque teoria) | C13: Quiz interactivo + Flashcards
A14: 11 | B14: Analisis fundamental: multiplos | C14: Guia cap. 8 + hoja 11
A15: 12 | B15: Estados financieros rapidos y resultados trimestrales | C15: Guia cap. 8
A16: 13 | B16: Analisis tecnico: tendencia, medias, RSI, Bollinger | C16: Guia cap. 9 + hoja 7
... A24: 21 | B24: Repaso final + Quiz completo + ajustes | C24: Quiz + Resumen Express
